Workbook
Name __gdp2: #REF!
Name __nlp2: #REF!
Name __Old3: '[1]T103'!#REF!
Name __Old4: '[1]T208'!#REF!
Name __Old5: '[1]T208'!#REF!
Name __Old6: '[1]T208'!#REF!
Name __Old7: '[1]T208'!#REF!
Name __old8: '[1]T208'!#REF!
Name _gdp2: #REF!
Name _nlp2: #REF!
Name _PMI2: #REF!
Name bad_debt: #REF!
Name bankruptcy: #REF!
Name BoxPlot: "BoxPlot"
Name Bubble: "Bubble"
Name buy_rent_gap: #REF!
Name CAB: #REF!
Name Candlestick: "Candlestick"
Name car: #REF!
Name Chart: "Chart"
Name ChartImage: "ChartImage"
Name CMTH5: '[1]T208'!#REF!
Name CMTH6: '[1]T208'!#REF!
Name CMTH7: '[1]T208'!#REF!
Name ColumnRange: "ColumnRange"
Name cpi: #REF!
Name data: #REF!
Name DATA: '[1]T5011'!#REF!
Name DATA1: '[1]T502'!#REF!
Name data2: #REF!
Name DATA2: '[1]T502'!#REF!
Name deposits: #REF!
Name Dumbbell: "Dumbbell"
Name equity: #REF!
Name fiscal: #REF!
Name fwd: #REF!
Name gdp: #REF!
Name Heatmap: "Heatmap"
Name Histogram: "Histogram"
Name insert: [2]!insert
Name interest: #REF!
Name IQ_CH: 110000
Name IQ_CQ: 5000
Name IQ_CY: 10000
Name IQ_DAILY: 500000
Name IQ_FH: 100000
Name IQ_FQ: 500
Name IQ_FY: 1000
Name IQ_LTM: 2000
Name IQ_MONTH: 15000
Name IQ_NTM: 6000
Name IQ_WEEK: 50000
Name IQ_YTD: 3000
Name labour: #REF!
Name loan: #REF!
Name loans: #REF!
Name LTD: #REF!
Name Map: "Map"
Name mci: #REF!
Name money: #REF!

Sheet Summary
F3: Table 3.5.1 : Authorized institutions (HK$ million, unless otherwise specified) | H3: 1.2 | J3: 2026-07 | K3: 2026-07 | L3: 2026-07 | M3: =TEXT(EOMONTH(DATE(LEFT(L3,4),RIGHT(L3,2),1),-1),"yyyy-mm") -> 2026-06 | N3: =M3 -> 2026-06 | O3: =N3 -> 2026-06 | P3: =TEXT(EOMONTH(DATE(LEFT(O3,4),RIGHT(O3,2),1),-1),"yyyy-mm") -> 2026-05 | Q3: =P3 -> 2026-05 | R3: =Q3 -> 2026-05 | S3: =TEXT(EOMONTH(DATE(LEFT(R3,4),RIGHT(R3,2),1),-1),"yyyy-mm") -> 2026-04 | T3: =S3 -> 2026-04 | U3: =T3 -> 2026-04 | V3: =TEXT(EOMONTH(DATE(LEFT(U3,4),RIGHT(U3,2),1),-1),"yyyy-mm") -> 2026-03 | W3: =V3 -> 2026-03 | X3: =W3 -> 2026-03 | Y3: =TEXT(EOMONTH(DATE(LEFT(X3,4),RIGHT(X3,2),1),-1),"yyyy-mm") -> 2026-02 | Z3: =Y3 -> 2026-02 | AA3: =Z3 -> 2026-02 | AB3: =TEXT(EOMONTH(DATE(LEFT(AA3,4),RIGHT(AA3,2),1),-1),"yyyy-mm") -> 2026-01 | AC3: =AB3 -> 2026-01 | AD3: =AC3 -> 2026-01 | AE3: =TEXT(EOMONTH(DATE(LEFT(AD3,4),RIGHT(AD3,2),1),-1),"yyyy-mm") -> 2025-12 | AF3: =AE3 -> 2025-12 | AG3: =AF3 -> 2025-12 | AH3: =TEXT(EOMONTH(DATE(LEFT(AG3,4),RIGHT(AG3,2),1),-1),"yyyy-mm") -> 2025-11 | AI3: =AH3 -> 2025-11 | AJ3: =AI3 -> 2025-11 | AK3: =TEXT(EOMONTH(DATE(LEFT(AJ3,4),RIGHT(AJ3,2),1),-1),"yyyy-mm") -> 2025-10 | AL3: =AK3 -> 2025-10 | AM3: =AL3 -> 2025-10 | AN3: =TEXT(EOMONTH(DATE(LEFT(AM3,4),RIGHT(AM3,2),1),-1),"yyyy-mm") -> 2025-09 | AO3: =AN3 -> 2025-09 | AP3: =AO3 -> 2025-09 | AQ3: =TEXT(EOMONTH(DATE(LEFT(AP3,4),RIGHT(AP3,2),1),-1),"yyyy-mm") -> 2025-08 | AR3: =AQ3 -> 2025-08 | AS3: =AR3 -> 2025-08 | AT3: =TEXT(EOMONTH(DATE(LEFT(AS3,4),RIGHT(AS3,2),1),-1),"yyyy-mm") -> 2025-07 | AU3: =AT3 -> 2025-07 | AV3: =AU3 -> 2025-07 | AW3: =TEXT(EOMONTH(DATE(LEFT(AV3,4),RIGHT(AV3,2),1),-1),"yyyy-mm") -> 2025-06 | AX3: =AW3 -> 2025-06 | AY3: =AX3 -> 2025-06 | AZ3: 2024-00 | BA3: =AZ3 -> 2024-00 | BB3: =BA3 -> 2024-00 | BC3: 2023-00 | BD3: =BC3 -> 2023-00 | BE3: =BD3 -> 2023-00 | BF3: 2022-00 | BG3: =BF3 -> 2022-00 | BH3: =BG3 -> 2022-00 | BI3: 2021-00 | BJ3: =BI3 -> 2021-00 | BK3: =BJ3 -> 2021-00
F4: 認可機構 (百萬港元, 另有說明者除外) | H4: 3.4.1 | J4: =J3 -> 2026-07 | K4: =K3 -> 2026-07 | L4: =L3 -> 2026-07 | M4: =M3 -> 2026-06 | N4: =N3 -> 2026-06 | O4: =O3 -> 2026-06 | P4: =P3 -> 2026-05 | Q4: =Q3 -> 2026-05 | ... AY4: =AY3 -> 2025-06 | AZ4: 2024-12 | BA4: 2024-12 | BB4: 2024-12 | BC4: 2023-12 | BD4: 2023-12 | BE4: 2023-12 | BF4: 2022-12 | BG4: 2022-12 | BH4: 2022-12 | BI4: 2021-12 | BJ4: 2021-12 | BK4: 2021-12
F9: Table : Loans and advances
F10: 貸款及墊款 | L10: =TEXT(DATE(LEFT(L3,4),RIGHT(L3,2),1),"[$-en-US]mmmm yyyy") -> July 2026 | O10: =TEXT(DATE(LEFT(O3,4),RIGHT(O3,2),1),"[$-en-US]mmmm yyyy") -> June 2026 | R10: =TEXT(DATE(LEFT(R3,4),RIGHT(R3,2),1),"[$-en-US]mmmm yyyy") -> May 2026 | U10: =TEXT(DATE(LEFT(U3,4),RIGHT(U3,2),1),"[$-en-US]mmmm yyyy") -> April 2026 | X10: =TEXT(DATE(LEFT(X3,4),RIGHT(X3,2),1),"[$-en-US]mmmm yyyy") -> March 2026 | AA10: =TEXT(DATE(LEFT(AA3,4),RIGHT(AA3,2),1),"[$-en-US]mmmm yyyy") -> February 2026 | AD10: =TEXT(DATE(LEFT(AD3,4),RIGHT(AD3,2),1),"[$-en-US]mmmm yyyy") -> January 2026 | AG10: =TEXT(DATE(LEFT(AG3,4),RIGHT(AG3,2),1),"[$-en-US]mmmm yyyy") -> December 2025 | AJ10: =TEXT(DATE(LEFT(AJ3,4),RIGHT(AJ3,2),1),"[$-en-US]mmmm yyyy") -> November 2025 | AM10: =TEXT(DATE(LEFT(AM3,4),RIGHT(AM3,2),1),"[$-en-US]mmmm yyyy") -> October 2025 | AP10: =TEXT(DATE(LEFT(AP3,4),RIGHT(AP3,2),1),"[$-en-US]mmmm yyyy") -> September 2025 | AS10: =TEXT(DATE(LEFT(AS3,4),RIGHT(AS3,2),1),"[$-en-US]mmmm yyyy") -> August 2025 | AV10: =TEXT(DATE(LEFT(AV3,4),RIGHT(AV3,2),1),"[$-en-US]mmmm yyyy") -> July 2025 | AY10: =TEXT(DATE(LEFT(AY3,4),RIGHT(AY3,2),1),"[$-en-US]mmmm yyyy") -> June 2025 | BB10: December 2024 | BE10: December 2023 | BH10: December 2022 | BK10: December 2021
F11: Table 3.5.1 : Authorized institutions (HK$ million, unless otherwise specified) | H11: Proportion% | I11: YoY% | J11: HK$ | K11: Foreign currency | L11: Total | M11: HK$ | N11: Foreign currency | O11: Total | P11: HK$ | Q11: Foreign currency | R11: Total | S11: HK$ | T11: Foreign currency | U11: Total | V11: HK$ | W11: Foreign currency | X11: Total | Y11: HK$ | Z11: Foreign currency | AA11: Total | AB11: HK$ | AC11: Foreign currency | AD11: Total | AE11: HK$ | AF11: Foreign currency | AG11: Total | AH11: HK$ | AI11: Foreign currency | AJ11: Total | AK11: HK$ | AL11: Foreign currency | AM11: Total | AN11: HK$ | AO11: Foreign currency | AP11: Total | AQ11: HK$ | AR11: Foreign currency | AS11: Total | AT11: HK$ | AU11: Foreign currency | AV11: Total | AW11: HK$ | AX11: Foreign currency | AY11: Total | AZ11: HK$ | BA11: Foreign currency | BB11: Total | BC11: HK$ | BD11: Foreign currency | BE11: Total | BF11: HK$ | BG11: Foreign currency | BH11: Total | BI11: HK$ | BJ11: Foreign currency | BK11: Total
C12: loans_total | E12: Total loan and advances | H12: =O12/$O$12 -> 1 | I12: =IFERROR(L12/AV12-1,"") -> 0.076511392 | L12: =INDEX('1.2'!$1:$104,MATCH(L$3,'1.2'!$A:$A,0),MATCH(Summary!$C12,'1.2'!$1:$1,0)) -> 10809854 | O12: =INDEX('1.2'!$1:$104,MATCH(M$3,'1.2'!$A:$A,0),MATCH(Summary!$C12,'1.2'!$1:$1,0)) -> 10787896 | R12: =INDEX('1.2'!$1:$104,MATCH(P$3,'1.2'!$A:$A,0),MATCH(Summary!$C12,'1.2'!$1:$1,0)) -> 10646152 | U12: =INDEX('1.2'!$1:$104,MATCH(S$3,'1.2'!$A:$A,0),MATCH(Summary!$C12,'1.2'!$1:$1,0)) -> 10496858 | X12: =INDEX('1.2'!$1:$104,MATCH(V$3,'1.2'!$A:$A,0),MATCH(Summary!$C12,'1.2'!$1:$1,0)) -> 10440278 | AA12: =INDEX('1.2'!$1:$104,MATCH(Y$3,'1.2'!$A:$A,0),MATCH(Summary!$C12,'1.2'!$1:$1,0)) -> 10302290 | AD12: =INDEX('1.2'!$1:$104,MATCH(AB$3,'1.2'!$A:$A,0),MATCH(Summary!$C12,'1.2'!$1:$1,0)) -> 10245411 | AG12: =INDEX('1.2'!$1:$104,MATCH(AE$3,'1.2'!$A:$A,0),MATCH(Summary!$C12,'1.2'!$1:$1,0)) -> 10136142 | AJ12: =INDEX('1.2'!$1:$104,MATCH(AH$3,'1.2'!$A:$A,0),MATCH(Summary!$C12,'1.2'!$1:$1,0)) -> 10002556 | AM12: =INDEX('1.2'!$1:$104,MATCH(AK$3,'1.2'!$A:$A,0),MATCH(Summary!$C12,'1.2'!$1:$1,0)) -> 9997067.5 | AP12: =INDEX('1.2'!$1:$104,MATCH(AN$3,'1.2'!$A:$A,0),MATCH(Summary!$C12,'1.2'!$1:$1,0)) -> 10068576 | AS12: =INDEX('1.2'!$1:$104,MATCH(AQ$3,'1.2'!$A:$A,0),MATCH(Summary!$C12,'1.2'!$1:$1,0)) -> 10003516 | AV12: =INDEX('1.2'!$1:$104,MATCH(AT$3,'1.2'!$A:$A,0),MATCH(Summary!$C12,'1.2'!$1:$1,0)) -> 10041560 | AY12: =INDEX('1.2'!$1:$104,MATCH(AW$3,'1.2'!$A:$A,0),MATCH(Summary!$C12,'1.2'!$1:$1,0)) -> 10158381 | BB12: =INDEX('1.2'!$1:$104,MATCH(AZ$3,'1.2'!$A:$A,0),MATCH(Summary!$C12,'1.2'!$1:$1,0)) -> 9907808 | BE12: =INDEX('1.2'!$1:$104,MATCH(BC$3,'1.2'!$A:$A,0),MATCH(Summary!$C12,'1.2'!$1:$1,0)) -> 10191315 | BH12: =INDEX('1.2'!$1:$104,MATCH(BF$3,'1.2'!$A:$A,0),MATCH(Summary!$C12,'1.2'!$1:$1,0)) -> 10571298 | BK12: =INDEX('1.2'!$1:$104,MATCH(BI$3,'1.2'!$A:$A,0),MATCH(Summary!$C12,'1.2'!$1:$1,0)) -> 10893147
C13: loans_in_hk | E13: Loans for use in HK | H13: =O13/$O$12 -> 0.75040076 | I13: =IFERROR(L13/AV13-1,"") -> 0.065162006 | L13: =INDEX('1.2'!$1:$104,MATCH(L$3,'1.2'!$A:$A,0),MATCH(Summary!$C13,'1.2'!$1:$1,0)) -> 8070867 | O13: =INDEX('1.2'!$1:$104,MATCH(M$3,'1.2'!$A:$A,0),MATCH(Summary!$C13,'1.2'!$1:$1,0)) -> 8095245.2 | R13: =INDEX('1.2'!$1:$104,MATCH(P$3,'1.2'!$A:$A,0),MATCH(Summary!$C13,'1.2'!$1:$1,0)) -> 7981206.3 | U13: =INDEX('1.2'!$1:$104,MATCH(S$3,'1.2'!$A:$A,0),MATCH(Summary!$C13,'1.2'!$1:$1,0)) -> 7869195.5 | X13: =INDEX('1.2'!$1:$104,MATCH(V$3,'1.2'!$A:$A,0),MATCH(Summary!$C13,'1.2'!$1:$1,0)) -> 7861821.8 | AA13: =INDEX('1.2'!$1:$104,MATCH(Y$3,'1.2'!$A:$A,0),MATCH(Summary!$C13,'1.2'!$1:$1,0)) -> 7721916.9 | AD13: =INDEX('1.2'!$1:$104,MATCH(AB$3,'1.2'!$A:$A,0),MATCH(Summary!$C13,'1.2'!$1:$1,0)) -> 7688694.2 | AG13: =INDEX('1.2'!$1:$104,MATCH(AE$3,'1.2'!$A:$A,0),MATCH(Summary!$C13,'1.2'!$1:$1,0)) -> 7635305.1 | AJ13: =INDEX('1.2'!$1:$104,MATCH(AH$3,'1.2'!$A:$A,0),MATCH(Summary!$C13,'1.2'!$1:$1,0)) -> 7546764.4 | AM13: =INDEX('1.2'!$1:$104,MATCH(AK$3,'1.2'!$A:$A,0),MATCH(Summary!$C13,'1.2'!$1:$1,0)) -> 7551750.3 | AP13: =INDEX('1.2'!$1:$104,MATCH(AN$3,'1.2'!$A:$A,0),MATCH(Summary!$C13,'1.2'!$1:$1,0)) -> 7617255.6 | AS13: =INDEX('1.2'!$1:$104,MATCH(AQ$3,'1.2'!$A:$A,0),MATCH(Summary!$C13,'1.2'!$1:$1,0)) -> 7570020.6 | AV13: =INDEX('1.2'!$1:$104,MATCH(AT$3,'1.2'!$A:$A,0),MATCH(Summary!$C13,'1.2'!$1:$1,0)) -> 7577126.3 | AY13: =INDEX('1.2'!$1:$104,MATCH(AW$3,'1.2'!$A:$A,0),MATCH(Summary!$C13,'1.2'!$1:$1,0)) -> 7650101.4 | BB13: =INDEX('1.2'!$1:$104,MATCH(AZ$3,'1.2'!$A:$A,0),MATCH(Summary!$C13,'1.2'!$1:$1,0)) -> 7489982.2 | BE13: =INDEX('1.2'!$1:$104,MATCH(BC$3,'1.2'!$A:$A,0),MATCH(Summary!$C13,'1.2'!$1:$1,0)) -> 7627950.9 | BH13: =INDEX('1.2'!$1:$104,MATCH(BF$3,'1.2'!$A:$A,0),MATCH(Summary!$C13,'1.2'!$1:$1,0)) -> 7710340.6 | BK13: =INDEX('1.2'!$1:$104,MATCH(BI$3,'1.2'!$A:$A,0),MATCH(Summary!$C13,'1.2'!$1:$1,0)) -> 7712295.5
E14: Trade finance | G14: 貿易融資 | H14: =O14/$O$12 -> 0.040423935 | I14: =IFERROR(L14/AV14-1,"") -> 0.17121328 | J14: =J15+J16 -> 69564.467 | K14: =K15+K16 -> 352264.12 | L14: =L15+L16 -> 421828.59 | M14: =M15+M16 -> 69891.593 | N14: =N15+N16 -> 366197.6 | O14: =O15+O16 -> 436089.19 | P14: =P15+P16 -> 69479.415 | Q14: =Q15+Q16 -> 345283.6 | ... BK14: =BK15+BK16 -> 485030.24
A15: imp_exp_reexp_fromhk_hkd | B15: imp_exp_reexp_fromhk_fc | C15: imp_exp_reexp_fromhk_total | E15: To finance H.K.'s visible trade | G15: 香港貨物的出入口及轉口融資 | H15: =O15/$O$12 -> 0.024362226 | I15: =IFERROR(L15/AV15-1,"") -> 0.12876795 | J15: =INDEX('3.4.1'!$1:$104,MATCH(J$4,'3.4.1'!$A:$A,0),MATCH(Summary!$A15,'3.4.1'!$1:$1,0)) -> 56511.102 | K15: =INDEX('3.4.1'!$1:$104,MATCH(K$4,'3.4.1'!$A:$A,0),MATCH(Summary!$B15,'3.4.1'!$1:$1,0)) -> 193800.71 | L15: =INDEX('3.4.1'!$1:$104,MATCH(L$4,'3.4.1'!$A:$A,0),MATCH(Summary!$C15,'3.4.1'!$1:$1,0)) -> 250311.81 | M15: =INDEX('3.4.1'!$1:$104,MATCH(M$4,'3.4.1'!$A:$A,0),MATCH(Summary!$A15,'3.4.1'!$1:$1,0)) -> 57111.395 | N15: =INDEX('3.4.1'!$1:$104,MATCH(N$4,'3.4.1'!$A:$A,0),MATCH(Summary!$B15,'3.4.1'!$1:$1,0)) -> 205705.76 | O15: =INDEX('3.4.1'!$1:$104,MATCH(O$4,'3.4.1'!$A:$A,0),MATCH(Summary!$C15,'3.4.1'!$1:$1,0)) -> 262817.16 | P15: =INDEX('3.4.1'!$1:$104,MATCH(P$4,'3.4.1'!$A:$A,0),MATCH(Summary!$A15,'3.4.1'!$1:$1,0)) -> 57013.091 | Q15: =INDEX('3.4.1'!$1:$104,MATCH(Q$4,'3.4.1'!$A:$A,0),MATCH(Summary!$B15,'3.4.1'!$1:$1,0)) -> 186630.31 | R15: =INDEX('3.4.1'!$1:$104,MATCH(R$4,'3.4.1'!$A:$A,0),MATCH(Summary!$C15,'3.4.1'!$1:$1,0)) -> 243643.4 | S15: =INDEX('3.4.1'!$1:$104,MATCH(S$4,'3.4.1'!$A:$A,0),MATCH(Summary!$A15,'3.4.1'!$1:$1,0)) -> 59126.986 | T15: =INDEX('3.4.1'!$1:$104,MATCH(T$4,'3.4.1'!$A:$A,0),MATCH(Summary!$B15,'3.4.1'!$1:$1,0)) -> 173799.62 | U15: =INDEX('3.4.1'!$1:$104,MATCH(U$4,'3.4.1'!$A:$A,0),MATCH(Summary!$C15,'3.4.1'!$1:$1,0)) -> 232926.61 | V15: =INDEX('3.4.1'!$1:$104,MATCH(V$4,'3.4.1'!$A:$A,0),MATCH(Summary!$A15,'3.4.1'!$1:$1,0)) -> 59339.624 | W15: =INDEX('3.4.1'!$1:$104,MATCH(W$4,'3.4.1'!$A:$A,0),MATCH(Summary!$B15,'3.4.1'!$1:$1,0)) -> 182422.15 | X15: =INDEX('3.4.1'!$1:$104,MATCH(X$4,'3.4.1'!$A:$A,0),MATCH(Summary!$C15,'3.4.1'!$1:$1,0)) -> 241761.77 | Y15: =INDEX('3.4.1'!$1:$104,MATCH(Y$4,'3.4.1'!$A:$A,0),MATCH(Summary!$A15,'3.4.1'!$1:$1,0)) -> 58040.729 | Z15: =INDEX('3.4.1'!$1:$104,MATCH(Z$4,'3.4.1'!$A:$A,0),MATCH(Summary!$B15,'3.4.1'!$1:$1,0)) -> 172201.21 | AA15: =INDEX('3.4.1'!$1:$104,MATCH(AA$4,'3.4.1'!$A:$A,0),MATCH(Summary!$C15,'3.4.1'!$1:$1,0)) -> 230241.94 | AB15: =INDEX('3.4.1'!$1:$104,MATCH(AB$4,'3.4.1'!$A:$A,0),MATCH(Summary!$A15,'3.4.1'!$1:$1,0)) -> 58057.961 | AC15: =INDEX('3.4.1'!$1:$104,MATCH(AC$4,'3.4.1'!$A:$A,0),MATCH(Summary!$B15,'3.4.1'!$1:$1,0)) -> 166061.31 | AD15: =INDEX('3.4.1'!$1:$104,MATCH(AD$4,'3.4.1'!$A:$A,0),MATCH(Summary!$C15,'3.4.1'!$1:$1,0)) -> 224119.27 | AE15: =INDEX('3.4.1'!$1:$104,MATCH(AE$4,'3.4.1'!$A:$A,0),MATCH(Summary!$A15,'3.4.1'!$1:$1,0)) -> 55987.338 | AF15: =INDEX('3.4.1'!$1:$104,MATCH(AF$4,'3.4.1'!$A:$A,0),MATCH(Summary!$B15,'3.4.1'!$1:$1,0)) -> 186177.14 | AG15: =INDEX('3.4.1'!$1:$104,MATCH(AG$4,'3.4.1'!$A:$A,0),MATCH(Summary!$C15,'3.4.1'!$1:$1,0)) -> 242164.48 | AH15: =INDEX('3.4.1'!$1:$104,MATCH(AH$4,'3.4.1'!$A:$A,0),MATCH(Summary!$A15,'3.4.1'!$1:$1,0)) -> 58570.371 | AI15: =INDEX('3.4.1'!$1:$104,MATCH(AI$4,'3.4.1'!$A:$A,0),MATCH(Summary!$B15,'3.4.1'!$1:$1,0)) -> 154966.04 | AJ15: =INDEX('3.4.1'!$1:$104,MATCH(AJ$4,'3.4.1'!$A:$A,0),MATCH(Summary!$C15,'3.4.1'!$1:$1,0)) -> 213536.41 | AK15: =INDEX('3.4.1'!$1:$104,MATCH(AK$4,'3.4.1'!$A:$A,0),MATCH(Summary!$A15,'3.4.1'!$1:$1,0)) -> 57795.635 | AL15: =INDEX('3.4.1'!$1:$104,MATCH(AL$4,'3.4.1'!$A:$A,0),MATCH(Summary!$B15,'3.4.1'!$1:$1,0)) -> 153915.67 | AM15: =INDEX('3.4.1'!$1:$104,MATCH(AM$4,'3.4.1'!$A:$A,0),MATCH(Summary!$C15,'3.4.1'!$1:$1,0)) -> 211711.3 | AN15: =INDEX('3.4.1'!$1:$104,MATCH(AN$4,'3.4.1'!$A:$A,0),MATCH(Summary!$A15,'3.4.1'!$1:$1,0)) -> 61251.15 | AO15: =INDEX('3.4.1'!$1:$104,MATCH(AO$4,'3.4.1'!$A:$A,0),MATCH(Summary!$B15,'3.4.1'!$1:$1,0)) -> 166019.3 | AP15: =INDEX('3.4.1'!$1:$104,MATCH(AP$4,'3.4.1'!$A:$A,0),MATCH(Summary!$C15,'3.4.1'!$1:$1,0)) -> 227270.45 | AQ15: =INDEX('3.4.1'!$1:$104,MATCH(AQ$4,'3.4.1'!$A:$A,0),MATCH(Summary!$A15,'3.4.1'!$1:$1,0)) -> 64970.17 | AR15: =INDEX('3.4.1'!$1:$104,MATCH(AR$4,'3.4.1'!$A:$A,0),MATCH(Summary!$B15,'3.4.1'!$1:$1,0)) -> 148628.36 | AS15: =INDEX('3.4.1'!$1:$104,MATCH(AS$4,'3.4.1'!$A:$A,0),MATCH(Summary!$C15,'3.4.1'!$1:$1,0)) -> 213598.53 | AT15: =INDEX('3.4.1'!$1:$104,MATCH(AT$4,'3.4.1'!$A:$A,0),MATCH(Summary!$A15,'3.4.1'!$1:$1,0)) -> 65997.963 | AU15: =INDEX('3.4.1'!$1:$104,MATCH(AU$4,'3.4.1'!$A:$A,0),MATCH(Summary!$B15,'3.4.1'!$1:$1,0)) -> 155758.7 | AV15: =INDEX('3.4.1'!$1:$104,MATCH(AV$4,'3.4.1'!$A:$A,0),MATCH(Summary!$C15,'3.4.1'!$1:$1,0)) -> 221756.66 | AW15: =INDEX('3.4.1'!$1:$104,MATCH(AW$4,'3.4.1'!$A:$A,0),MATCH(Summary!$A15,'3.4.1'!$1:$1,0)) -> 64711.344 | AX15: =INDEX('3.4.1'!$1:$104,MATCH(AX$4,'3.4.1'!$A:$A,0),MATCH(Summary!$B15,'3.4.1'!$1:$1,0)) -> 159163.17 | AY15: =INDEX('3.4.1'!$1:$104,MATCH(AY$4,'3.4.1'!$A:$A,0),MATCH(Summary!$C15,'3.4.1'!$1:$1,0)) -> 223874.52 | AZ15: =INDEX('3.4.1'!$1:$104,MATCH(AZ$4,'3.4.1'!$A:$A,0),MATCH(Summary!$A15,'3.4.1'!$1:$1,0)) -> 60444.762 | BA15: =INDEX('3.4.1'!$1:$104,MATCH(BA$4,'3.4.1'!$A:$A,0),MATCH(Summary!$B15,'3.4.1'!$1:$1,0)) -> 171303.02 | BB15: =INDEX('3.4.1'!$1:$104,MATCH(BB$4,'3.4.1'!$A:$A,0),MATCH(Summary!$C15,'3.4.1'!$1:$1,0)) -> 231747.78 | BC15: =INDEX('3.4.1'!$1:$104,MATCH(BC$4,'3.4.1'!$A:$A,0),MATCH(Summary!$A15,'3.4.1'!$1:$1,0)) -> 55411.698 | BD15: =INDEX('3.4.1'!$1:$104,MATCH(BD$4,'3.4.1'!$A:$A,0),MATCH(Summary!$B15,'3.4.1'!$1:$1,0)) -> 149701.38 | BE15: =INDEX('3.4.1'!$1:$104,MATCH(BE$4,'3.4.1'!$A:$A,0),MATCH(Summary!$C15,'3.4.1'!$1:$1,0)) -> 205113.08 | BF15: =INDEX('3.4.1'!$1:$104,MATCH(BF$4,'3.4.1'!$A:$A,0),MATCH(Summary!$A15,'3.4.1'!$1:$1,0)) -> 58068.637 | BG15: =INDEX('3.4.1'!$1:$104,MATCH(BG$4,'3.4.1'!$A:$A,0),MATCH(Summary!$B15,'3.4.1'!$1:$1,0)) -> 189414.86 | BH15: =INDEX('3.4.1'!$1:$104,MATCH(BH$4,'3.4.1'!$A:$A,0),MATCH(Summary!$C15,'3.4.1'!$1:$1,0)) -> 247483.5 | BI15: =INDEX('3.4.1'!$1:$104,MATCH(BI$4,'3.4.1'!$A:$A,0),MATCH(Summary!$A15,'3.4.1'!$1:$1,0)) -> 55055.337 | BJ15: =INDEX('3.4.1'!$1:$104,MATCH(BJ$4,'3.4.1'!$A:$A,0),MATCH(Summary!$B15,'3.4.1'!$1:$1,0)) -> 236330.96 | BK15: =INDEX('3.4.1'!$1:$104,MATCH(BK$4,'3.4.1'!$A:$A,0),MATCH(Summary!$C15,'3.4.1'!$1:$1,0)) -> 291386.29
A16: merch_trade_nonhk_hkd | B16: merch_trade_nonhk_fc | C16: merch_trade_nonhk_total | E16: To finance merchandising trade not touching H.K. | G16: 香港境外的商品貿易融資 | H16: =O16/$O$12 -> 0.016061708 | I16: =IFERROR(L16/AV16-1,"") -> 0.23921942 | J16: =INDEX('3.4.1'!$1:$104,MATCH(J$4,'3.4.1'!$A:$A,0),MATCH(Summary!$A16,'3.4.1'!$1:$1,0)) -> 13053.365 | K16: =INDEX('3.4.1'!$1:$104,MATCH(K$4,'3.4.1'!$A:$A,0),MATCH(Summary!$B16,'3.4.1'!$1:$1,0)) -> 158463.42 | L16: =INDEX('3.4.1'!$1:$104,MATCH(L$4,'3.4.1'!$A:$A,0),MATCH(Summary!$C16,'3.4.1'!$1:$1,0)) -> 171516.78 | M16: =INDEX('3.4.1'!$1:$104,MATCH(M$4,'3.4.1'!$A:$A,0),MATCH(Summary!$A16,'3.4.1'!$1:$1,0)) -> 12780.198 | N16: =INDEX('3.4.1'!$1:$104,MATCH(N$4,'3.4.1'!$A:$A,0),MATCH(Summary!$B16,'3.4.1'!$1:$1,0)) -> 160491.84 | O16: =INDEX('3.4.1'!$1:$104,MATCH(O$4,'3.4.1'!$A:$A,0),MATCH(Summary!$C16,'3.4.1'!$1:$1,0)) -> 173272.03 | P16: =INDEX('3.4.1'!$1:$104,MATCH(P$4,'3.4.1'!$A:$A,0),MATCH(Summary!$A16,'3.4.1'!$1:$1,0)) -> 12466.324 | Q16: =INDEX('3.4.1'!$1:$104,MATCH(Q$4,'3.4.1'!$A:$A,0),MATCH(Summary!$B16,'3.4.1'!$1:$1,0)) -> 158653.3 | R16: =INDEX('3.4.1'!$1:$104,MATCH(R$4,'3.4.1'!$A:$A,0),MATCH(Summary!$C16,'3.4.1'!$1:$1,0)) -> 171119.62 | S16: =INDEX('3.4.1'!$1:$104,MATCH(S$4,'3.4.1'!$A:$A,0),MATCH(Summary!$A16,'3.4.1'!$1:$1,0)) -> 11984.01 | T16: =INDEX('3.4.1'!$1:$104,MATCH(T$4,'3.4.1'!$A:$A,0),MATCH(Summary!$B16,'3.4.1'!$1:$1,0)) -> 160556.36 | U16: =INDEX('3.4.1'!$1:$104,MATCH(U$4,'3.4.1'!$A:$A,0),MATCH(Summary!$C16,'3.4.1'!$1:$1,0)) -> 172540.37 | V16: =INDEX('3.4.1'!$1:$104,MATCH(V$4,'3.4.1'!$A:$A,0),MATCH(Summary!$A16,'3.4.1'!$1:$1,0)) -> 11972.022 | W16: =INDEX('3.4.1'!$1:$104,MATCH(W$4,'3.4.1'!$A:$A,0),MATCH(Summary!$B16,'3.4.1'!$1:$1,0)) -> 167767.32 | X16: =INDEX('3.4.1'!$1:$104,MATCH(X$4,'3.4.1'!$A:$A,0),MATCH(Summary!$C16,'3.4.1'!$1:$1,0)) -> 179739.34 | Y16: =INDEX('3.4.1'!$1:$104,MATCH(Y$4,'3.4.1'!$A:$A,0),MATCH(Summary!$A16,'3.4.1'!$1:$1,0)) -> 13041.727 | Z16: =INDEX('3.4.1'!$1:$104,MATCH(Z$4,'3.4.1'!$A:$A,0),MATCH(Summary!$B16,'3.4.1'!$1:$1,0)) -> 126050.45 | AA16: =INDEX('3.4.1'!$1:$104,MATCH(AA$4,'3.4.1'!$A:$A,0),MATCH(Summary!$C16,'3.4.1'!$1:$1,0)) -> 139092.18 | AB16: =INDEX('3.4.1'!$1:$104,MATCH(AB$4,'3.4.1'!$A:$A,0),MATCH(Summary!$A16,'3.4.1'!$1:$1,0)) -> 13924.763 | AC16: =INDEX('3.4.1'!$1:$104,MATCH(AC$4,'3.4.1'!$A:$A,0),MATCH(Summary!$B16,'3.4.1'!$1:$1,0)) -> 121553.74 | AD16: =INDEX('3.4.1'!$1:$104,MATCH(AD$4,'3.4.1'!$A:$A,0),MATCH(Summary!$C16,'3.4.1'!$1:$1,0)) -> 135478.5 | AE16: =INDEX('3.4.1'!$1:$104,MATCH(AE$4,'3.4.1'!$A:$A,0),MATCH(Summary!$A16,'3.4.1'!$1:$1,0)) -> 14415.68 | AF16: =INDEX('3.4.1'!$1:$104,MATCH(AF$4,'3.4.1'!$A:$A,0),MATCH(Summary!$B16,'3.4.1'!$1:$1,0)) -> 134200.05 | AG16: =INDEX('3.4.1'!$1:$104,MATCH(AG$4,'3.4.1'!$A:$A,0),MATCH(Summary!$C16,'3.4.1'!$1:$1,0)) -> 148615.73 | AH16: =INDEX('3.4.1'!$1:$104,MATCH(AH$4,'3.4.1'!$A:$A,0),MATCH(Summary!$A16,'3.4.1'!$1:$1,0)) -> 13974.943 | AI16: =INDEX('3.4.1'!$1:$104,MATCH(AI$4,'3.4.1'!$A:$A,0),MATCH(Summary!$B16,'3.4.1'!$1:$1,0)) -> 116204.61 | AJ16: =INDEX('3.4.1'!$1:$104,MATCH(AJ$4,'3.4.1'!$A:$A,0),MATCH(Summary!$C16,'3.4.1'!$1:$1,0)) -> 130179.55 | AK16: =INDEX('3.4.1'!$1:$104,MATCH(AK$4,'3.4.1'!$A:$A,0),MATCH(Summary!$A16,'3.4.1'!$1:$1,0)) -> 14483.044 | AL16: =INDEX('3.4.1'!$1:$104,MATCH(AL$4,'3.4.1'!$A:$A,0),MATCH(Summary!$B16,'3.4.1'!$1:$1,0)) -> 113621.16 | AM16: =INDEX('3.4.1'!$1:$104,MATCH(AM$4,'3.4.1'!$A:$A,0),MATCH(Summary!$C16,'3.4.1'!$1:$1,0)) -> 128104.21 | AN16: =INDEX('3.4.1'!$1:$104,MATCH(AN$4,'3.4.1'!$A:$A,0),MATCH(Summary!$A16,'3.4.1'!$1:$1,0)) -> 15221.531 | AO16: =INDEX('3.4.1'!$1:$104,MATCH(AO$4,'3.4.1'!$A:$A,0),MATCH(Summary!$B16,'3.4.1'!$1:$1,0)) -> 131263.17 | AP16: =INDEX('3.4.1'!$1:$104,MATCH(AP$4,'3.4.1'!$A:$A,0),MATCH(Summary!$C16,'3.4.1'!$1:$1,0)) -> 146484.71 | AQ16: =INDEX('3.4.1'!$1:$104,MATCH(AQ$4,'3.4.1'!$A:$A,0),MATCH(Summary!$A16,'3.4.1'!$1:$1,0)) -> 15025.371 | AR16: =INDEX('3.4.1'!$1:$104,MATCH(AR$4,'3.4.1'!$A:$A,0),MATCH(Summary!$B16,'3.4.1'!$1:$1,0)) -> 121429.41 | AS16: =INDEX('3.4.1'!$1:$104,MATCH(AS$4,'3.4.1'!$A:$A,0),MATCH(Summary!$C16,'3.4.1'!$1:$1,0)) -> 136454.78 | AT16: =INDEX('3.4.1'!$1:$104,MATCH(AT$4,'3.4.1'!$A:$A,0),MATCH(Summary!$A16,'3.4.1'!$1:$1,0)) -> 14073.304 | AU16: =INDEX('3.4.1'!$1:$104,MATCH(AU$4,'3.4.1'!$A:$A,0),MATCH(Summary!$B16,'3.4.1'!$1:$1,0)) -> 124333.81 | AV16: =INDEX('3.4.1'!$1:$104,MATCH(AV$4,'3.4.1'!$A:$A,0),MATCH(Summary!$C16,'3.4.1'!$1:$1,0)) -> 138407.11 | AW16: =INDEX('3.4.1'!$1:$104,MATCH(AW$4,'3.4.1'!$A:$A,0),MATCH(Summary!$A16,'3.4.1'!$1:$1,0)) -> 13226.637 | AX16: =INDEX('3.4.1'!$1:$104,MATCH(AX$4,'3.4.1'!$A:$A,0),MATCH(Summary!$B16,'3.4.1'!$1:$1,0)) -> 139122.73 | AY16: =INDEX('3.4.1'!$1:$104,MATCH(AY$4,'3.4.1'!$A:$A,0),MATCH(Summary!$C16,'3.4.1'!$1:$1,0)) -> 152349.36 | AZ16: =INDEX('3.4.1'!$1:$104,MATCH(AZ$4,'3.4.1'!$A:$A,0),MATCH(Summary!$A16,'3.4.1'!$1:$1,0)) -> 10821.36 | BA16: =INDEX('3.4.1'!$1:$104,MATCH(BA$4,'3.4.1'!$A:$A,0),MATCH(Summary!$B16,'3.4.1'!$1:$1,0)) -> 138673.73 | BB16: =INDEX('3.4.1'!$1:$104,MATCH(BB$4,'3.4.1'!$A:$A,0),MATCH(Summary!$C16,'3.4.1'!$1:$1,0)) -> 149495.09 | BC16: =INDEX('3.4.1'!$1:$104,MATCH(BC$4,'3.4.1'!$A:$A,0),MATCH(Summary!$A16,'3.4.1'!$1:$1,0)) -> 10577.562 | BD16: =INDEX('3.4.1'!$1:$104,MATCH(BD$4,'3.4.1'!$A:$A,0),MATCH(Summary!$B16,'3.4.1'!$1:$1,0)) -> 148935.23 | BE16: =INDEX('3.4.1'!$1:$104,MATCH(BE$4,'3.4.1'!$A:$A,0),MATCH(Summary!$C16,'3.4.1'!$1:$1,0)) -> 159512.79 | BF16: =INDEX('3.4.1'!$1:$104,MATCH(BF$4,'3.4.1'!$A:$A,0),MATCH(Summary!$A16,'3.4.1'!$1:$1,0)) -> 12622.642 | BG16: =INDEX('3.4.1'!$1:$104,MATCH(BG$4,'3.4.1'!$A:$A,0),MATCH(Summary!$B16,'3.4.1'!$1:$1,0)) -> 159585.63 | BH16: =INDEX('3.4.1'!$1:$104,MATCH(BH$4,'3.4.1'!$A:$A,0),MATCH(Summary!$C16,'3.4.1'!$1:$1,0)) -> 172208.27 | BI16: =INDEX('3.4.1'!$1:$104,MATCH(BI$4,'3.4.1'!$A:$A,0),MATCH(Summary!$A16,'3.4.1'!$1:$1,0)) -> 13888.557 | BJ16: =INDEX('3.4.1'!$1:$104,MATCH(BJ$4,'3.4.1'!$A:$A,0),MATCH(Summary!$B16,'3.4.1'!$1:$1,0)) -> 179755.39 | BK16: =INDEX('3.4.1'!$1:$104,MATCH(BK$4,'3.4.1'!$A:$A,0),MATCH(Summary!$C16,'3.4.1'!$1:$1,0)) -> 193643.95
A17: loans_inhk_hkd | B17: loans_inhk_fc | C17: loans_inhk_total | E17: Other loans for use in H.K(1) | H17: =O17/$O$12 -> 0.70997683 | I17: =IFERROR(L17/AV17-1,"") -> 0.059869499 | J17: =INDEX('3.4.1'!$1:$104,MATCH(J$4,'3.4.1'!$A:$A,0),MATCH(Summary!$A17,'3.4.1'!$1:$1,0)) -> 5580470.7 | K17: =INDEX('3.4.1'!$1:$104,MATCH(K$4,'3.4.1'!$A:$A,0),MATCH(Summary!$B17,'3.4.1'!$1:$1,0)) -> 2068567.8 | L17: =INDEX('3.4.1'!$1:$104,MATCH(L$4,'3.4.1'!$A:$A,0),MATCH(Summary!$C17,'3.4.1'!$1:$1,0)) -> 7649038.4 | M17: =INDEX('3.4.1'!$1:$104,MATCH(M$4,'3.4.1'!$A:$A,0),MATCH(Summary!$A17,'3.4.1'!$1:$1,0)) -> 5589675.4 | N17: =INDEX('3.4.1'!$1:$104,MATCH(N$4,'3.4.1'!$A:$A,0),MATCH(Summary!$B17,'3.4.1'!$1:$1,0)) -> 2069480.6 | O17: =INDEX('3.4.1'!$1:$104,MATCH(O$4,'3.4.1'!$A:$A,0),MATCH(Summary!$C17,'3.4.1'!$1:$1,0)) -> 7659156 | P17: =INDEX('3.4.1'!$1:$104,MATCH(P$4,'3.4.1'!$A:$A,0),MATCH(Summary!$A17,'3.4.1'!$1:$1,0)) -> 5488152.2 | Q17: =INDEX('3.4.1'!$1:$104,MATCH(Q$4,'3.4.1'!$A:$A,0),MATCH(Summary!$B17,'3.4.1'!$1:$1,0)) -> 2078291 | R17: =INDEX('3.4.1'!$1:$104,MATCH(R$4,'3.4.1'!$A:$A,0),MATCH(Summary!$C17,'3.4.1'!$1:$1,0)) -> 7566443.3 | S17: =INDEX('3.4.1'!$1:$104,MATCH(S$4,'3.4.1'!$A:$A,0),MATCH(Summary!$A17,'3.4.1'!$1:$1,0)) -> 5472828.6 | T17: =INDEX('3.4.1'!$1:$104,MATCH(T$4,'3.4.1'!$A:$A,0),MATCH(Summary!$B17,'3.4.1'!$1:$1,0)) -> 1990899.9 | U17: =INDEX('3.4.1'!$1:$104,MATCH(U$4,'3.4.1'!$A:$A,0),MATCH(Summary!$C17,'3.4.1'!$1:$1,0)) -> 7463728.5 | V17: =INDEX('3.4.1'!$1:$104,MATCH(V$4,'3.4.1'!$A:$A,0),MATCH(Summary!$A17,'3.4.1'!$1:$1,0)) -> 5461882.5 | W17: =INDEX('3.4.1'!$1:$104,MATCH(W$4,'3.4.1'!$A:$A,0),MATCH(Summary!$B17,'3.4.1'!$1:$1,0)) -> 1978438.2 | X17: =INDEX('3.4.1'!$1:$104,MATCH(X$4,'3.4.1'!$A:$A,0),MATCH(Summary!$C17,'3.4.1'!$1:$1,0)) -> 7440320.7 | Y17: =INDEX('3.4.1'!$1:$104,MATCH(Y$4,'3.4.1'!$A:$A,0),MATCH(Summary!$A17,'3.4.1'!$1:$1,0)) -> 5431952.5 | Z17: =INDEX('3.4.1'!$1:$104,MATCH(Z$4,'3.4.1'!$A:$A,0),MATCH(Summary!$B17,'3.4.1'!$1:$1,0)) -> 1920630.3 | AA17: =INDEX('3.4.1'!$1:$104,MATCH(AA$4,'3.4.1'!$A:$A,0),MATCH(Summary!$C17,'3.4.1'!$1:$1,0)) -> 7352582.8 | AB17: =INDEX('3.4.1'!$1:$104,MATCH(AB$4,'3.4.1'!$A:$A,0),MATCH(Summary!$A17,'3.4.1'!$1:$1,0)) -> 5430504.2 | AC17: =INDEX('3.4.1'!$1:$104,MATCH(AC$4,'3.4.1'!$A:$A,0),MATCH(Summary!$B17,'3.4.1'!$1:$1,0)) -> 1898592.3 | AD17: =INDEX('3.4.1'!$1:$104,MATCH(AD$4,'3.4.1'!$A:$A,0),MATCH(Summary!$C17,'3.4.1'!$1:$1,0)) -> 7329096.5 | AE17: =INDEX('3.4.1'!$1:$104,MATCH(AE$4,'3.4.1'!$A:$A,0),MATCH(Summary!$A17,'3.4.1'!$1:$1,0)) -> 5408698.2 | AF17: =INDEX('3.4.1'!$1:$104,MATCH(AF$4,'3.4.1'!$A:$A,0),MATCH(Summary!$B17,'3.4.1'!$1:$1,0)) -> 1835826.7 | AG17: =INDEX('3.4.1'!$1:$104,MATCH(AG$4,'3.4.1'!$A:$A,0),MATCH(Summary!$C17,'3.4.1'!$1:$1,0)) -> 7244524.9 | AH17: =INDEX('3.4.1'!$1:$104,MATCH(AH$4,'3.4.1'!$A:$A,0),MATCH(Summary!$A17,'3.4.1'!$1:$1,0)) -> 5391482.5 | AI17: =INDEX('3.4.1'!$1:$104,MATCH(AI$4,'3.4.1'!$A:$A,0),MATCH(Summary!$B17,'3.4.1'!$1:$1,0)) -> 1811566 | AJ17: =INDEX('3.4.1'!$1:$104,MATCH(AJ$4,'3.4.1'!$A:$A,0),MATCH(Summary!$C17,'3.4.1'!$1:$1,0)) -> 7203048.4 | AK17: =INDEX('3.4.1'!$1:$104,MATCH(AK$4,'3.4.1'!$A:$A,0),MATCH(Summary!$A17,'3.4.1'!$1:$1,0)) -> 5414751.6 | AL17: =INDEX('3.4.1'!$1:$104,MATCH(AL$4,'3.4.1'!$A:$A,0),MATCH(Summary!$B17,'3.4.1'!$1:$1,0)) -> 1797183.2 | AM17: =INDEX('3.4.1'!$1:$104,MATCH(AM$4,'3.4.1'!$A:$A,0),MATCH(Summary!$C17,'3.4.1'!$1:$1,0)) -> 7211934.8 | AN17: =INDEX('3.4.1'!$1:$104,MATCH(AN$4,'3.4.1'!$A:$A,0),MATCH(Summary!$A17,'3.4.1'!$1:$1,0)) -> 5452570 | AO17: =INDEX('3.4.1'!$1:$104,MATCH(AO$4,'3.4.1'!$A:$A,0),MATCH(Summary!$B17,'3.4.1'!$1:$1,0)) -> 1790930.5 | AP17: =INDEX('3.4.1'!$1:$104,MATCH(AP$4,'3.4.1'!$A:$A,0),MATCH(Summary!$C17,'3.4.1'!$1:$1,0)) -> 7243500.5 | AQ17: =INDEX('3.4.1'!$1:$104,MATCH(AQ$4,'3.4.1'!$A:$A,0),MATCH(Summary!$A17,'3.4.1'!$1:$1,0)) -> 5433198.2 | AR17: =INDEX('3.4.1'!$1:$104,MATCH(AR$4,'3.4.1'!$A:$A,0),MATCH(Summary!$B17,'3.4.1'!$1:$1,0)) -> 1786769.1 | AS17: =INDEX('3.4.1'!$1:$104,MATCH(AS$4,'3.4.1'!$A:$A,0),MATCH(Summary!$C17,'3.4.1'!$1:$1,0)) -> 7219967.3 | AT17: =INDEX('3.4.1'!$1:$104,MATCH(AT$4,'3.4.1'!$A:$A,0),MATCH(Summary!$A17,'3.4.1'!$1:$1,0)) -> 5429428.7 | AU17: =INDEX('3.4.1'!$1:$104,MATCH(AU$4,'3.4.1'!$A:$A,0),MATCH(Summary!$B17,'3.4.1'!$1:$1,0)) -> 1787533.8 | AV17: =INDEX('3.4.1'!$1:$104,MATCH(AV$4,'3.4.1'!$A:$A,0),MATCH(Summary!$C17,'3.4.1'!$1:$1,0)) -> 7216962.5 | AW17: =INDEX('3.4.1'!$1:$104,MATCH(AW$4,'3.4.1'!$A:$A,0),MATCH(Summary!$A17,'3.4.1'!$1:$1,0)) -> 5464932.4 | AX17: =INDEX('3.4.1'!$1:$104,MATCH(AX$4,'3.4.1'!$A:$A,0),MATCH(Summary!$B17,'3.4.1'!$1:$1,0)) -> 1808945.2 | AY17: =INDEX('3.4.1'!$1:$104,MATCH(AY$4,'3.4.1'!$A:$A,0),MATCH(Summary!$C17,'3.4.1'!$1:$1,0)) -> 7273877.6 | AZ17: =INDEX('3.4.1'!$1:$104,MATCH(AZ$4,'3.4.1'!$A:$A,0),MATCH(Summary!$A17,'3.4.1'!$1:$1,0)) -> 5442170.1 | BA17: =INDEX('3.4.1'!$1:$104,MATCH(BA$4,'3.4.1'!$A:$A,0),MATCH(Summary!$B17,'3.4.1'!$1:$1,0)) -> 1666569.3 | BB17: =INDEX('3.4.1'!$1:$104,MATCH(BB$4,'3.4.1'!$A:$A,0),MATCH(Summary!$C17,'3.4.1'!$1:$1,0)) -> 7108739.3 | BC17: =INDEX('3.4.1'!$1:$104,MATCH(BC$4,'3.4.1'!$A:$A,0),MATCH(Summary!$A17,'3.4.1'!$1:$1,0)) -> 5636493.2 | BD17: =INDEX('3.4.1'!$1:$104,MATCH(BD$4,'3.4.1'!$A:$A,0),MATCH(Summary!$B17,'3.4.1'!$1:$1,0)) -> 1626831.8 | BE17: =INDEX('3.4.1'!$1:$104,MATCH(BE$4,'3.4.1'!$A:$A,0),MATCH(Summary!$C17,'3.4.1'!$1:$1,0)) -> 7263325 | BF17: =INDEX('3.4.1'!$1:$104,MATCH(BF$4,'3.4.1'!$A:$A,0),MATCH(Summary!$A17,'3.4.1'!$1:$1,0)) -> 5648487.7 | BG17: =INDEX('3.4.1'!$1:$104,MATCH(BG$4,'3.4.1'!$A:$A,0),MATCH(Summary!$B17,'3.4.1'!$1:$1,0)) -> 1642161.1 | BH17: =INDEX('3.4.1'!$1:$104,MATCH(BH$4,'3.4.1'!$A:$A,0),MATCH(Summary!$C17,'3.4.1'!$1:$1,0)) -> 7290648.8 | BI17: =INDEX('3.4.1'!$1:$104,MATCH(BI$4,'3.4.1'!$A:$A,0),MATCH(Summary!$A17,'3.4.1'!$1:$1,0)) -> 5468186.2 | BJ17: =INDEX('3.4.1'!$1:$104,MATCH(BJ$4,'3.4.1'!$A:$A,0),MATCH(Summary!$B17,'3.4.1'!$1:$1,0)) -> 1759079.1 | BK17: =INDEX('3.4.1'!$1:$104,MATCH(BK$4,'3.4.1'!$A:$A,0),MATCH(Summary!$C17,'3.4.1'!$1:$1,0)) -> 7227265.3
C18: mfg | F18: Manufacturing | G18: 製造業 | H18: =O18/$O$12 -> 0.03370759 | I18: =IFERROR(L18/AV18-1,"") | L18: =_xlfn.IFNA(INDEX('3.5.1'!$1:$104,MATCH(L$4,'3.5.1'!$A:$A,0),MATCH(Summary!$C18,'3.5.1'!$1:$1,0)),"") | O18: =_xlfn.IFNA(INDEX('3.5.1'!$1:$104,MATCH(O$4,'3.5.1'!$A:$A,0),MATCH(Summary!$C18,'3.5.1'!$1:$1,0)),"") -> 363633.97 | R18: =_xlfn.IFNA(INDEX('3.5.1'!$1:$104,MATCH(R$4,'3.5.1'!$A:$A,0),MATCH(Summary!$C18,'3.5.1'!$1:$1,0)),"") | U18: =_xlfn.IFNA(INDEX('3.5.1'!$1:$104,MATCH(U$4,'3.5.1'!$A:$A,0),MATCH(Summary!$C18,'3.5.1'!$1:$1,0)),"") | X18: =_xlfn.IFNA(INDEX('3.5.1'!$1:$104,MATCH(X$4,'3.5.1'!$A:$A,0),MATCH(Summary!$C18,'3.5.1'!$1:$1,0)),"") -> 328188.24 | AA18: =_xlfn.IFNA(INDEX('3.5.1'!$1:$104,MATCH(AA$4,'3.5.1'!$A:$A,0),MATCH(Summary!$C18,'3.5.1'!$1:$1,0)),"") | AD18: =_xlfn.IFNA(INDEX('3.5.1'!$1:$104,MATCH(AD$4,'3.5.1'!$A:$A,0),MATCH(Summary!$C18,'3.5.1'!$1:$1,0)),"") | AG18: =_xlfn.IFNA(INDEX('3.5.1'!$1:$104,MATCH(AG$4,'3.5.1'!$A:$A,0),MATCH(Summary!$C18,'3.5.1'!$1:$1,0)),"") -> 306596.64 | AJ18: =_xlfn.IFNA(INDEX('3.5.1'!$1:$104,MATCH(AJ$4,'3.5.1'!$A:$A,0),MATCH(Summary!$C18,'3.5.1'!$1:$1,0)),"") | AM18: =_xlfn.IFNA(INDEX('3.5.1'!$1:$104,MATCH(AM$4,'3.5.1'!$A:$A,0),MATCH(Summary!$C18,'3.5.1'!$1:$1,0)),"") | AP18: =_xlfn.IFNA(INDEX('3.5.1'!$1:$104,MATCH(AP$4,'3.5.1'!$A:$A,0),MATCH(Summary!$C18,'3.5.1'!$1:$1,0)),"") -> 322774.75 | AS18: =_xlfn.IFNA(INDEX('3.5.1'!$1:$104,MATCH(AS$4,'3.5.1'!$A:$A,0),MATCH(Summary!$C18,'3.5.1'!$1:$1,0)),"") | AV18: =_xlfn.IFNA(INDEX('3.5.1'!$1:$104,MATCH(AV$4,'3.5.1'!$A:$A,0),MATCH(Summary!$C18,'3.5.1'!$1:$1,0)),"") | AY18: =_xlfn.IFNA(INDEX('3.5.1'!$1:$104,MATCH(AY$4,'3.5.1'!$A:$A,0),MATCH(Summary!$C18,'3.5.1'!$1:$1,0)),"") -> 324870.77 | BB18: =_xlfn.IFNA(INDEX('3.5.1'!$1:$104,MATCH(BB$4,'3.5.1'!$A:$A,0),MATCH(Summary!$C18,'3.5.1'!$1:$1,0)),"") -> 295132.54 | BE18: =_xlfn.IFNA(INDEX('3.5.1'!$1:$104,MATCH(BE$4,'3.5.1'!$A:$A,0),MATCH(Summary!$C18,'3.5.1'!$1:$1,0)),"") | BH18: =_xlfn.IFNA(INDEX('3.5.1'!$1:$104,MATCH(BH$4,'3.5.1'!$A:$A,0),MATCH(Summary!$C18,'3.5.1'!$1:$1,0)),"") | BK18: =_xlfn.IFNA(INDEX('3.5.1'!$1:$104,MATCH(BK$4,'3.5.1'!$A:$A,0),MATCH(Summary!$C18,'3.5.1'!$1:$1,0)),"")
C19: mfg_textiles | F19: Textiles | G19: 紡織 | H19: =O19/$O$12 -> 0.00098331336 | I19: =IFERROR(L19/AV19-1,"") | L19: =_xlfn.IFNA(INDEX('3.5.1'!$1:$104,MATCH(L$4,'3.5.1'!$A:$A,0),MATCH(Summary!$C19,'3.5.1'!$1:$1,0)),"") | O19: =_xlfn.IFNA(INDEX('3.5.1'!$1:$104,MATCH(O$4,'3.5.1'!$A:$A,0),MATCH(Summary!$C19,'3.5.1'!$1:$1,0)),"") -> 10607.882 | R19: =_xlfn.IFNA(INDEX('3.5.1'!$1:$104,MATCH(R$4,'3.5.1'!$A:$A,0),MATCH(Summary!$C19,'3.5.1'!$1:$1,0)),"") | U19: =_xlfn.IFNA(INDEX('3.5.1'!$1:$104,MATCH(U$4,'3.5.1'!$A:$A,0),MATCH(Summary!$C19,'3.5.1'!$1:$1,0)),"") | X19: =_xlfn.IFNA(INDEX('3.5.1'!$1:$104,MATCH(X$4,'3.5.1'!$A:$A,0),MATCH(Summary!$C19,'3.5.1'!$1:$1,0)),"") -> 10407.843 | AA19: =_xlfn.IFNA(INDEX('3.5.1'!$1:$104,MATCH(AA$4,'3.5.1'!$A:$A,0),MATCH(Summary!$C19,'3.5.1'!$1:$1,0)),"") | AD19: =_xlfn.IFNA(INDEX('3.5.1'!$1:$104,MATCH(AD$4,'3.5.1'!$A:$A,0),MATCH(Summary!$C19,'3.5.1'!$1:$1,0)),"") | AG19: =_xlfn.IFNA(INDEX('3.5.1'!$1:$104,MATCH(AG$4,'3.5.1'!$A:$A,0),MATCH(Summary!$C19,'3.5.1'!$1:$1,0)),"") -> 10579.608 | AJ19: =_xlfn.IFNA(INDEX('3.5.1'!$1:$104,MATCH(AJ$4,'3.5.1'!$A:$A,0),MATCH(Summary!$C19,'3.5.1'!$1:$1,0)),"") | AM19: =_xlfn.IFNA(INDEX('3.5.1'!$1:$104,MATCH(AM$4,'3.5.1'!$A:$A,0),MATCH(Summary!$C19,'3.5.1'!$1:$1,0)),"") | AP19: =_xlfn.IFNA(INDEX('3.5.1'!$1:$104,MATCH(AP$4,'3.5.1'!$A:$A,0),MATCH(Summary!$C19,'3.5.1'!$1:$1,0)),"") -> 10888.719 | AS19: =_xlfn.IFNA(INDEX('3.5.1'!$1:$104,MATCH(AS$4,'3.5.1'!$A:$A,0),MATCH(Summary!$C19,'3.5.1'!$1:$1,0)),"") | AV19: =_xlfn.IFNA(INDEX('3.5.1'!$1:$104,MATCH(AV$4,'3.5.1'!$A:$A,0),MATCH(Summary!$C19,'3.5.1'!$1:$1,0)),"") | AY19: =_xlfn.IFNA(INDEX('3.5.1'!$1:$104,MATCH(AY$4,'3.5.1'!$A:$A,0),MATCH(Summary!$C19,'3.5.1'!$1:$1,0)),"") -> 10105.352 | BB19: =_xlfn.IFNA(INDEX('3.5.1'!$1:$104,MATCH(BB$4,'3.5.1'!$A:$A,0),MATCH(Summary!$C19,'3.5.1'!$1:$1,0)),"") -> 12543.956 | BE19: =_xlfn.IFNA(INDEX('3.5.1'!$1:$104,MATCH(BE$4,'3.5.1'!$A:$A,0),MATCH(Summary!$C19,'3.5.1'!$1:$1,0)),"") | BH19: =_xlfn.IFNA(INDEX('3.5.1'!$1:$104,MATCH(BH$4,'3.5.1'!$A:$A,0),MATCH(Summary!$C19,'3.5.1'!$1:$1,0)),"") | BK19: =_xlfn.IFNA(INDEX('3.5.1'!$1:$104,MATCH(BK$4,'3.5.1'!$A:$A,0),MATCH(Summary!$C19,'3.5.1'!$1:$1,0)),"")
C20: mfg_footwear | F20: Footwear and wearing apparel | G20: 鞋類及衣飾 | H20: =O20/$O$12 -> 0.0029058091 | I20: =IFERROR(L20/AV20-1,"") | L20: =_xlfn.IFNA(INDEX('3.5.1'!$1:$104,MATCH(L$4,'3.5.1'!$A:$A,0),MATCH(Summary!$C20,'3.5.1'!$1:$1,0)),"") | O20: =_xlfn.IFNA(INDEX('3.5.1'!$1:$104,MATCH(O$4,'3.5.1'!$A:$A,0),MATCH(Summary!$C20,'3.5.1'!$1:$1,0)),"") -> 31347.566 | R20: =_xlfn.IFNA(INDEX('3.5.1'!$1:$104,MATCH(R$4,'3.5.1'!$A:$A,0),MATCH(Summary!$C20,'3.5.1'!$1:$1,0)),"") | U20: =_xlfn.IFNA(INDEX('3.5.1'!$1:$104,MATCH(U$4,'3.5.1'!$A:$A,0),MATCH(Summary!$C20,'3.5.1'!$1:$1,0)),"") | X20: =_xlfn.IFNA(INDEX('3.5.1'!$1:$104,MATCH(X$4,'3.5.1'!$A:$A,0),MATCH(Summary!$C20,'3.5.1'!$1:$1,0)),"") -> 27516.138 | AA20: =_xlfn.IFNA(INDEX('3.5.1'!$1:$104,MATCH(AA$4,'3.5.1'!$A:$A,0),MATCH(Summary!$C20,'3.5.1'!$1:$1,0)),"") | AD20: =_xlfn.IFNA(INDEX('3.5.1'!$1:$104,MATCH(AD$4,'3.5.1'!$A:$A,0),MATCH(Summary!$C20,'3.5.1'!$1:$1,0)),"") | AG20: =_xlfn.IFNA(INDEX('3.5.1'!$1:$104,MATCH(AG$4,'3.5.1'!$A:$A,0),MATCH(Summary!$C20,'3.5.1'!$1:$1,0)),"") -> 26813.224 | AJ20: =_xlfn.IFNA(INDEX('3.5.1'!$1:$104,MATCH(AJ$4,'3.5.1'!$A:$A,0),MATCH(Summary!$C20,'3.5.1'!$1:$1,0)),"") | AM20: =_xlfn.IFNA(INDEX('3.5.1'!$1:$104,MATCH(AM$4,'3.5.1'!$A:$A,0),MATCH(Summary!$C20,'3.5.1'!$1:$1,0)),"") | AP20: =_xlfn.IFNA(INDEX('3.5.1'!$1:$104,MATCH(AP$4,'3.5.1'!$A:$A,0),MATCH(Summary!$C20,'3.5.1'!$1:$1,0)),"") -> 27397.964 | AS20: =_xlfn.IFNA(INDEX('3.5.1'!$1:$104,MATCH(AS$4,'3.5.1'!$A:$A,0),MATCH(Summary!$C20,'3.5.1'!$1:$1,0)),"") | AV20: =_xlfn.IFNA(INDEX('3.5.1'!$1:$104,MATCH(AV$4,'3.5.1'!$A:$A,0),MATCH(Summary!$C20,'3.5.1'!$1:$1,0)),"") | AY20: =_xlfn.IFNA(INDEX('3.5.1'!$1:$104,MATCH(AY$4,'3.5.1'!$A:$A,0),MATCH(Summary!$C20,'3.5.1'!$1:$1,0)),"") -> 27564.337 | BB20: =_xlfn.IFNA(INDEX('3.5.1'!$1:$104,MATCH(BB$4,'3.5.1'!$A:$A,0),MATCH(Summary!$C20,'3.5.1'!$1:$1,0)),"") -> 21597.563 | BE20: =_xlfn.IFNA(INDEX('3.5.1'!$1:$104,MATCH(BE$4,'3.5.1'!$A:$A,0),MATCH(Summary!$C20,'3.5.1'!$1:$1,0)),"") | BH20: =_xlfn.IFNA(INDEX('3.5.1'!$1:$104,MATCH(BH$4,'3.5.1'!$A:$A,0),MATCH(Summary!$C20,'3.5.1'!$1:$1,0)),"") | BK20: =_xlfn.IFNA(INDEX('3.5.1'!$1:$104,MATCH(BK$4,'3.5.1'!$A:$A,0),MATCH(Summary!$C20,'3.5.1'!$1:$1,0)),"")
C21: mfg_metalengr | F21: Metal products and engineering | G21: 金屬製品及工程 | H21: =O21/$O$12 -> 0.0042592287 | I21: =IFERROR(L21/AV21-1,"") | L21: =_xlfn.IFNA(INDEX('3.5.1'!$1:$104,MATCH(L$4,'3.5.1'!$A:$A,0),MATCH(Summary!$C21,'3.5.1'!$1:$1,0)),"") | O21: =_xlfn.IFNA(INDEX('3.5.1'!$1:$104,MATCH(O$4,'3.5.1'!$A:$A,0),MATCH(Summary!$C21,'3.5.1'!$1:$1,0)),"") -> 45948.115 | R21: =_xlfn.IFNA(INDEX('3.5.1'!$1:$104,MATCH(R$4,'3.5.1'!$A:$A,0),MATCH(Summary!$C21,'3.5.1'!$1:$1,0)),"") | U21: =_xlfn.IFNA(INDEX('3.5.1'!$1:$104,MATCH(U$4,'3.5.1'!$A:$A,0),MATCH(Summary!$C21,'3.5.1'!$1:$1,0)),"") | X21: =_xlfn.IFNA(INDEX('3.5.1'!$1:$104,MATCH(X$4,'3.5.1'!$A:$A,0),MATCH(Summary!$C21,'3.5.1'!$1:$1,0)),"") -> 44021.965 | AA21: =_xlfn.IFNA(INDEX('3.5.1'!$1:$104,MATCH(AA$4,'3.5.1'!$A:$A,0),MATCH(Summary!$C21,'3.5.1'!$1:$1,0)),"") | AD21: =_xlfn.IFNA(INDEX('3.5.1'!$1:$104,MATCH(AD$4,'3.5.1'!$A:$A,0),MATCH(Summary!$C21,'3.5.1'!$1:$1,0)),"") | AG21: =_xlfn.IFNA(INDEX('3.5.1'!$1:$104,MATCH(AG$4,'3.5.1'!$A:$A,0),MATCH(Summary!$C21,'3.5.1'!$1:$1,0)),"") -> 39803.767 | AJ21: =_xlfn.IFNA(INDEX('3.5.1'!$1:$104,MATCH(AJ$4,'3.5.1'!$A:$A,0),MATCH(Summary!$C21,'3.5.1'!$1:$1,0)),"") | AM21: =_xlfn.IFNA(INDEX('3.5.1'!$1:$104,MATCH(AM$4,'3.5.1'!$A:$A,0),MATCH(Summary!$C21,'3.5.1'!$1:$1,0)),"") | AP21: =_xlfn.IFNA(INDEX('3.5.1'!$1:$104,MATCH(AP$4,'3.5.1'!$A:$A,0),MATCH(Summary!$C21,'3.5.1'!$1:$1,0)),"") -> 43053.556 | AS21: =_xlfn.IFNA(INDEX('3.5.1'!$1:$104,MATCH(AS$4,'3.5.1'!$A:$A,0),MATCH(Summary!$C21,'3.5.1'!$1:$1,0)),"") | AV21: =_xlfn.IFNA(INDEX('3.5.1'!$1:$104,MATCH(AV$4,'3.5.1'!$A:$A,0),MATCH(Summary!$C21,'3.5.1'!$1:$1,0)),"") | AY21: =_xlfn.IFNA(INDEX('3.5.1'!$1:$104,MATCH(AY$4,'3.5.1'!$A:$A,0),MATCH(Summary!$C21,'3.5.1'!$1:$1,0)),"") -> 43381.244 | BB21: =_xlfn.IFNA(INDEX('3.5.1'!$1:$104,MATCH(BB$4,'3.5.1'!$A:$A,0),MATCH(Summary!$C21,'3.5.1'!$1:$1,0)),"") -> 37385.872 | BE21: =_xlfn.IFNA(INDEX('3.5.1'!$1:$104,MATCH(BE$4,'3.5.1'!$A:$A,0),MATCH(Summary!$C21,'3.5.1'!$1:$1,0)),"") | BH21: =_xlfn.IFNA(INDEX('3.5.1'!$1:$104,MATCH(BH$4,'3.5.1'!$A:$A,0),MATCH(Summary!$C21,'3.5.1'!$1:$1,0)),"") | BK21: =_xlfn.IFNA(INDEX('3.5.1'!$1:$104,MATCH(BK$4,'3.5.1'!$A:$A,0),MATCH(Summary!$C21,'3.5.1'!$1:$1,0)),"")
C22: mfg_rubbplastchem | F22: Rubber, plastic and chemicals | G22: 橡膠、塑膠及化工 | H22: =O22/$O$12 -> 0.0067788867 | I22: =IFERROR(L22/AV22-1,"") | L22: =_xlfn.IFNA(INDEX('3.5.1'!$1:$104,MATCH(L$4,'3.5.1'!$A:$A,0),MATCH(Summary!$C22,'3.5.1'!$1:$1,0)),"") | O22: =_xlfn.IFNA(INDEX('3.5.1'!$1:$104,MATCH(O$4,'3.5.1'!$A:$A,0),MATCH(Summary!$C22,'3.5.1'!$1:$1,0)),"") -> 73129.923 | R22: =_xlfn.IFNA(INDEX('3.5.1'!$1:$104,MATCH(R$4,'3.5.1'!$A:$A,0),MATCH(Summary!$C22,'3.5.1'!$1:$1,0)),"") | U22: =_xlfn.IFNA(INDEX('3.5.1'!$1:$104,MATCH(U$4,'3.5.1'!$A:$A,0),MATCH(Summary!$C22,'3.5.1'!$1:$1,0)),"") | X22: =_xlfn.IFNA(INDEX('3.5.1'!$1:$104,MATCH(X$4,'3.5.1'!$A:$A,0),MATCH(Summary!$C22,'3.5.1'!$1:$1,0)),"") -> 63578.479 | AA22: =_xlfn.IFNA(INDEX('3.5.1'!$1:$104,MATCH(AA$4,'3.5.1'!$A:$A,0),MATCH(Summary!$C22,'3.5.1'!$1:$1,0)),"") | AD22: =_xlfn.IFNA(INDEX('3.5.1'!$1:$104,MATCH(AD$4,'3.5.1'!$A:$A,0),MATCH(Summary!$C22,'3.5.1'!$1:$1,0)),"") | AG22: =_xlfn.IFNA(INDEX('3.5.1'!$1:$104,MATCH(AG$4,'3.5.1'!$A:$A,0),MATCH(Summary!$C22,'3.5.1'!$1:$1,0)),"") -> 62683.653 | AJ22: =_xlfn.IFNA(INDEX('3.5.1'!$1:$104,MATCH(AJ$4,'3.5.1'!$A:$A,0),MATCH(Summary!$C22,'3.5.1'!$1:$1,0)),"") | AM22: =_xlfn.IFNA(INDEX('3.5.1'!$1:$104,MATCH(AM$4,'3.5.1'!$A:$A,0),MATCH(Summary!$C22,'3.5.1'!$1:$1,0)),"") | AP22: =_xlfn.IFNA(INDEX('3.5.1'!$1:$104,MATCH(AP$4,'3.5.1'!$A:$A,0),MATCH(Summary!$C22,'3.5.1'!$1:$1,0)),"") -> 72133.026 | AS22: =_xlfn.IFNA(INDEX('3.5.1'!$1:$104,MATCH(AS$4,'3.5.1'!$A:$A,0),MATCH(Summary!$C22,'3.5.1'!$1:$1,0)),"") | AV22: =_xlfn.IFNA(INDEX('3.5.1'!$1:$104,MATCH(AV$4,'3.5.1'!$A:$A,0),MATCH(Summary!$C22,'3.5.1'!$1:$1,0)),"") | AY22: =_xlfn.IFNA(INDEX('3.5.1'!$1:$104,MATCH(AY$4,'3.5.1'!$A:$A,0),MATCH(Summary!$C22,'3.5.1'!$1:$1,0)),"") -> 64991.74 | BB22: =_xlfn.IFNA(INDEX('3.5.1'!$1:$104,MATCH(BB$4,'3.5.1'!$A:$A,0),MATCH(Summary!$C22,'3.5.1'!$1:$1,0)),"") -> 57264.194 | BE22: =_xlfn.IFNA(INDEX('3.5.1'!$1:$104,MATCH(BE$4,'3.5.1'!$A:$A,0),MATCH(Summary!$C22,'3.5.1'!$1:$1,0)),"") | BH22: =_xlfn.IFNA(INDEX('3.5.1'!$1:$104,MATCH(BH$4,'3.5.1'!$A:$A,0),MATCH(Summary!$C22,'3.5.1'!$1:$1,0)),"") | BK22: =_xlfn.IFNA(INDEX('3.5.1'!$1:$104,MATCH(BK$4,'3.5.1'!$A:$A,0),MATCH(Summary!$C22,'3.5.1'!$1:$1,0)),"")
C23: mfg_shipbuildrepair | F23: Shipbuilding and repair 3 | G23: 造船及修理3 | H23: =O23/$O$12 -> 0 | I23: =IFERROR(L23/AV23-1,"") | L23: =_xlfn.IFNA(INDEX('3.5.1'!$1:$104,MATCH(L$4,'3.5.1'!$A:$A,0),MATCH(Summary!$C23,'3.5.1'!$1:$1,0)),"") | O23: =_xlfn.IFNA(INDEX('3.5.1'!$1:$104,MATCH(O$4,'3.5.1'!$A:$A,0),MATCH(Summary!$C23,'3.5.1'!$1:$1,0)),"") -> 0 | R23: =_xlfn.IFNA(INDEX('3.5.1'!$1:$104,MATCH(R$4,'3.5.1'!$A:$A,0),MATCH(Summary!$C23,'3.5.1'!$1:$1,0)),"") | U23: =_xlfn.IFNA(INDEX('3.5.1'!$1:$104,MATCH(U$4,'3.5.1'!$A:$A,0),MATCH(Summary!$C23,'3.5.1'!$1:$1,0)),"") | X23: =_xlfn.IFNA(INDEX('3.5.1'!$1:$104,MATCH(X$4,'3.5.1'!$A:$A,0),MATCH(Summary!$C23,'3.5.1'!$1:$1,0)),"") -> 0 | AA23: =_xlfn.IFNA(INDEX('3.5.1'!$1:$104,MATCH(AA$4,'3.5.1'!$A:$A,0),MATCH(Summary!$C23,'3.5.1'!$1:$1,0)),"") | AD23: =_xlfn.IFNA(INDEX('3.5.1'!$1:$104,MATCH(AD$4,'3.5.1'!$A:$A,0),MATCH(Summary!$C23,'3.5.1'!$1:$1,0)),"") | AG23: =_xlfn.IFNA(INDEX('3.5.1'!$1:$104,MATCH(AG$4,'3.5.1'!$A:$A,0),MATCH(Summary!$C23,'3.5.1'!$1:$1,0)),"") -> 0 | AJ23: =_xlfn.IFNA(INDEX('3.5.1'!$1:$104,MATCH(AJ$4,'3.5.1'!$A:$A,0),MATCH(Summary!$C23,'3.5.1'!$1:$1,0)),"") | AM23: =_xlfn.IFNA(INDEX('3.5.1'!$1:$104,MATCH(AM$4,'3.5.1'!$A:$A,0),MATCH(Summary!$C23,'3.5.1'!$1:$1,0)),"") | AP23: =_xlfn.IFNA(INDEX('3.5.1'!$1:$104,MATCH(AP$4,'3.5.1'!$A:$A,0),MATCH(Summary!$C23,'3.5.1'!$1:$1,0)),"") -> 0 | AS23: =_xlfn.IFNA(INDEX('3.5.1'!$1:$104,MATCH(AS$4,'3.5.1'!$A:$A,0),MATCH(Summary!$C23,'3.5.1'!$1:$1,0)),"") | AV23: =_xlfn.IFNA(INDEX('3.5.1'!$1:$104,MATCH(AV$4,'3.5.1'!$A:$A,0),MATCH(Summary!$C23,'3.5.1'!$1:$1,0)),"") | AY23: =_xlfn.IFNA(INDEX('3.5.1'!$1:$104,MATCH(AY$4,'3.5.1'!$A:$A,0),MATCH(Summary!$C23,'3.5.1'!$1:$1,0)),"") -> 0 | BB23: =_xlfn.IFNA(INDEX('3.5.1'!$1:$104,MATCH(BB$4,'3.5.1'!$A:$A,0),MATCH(Summary!$C23,'3.5.1'!$1:$1,0)),"") -> 0 | BE23: =_xlfn.IFNA(INDEX('3.5.1'!$1:$104,MATCH(BE$4,'3.5.1'!$A:$A,0),MATCH(Summary!$C23,'3.5.1'!$1:$1,0)),"") | BH23: =_xlfn.IFNA(INDEX('3.5.1'!$1:$104,MATCH(BH$4,'3.5.1'!$A:$A,0),MATCH(Summary!$C23,'3.5.1'!$1:$1,0)),"") | BK23: =_xlfn.IFNA(INDEX('3.5.1'!$1:$104,MATCH(BK$4,'3.5.1'!$A:$A,0),MATCH(Summary!$C23,'3.5.1'!$1:$1,0)),"")
C24: mfg_ee | F24: Electrical and electronic4 | G24: 電器及電子4 | H24: =O24/$O$12 -> 0.0056476257 | I24: =IFERROR(L24/AV24-1,"") | L24: =_xlfn.IFNA(INDEX('3.5.1'!$1:$104,MATCH(L$4,'3.5.1'!$A:$A,0),MATCH(Summary!$C24,'3.5.1'!$1:$1,0)),"") | O24: =_xlfn.IFNA(INDEX('3.5.1'!$1:$104,MATCH(O$4,'3.5.1'!$A:$A,0),MATCH(Summary!$C24,'3.5.1'!$1:$1,0)),"") -> 60925.997 | R24: =_xlfn.IFNA(INDEX('3.5.1'!$1:$104,MATCH(R$4,'3.5.1'!$A:$A,0),MATCH(Summary!$C24,'3.5.1'!$1:$1,0)),"") | U24: =_xlfn.IFNA(INDEX('3.5.1'!$1:$104,MATCH(U$4,'3.5.1'!$A:$A,0),MATCH(Summary!$C24,'3.5.1'!$1:$1,0)),"") | X24: =_xlfn.IFNA(INDEX('3.5.1'!$1:$104,MATCH(X$4,'3.5.1'!$A:$A,0),MATCH(Summary!$C24,'3.5.1'!$1:$1,0)),"") -> 61296.591 | AA24: =_xlfn.IFNA(INDEX('3.5.1'!$1:$104,MATCH(AA$4,'3.5.1'!$A:$A,0),MATCH(Summary!$C24,'3.5.1'!$1:$1,0)),"") | AD24: =_xlfn.IFNA(INDEX('3.5.1'!$1:$104,MATCH(AD$4,'3.5.1'!$A:$A,0),MATCH(Summary!$C24,'3.5.1'!$1:$1,0)),"") | AG24: =_xlfn.IFNA(INDEX('3.5.1'!$1:$104,MATCH(AG$4,'3.5.1'!$A:$A,0),MATCH(Summary!$C24,'3.5.1'!$1:$1,0)),"") -> 54150.184 | AJ24: =_xlfn.IFNA(INDEX('3.5.1'!$1:$104,MATCH(AJ$4,'3.5.1'!$A:$A,0),MATCH(Summary!$C24,'3.5.1'!$1:$1,0)),"") | AM24: =_xlfn.IFNA(INDEX('3.5.1'!$1:$104,MATCH(AM$4,'3.5.1'!$A:$A,0),MATCH(Summary!$C24,'3.5.1'!$1:$1,0)),"") | AP24: =_xlfn.IFNA(INDEX('3.5.1'!$1:$104,MATCH(AP$4,'3.5.1'!$A:$A,0),MATCH(Summary!$C24,'3.5.1'!$1:$1,0)),"") -> 49492.873 | AS24: =_xlfn.IFNA(INDEX('3.5.1'!$1:$104,MATCH(AS$4,'3.5.1'!$A:$A,0),MATCH(Summary!$C24,'3.5.1'!$1:$1,0)),"") | AV24: =_xlfn.IFNA(INDEX('3.5.1'!$1:$104,MATCH(AV$4,'3.5.1'!$A:$A,0),MATCH(Summary!$C24,'3.5.1'!$1:$1,0)),"") | AY24: =_xlfn.IFNA(INDEX('3.5.1'!$1:$104,MATCH(AY$4,'3.5.1'!$A:$A,0),MATCH(Summary!$C24,'3.5.1'!$1:$1,0)),"") -> 51873.188 | BB24: =_xlfn.IFNA(INDEX('3.5.1'!$1:$104,MATCH(BB$4,'3.5.1'!$A:$A,0),MATCH(Summary!$C24,'3.5.1'!$1:$1,0)),"") -> 52623.241 | BE24: =_xlfn.IFNA(INDEX('3.5.1'!$1:$104,MATCH(BE$4,'3.5.1'!$A:$A,0),MATCH(Summary!$C24,'3.5.1'!$1:$1,0)),"") | BH24: =_xlfn.IFNA(INDEX('3.5.1'!$1:$104,MATCH(BH$4,'3.5.1'!$A:$A,0),MATCH(Summary!$C24,'3.5.1'!$1:$1,0)),"") | BK24: =_xlfn.IFNA(INDEX('3.5.1'!$1:$104,MATCH(BK$4,'3.5.1'!$A:$A,0),MATCH(Summary!$C24,'3.5.1'!$1:$1,0)),"")
C25: mfg_ee_teleequip | F25: Telecommunication equipment | G25: 電子通訊設備 | H25: =O25/$O$12 -> 0.00092683942 | I25: =IFERROR(L25/AV25-1,"") | L25: =_xlfn.IFNA(INDEX('3.5.1'!$1:$104,MATCH(L$4,'3.5.1'!$A:$A,0),MATCH(Summary!$C25,'3.5.1'!$1:$1,0)),"") | O25: =_xlfn.IFNA(INDEX('3.5.1'!$1:$104,MATCH(O$4,'3.5.1'!$A:$A,0),MATCH(Summary!$C25,'3.5.1'!$1:$1,0)),"") -> 9998.647 | R25: =_xlfn.IFNA(INDEX('3.5.1'!$1:$104,MATCH(R$4,'3.5.1'!$A:$A,0),MATCH(Summary!$C25,'3.5.1'!$1:$1,0)),"") | U25: =_xlfn.IFNA(INDEX('3.5.1'!$1:$104,MATCH(U$4,'3.5.1'!$A:$A,0),MATCH(Summary!$C25,'3.5.1'!$1:$1,0)),"") | X25: =_xlfn.IFNA(INDEX('3.5.1'!$1:$104,MATCH(X$4,'3.5.1'!$A:$A,0),MATCH(Summary!$C25,'3.5.1'!$1:$1,0)),"") -> 6636.04 | AA25: =_xlfn.IFNA(INDEX('3.5.1'!$1:$104,MATCH(AA$4,'3.5.1'!$A:$A,0),MATCH(Summary!$C25,'3.5.1'!$1:$1,0)),"") | AD25: =_xlfn.IFNA(INDEX('3.5.1'!$1:$104,MATCH(AD$4,'3.5.1'!$A:$A,0),MATCH(Summary!$C25,'3.5.1'!$1:$1,0)),"") | AG25: =_xlfn.IFNA(INDEX('3.5.1'!$1:$104,MATCH(AG$4,'3.5.1'!$A:$A,0),MATCH(Summary!$C25,'3.5.1'!$1:$1,0)),"") -> 6090.297 | AJ25: =_xlfn.IFNA(INDEX('3.5.1'!$1:$104,MATCH(AJ$4,'3.5.1'!$A:$A,0),MATCH(Summary!$C25,'3.5.1'!$1:$1,0)),"") | AM25: =_xlfn.IFNA(INDEX('3.5.1'!$1:$104,MATCH(AM$4,'3.5.1'!$A:$A,0),MATCH(Summary!$C25,'3.5.1'!$1:$1,0)),"") | AP25: =_xlfn.IFNA(INDEX('3.5.1'!$1:$104,MATCH(AP$4,'3.5.1'!$A:$A,0),MATCH(Summary!$C25,'3.5.1'!$1:$1,0)),"") -> 5069.957 | AS25: =_xlfn.IFNA(INDEX('3.5.1'!$1:$104,MATCH(AS$4,'3.5.1'!$A:$A,0),MATCH(Summary!$C25,'3.5.1'!$1:$1,0)),"") | AV25: =_xlfn.IFNA(INDEX('3.5.1'!$1:$104,MATCH(AV$4,'3.5.1'!$A:$A,0),MATCH(Summary!$C25,'3.5.1'!$1:$1,0)),"") | AY25: =_xlfn.IFNA(INDEX('3.5.1'!$1:$104,MATCH(AY$4,'3.5.1'!$A:$A,0),MATCH(Summary!$C25,'3.5.1'!$1:$1,0)),"") -> 5434.78 | BB25: =_xlfn.IFNA(INDEX('3.5.1'!$1:$104,MATCH(BB$4,'3.5.1'!$A:$A,0),MATCH(Summary!$C25,'3.5.1'!$1:$1,0)),"") -> 6571.414 | BE25: =_xlfn.IFNA(INDEX('3.5.1'!$1:$104,MATCH(BE$4,'3.5.1'!$A:$A,0),MATCH(Summary!$C25,'3.5.1'!$1:$1,0)),"") | BH25: =_xlfn.IFNA(INDEX('3.5.1'!$1:$104,MATCH(BH$4,'3.5.1'!$A:$A,0),MATCH(Summary!$C25,'3.5.1'!$1:$1,0)),"") | BK25: =_xlfn.IFNA(INDEX('3.5.1'!$1:$104,MATCH(BK$4,'3.5.1'!$A:$A,0),MATCH(Summary!$C25,'3.5.1'!$1:$1,0)),"")
C26: mfg_ee_other | F26: Others | G26: 其他 | H26: =O26/$O$12 -> 0.0047207863 | I26: =IFERROR(L26/AV26-1,"") | L26: =_xlfn.IFNA(INDEX('3.5.1'!$1:$104,MATCH(L$4,'3.5.1'!$A:$A,0),MATCH(Summary!$C26,'3.5.1'!$1:$1,0)),"") | O26: =_xlfn.IFNA(INDEX('3.5.1'!$1:$104,MATCH(O$4,'3.5.1'!$A:$A,0),MATCH(Summary!$C26,'3.5.1'!$1:$1,0)),"") -> 50927.35 | R26: =_xlfn.IFNA(INDEX('3.5.1'!$1:$104,MATCH(R$4,'3.5.1'!$A:$A,0),MATCH(Summary!$C26,'3.5.1'!$1:$1,0)),"") | U26: =_xlfn.IFNA(INDEX('3.5.1'!$1:$104,MATCH(U$4,'3.5.1'!$A:$A,0),MATCH(Summary!$C26,'3.5.1'!$1:$1,0)),"") | X26: =_xlfn.IFNA(INDEX('3.5.1'!$1:$104,MATCH(X$4,'3.5.1'!$A:$A,0),MATCH(Summary!$C26,'3.5.1'!$1:$1,0)),"") -> 54660.551 | AA26: =_xlfn.IFNA(INDEX('3.5.1'!$1:$104,MATCH(AA$4,'3.5.1'!$A:$A,0),MATCH(Summary!$C26,'3.5.1'!$1:$1,0)),"") | AD26: =_xlfn.IFNA(INDEX('3.5.1'!$1:$104,MATCH(AD$4,'3.5.1'!$A:$A,0),MATCH(Summary!$C26,'3.5.1'!$1:$1,0)),"") | AG26: =_xlfn.IFNA(INDEX('3.5.1'!$1:$104,MATCH(AG$4,'3.5.1'!$A:$A,0),MATCH(Summary!$C26,'3.5.1'!$1:$1,0)),"") -> 48059.887 | AJ26: =_xlfn.IFNA(INDEX('3.5.1'!$1:$104,MATCH(AJ$4,'3.5.1'!$A:$A,0),MATCH(Summary!$C26,'3.5.1'!$1:$1,0)),"") | AM26: =_xlfn.IFNA(INDEX('3.5.1'!$1:$104,MATCH(AM$4,'3.5.1'!$A:$A,0),MATCH(Summary!$C26,'3.5.1'!$1:$1,0)),"") | AP26: =_xlfn.IFNA(INDEX('3.5.1'!$1:$104,MATCH(AP$4,'3.5.1'!$A:$A,0),MATCH(Summary!$C26,'3.5.1'!$1:$1,0)),"") -> 44422.916 | AS26: =_xlfn.IFNA(INDEX('3.5.1'!$1:$104,MATCH(AS$4,'3.5.1'!$A:$A,0),MATCH(Summary!$C26,'3.5.1'!$1:$1,0)),"") | AV26: =_xlfn.IFNA(INDEX('3.5.1'!$1:$104,MATCH(AV$4,'3.5.1'!$A:$A,0),MATCH(Summary!$C26,'3.5.1'!$1:$1,0)),"") | AY26: =_xlfn.IFNA(INDEX('3.5.1'!$1:$104,MATCH(AY$4,'3.5.1'!$A:$A,0),MATCH(Summary!$C26,'3.5.1'!$1:$1,0)),"") -> 46438.408 | BB26: =_xlfn.IFNA(INDEX('3.5.1'!$1:$104,MATCH(BB$4,'3.5.1'!$A:$A,0),MATCH(Summary!$C26,'3.5.1'!$1:$1,0)),"") -> 46051.827 | BE26: =_xlfn.IFNA(INDEX('3.5.1'!$1:$104,MATCH(BE$4,'3.5.1'!$A:$A,0),MATCH(Summary!$C26,'3.5.1'!$1:$1,0)),"") | BH26: =_xlfn.IFNA(INDEX('3.5.1'!$1:$104,MATCH(BH$4,'3.5.1'!$A:$A,0),MATCH(Summary!$C26,'3.5.1'!$1:$1,0)),"") | BK26: =_xlfn.IFNA(INDEX('3.5.1'!$1:$104,MATCH(BK$4,'3.5.1'!$A:$A,0),MATCH(Summary!$C26,'3.5.1'!$1:$1,0)),"")
C27: mfg_food | F27: Food | G27: 食品 | H27: =O27/$O$12 -> 0.0023406006 | I27: =IFERROR(L27/AV27-1,"") | L27: =_xlfn.IFNA(INDEX('3.5.1'!$1:$104,MATCH(L$4,'3.5.1'!$A:$A,0),MATCH(Summary!$C27,'3.5.1'!$1:$1,0)),"") | O27: =_xlfn.IFNA(INDEX('3.5.1'!$1:$104,MATCH(O$4,'3.5.1'!$A:$A,0),MATCH(Summary!$C27,'3.5.1'!$1:$1,0)),"") -> 25250.155 | R27: =_xlfn.IFNA(INDEX('3.5.1'!$1:$104,MATCH(R$4,'3.5.1'!$A:$A,0),MATCH(Summary!$C27,'3.5.1'!$1:$1,0)),"") | U27: =_xlfn.IFNA(INDEX('3.5.1'!$1:$104,MATCH(U$4,'3.5.1'!$A:$A,0),MATCH(Summary!$C27,'3.5.1'!$1:$1,0)),"") | X27: =_xlfn.IFNA(INDEX('3.5.1'!$1:$104,MATCH(X$4,'3.5.1'!$A:$A,0),MATCH(Summary!$C27,'3.5.1'!$1:$1,0)),"") -> 21536.222 | AA27: =_xlfn.IFNA(INDEX('3.5.1'!$1:$104,MATCH(AA$4,'3.5.1'!$A:$A,0),MATCH(Summary!$C27,'3.5.1'!$1:$1,0)),"") | AD27: =_xlfn.IFNA(INDEX('3.5.1'!$1:$104,MATCH(AD$4,'3.5.1'!$A:$A,0),MATCH(Summary!$C27,'3.5.1'!$1:$1,0)),"") | AG27: =_xlfn.IFNA(INDEX('3.5.1'!$1:$104,MATCH(AG$4,'3.5.1'!$A:$A,0),MATCH(Summary!$C27,'3.5.1'!$1:$1,0)),"") -> 21795.043 | AJ27: =_xlfn.IFNA(INDEX('3.5.1'!$1:$104,MATCH(AJ$4,'3.5.1'!$A:$A,0),MATCH(Summary!$C27,'3.5.1'!$1:$1,0)),"") | AM27: =_xlfn.IFNA(INDEX('3.5.1'!$1:$104,MATCH(AM$4,'3.5.1'!$A:$A,0),MATCH(Summary!$C27,'3.5.1'!$1:$1,0)),"") | AP27: =_xlfn.IFNA(INDEX('3.5.1'!$1:$104,MATCH(AP$4,'3.5.1'!$A:$A,0),MATCH(Summary!$C27,'3.5.1'!$1:$1,0)),"") -> 26661.418 | AS27: =_xlfn.IFNA(INDEX('3.5.1'!$1:$104,MATCH(AS$4,'3.5.1'!$A:$A,0),MATCH(Summary!$C27,'3.5.1'!$1:$1,0)),"") | AV27: =_xlfn.IFNA(INDEX('3.5.1'!$1:$104,MATCH(AV$4,'3.5.1'!$A:$A,0),MATCH(Summary!$C27,'3.5.1'!$1:$1,0)),"") | AY27: =_xlfn.IFNA(INDEX('3.5.1'!$1:$104,MATCH(AY$4,'3.5.1'!$A:$A,0),MATCH(Summary!$C27,'3.5.1'!$1:$1,0)),"") -> 26633.559 | BB27: =_xlfn.IFNA(INDEX('3.5.1'!$1:$104,MATCH(BB$4,'3.5.1'!$A:$A,0),MATCH(Summary!$C27,'3.5.1'!$1:$1,0)),"") -> 23465.175 | BE27: =_xlfn.IFNA(INDEX('3.5.1'!$1:$104,MATCH(BE$4,'3.5.1'!$A:$A,0),MATCH(Summary!$C27,'3.5.1'!$1:$1,0)),"") | BH27: =_xlfn.IFNA(INDEX('3.5.1'!$1:$104,MATCH(BH$4,'3.5.1'!$A:$A,0),MATCH(Summary!$C27,'3.5.1'!$1:$1,0)),"") | BK27: =_xlfn.IFNA(INDEX('3.5.1'!$1:$104,MATCH(BK$4,'3.5.1'!$A:$A,0),MATCH(Summary!$C27,'3.5.1'!$1:$1,0)),"")
C28: mfg_bevtob | F28: Beverages and tobacco | G28: 飲料及煙草 | H28: =O28/$O$12 -> 0.0016299045 | I28: =IFERROR(L28/AV28-1,"") | L28: =_xlfn.IFNA(INDEX('3.5.1'!$1:$104,MATCH(L$4,'3.5.1'!$A:$A,0),MATCH(Summary!$C28,'3.5.1'!$1:$1,0)),"") | O28: =_xlfn.IFNA(INDEX('3.5.1'!$1:$104,MATCH(O$4,'3.5.1'!$A:$A,0),MATCH(Summary!$C28,'3.5.1'!$1:$1,0)),"") -> 17583.24 | R28: =_xlfn.IFNA(INDEX('3.5.1'!$1:$104,MATCH(R$4,'3.5.1'!$A:$A,0),MATCH(Summary!$C28,'3.5.1'!$1:$1,0)),"") | U28: =_xlfn.IFNA(INDEX('3.5.1'!$1:$104,MATCH(U$4,'3.5.1'!$A:$A,0),MATCH(Summary!$C28,'3.5.1'!$1:$1,0)),"") | X28: =_xlfn.IFNA(INDEX('3.5.1'!$1:$104,MATCH(X$4,'3.5.1'!$A:$A,0),MATCH(Summary!$C28,'3.5.1'!$1:$1,0)),"") -> 13861.623 | AA28: =_xlfn.IFNA(INDEX('3.5.1'!$1:$104,MATCH(AA$4,'3.5.1'!$A:$A,0),MATCH(Summary!$C28,'3.5.1'!$1:$1,0)),"") | AD28: =_xlfn.IFNA(INDEX('3.5.1'!$1:$104,MATCH(AD$4,'3.5.1'!$A:$A,0),MATCH(Summary!$C28,'3.5.1'!$1:$1,0)),"") | AG28: =_xlfn.IFNA(INDEX('3.5.1'!$1:$104,MATCH(AG$4,'3.5.1'!$A:$A,0),MATCH(Summary!$C28,'3.5.1'!$1:$1,0)),"") -> 10977.891 | AJ28: =_xlfn.IFNA(INDEX('3.5.1'!$1:$104,MATCH(AJ$4,'3.5.1'!$A:$A,0),MATCH(Summary!$C28,'3.5.1'!$1:$1,0)),"") | AM28: =_xlfn.IFNA(INDEX('3.5.1'!$1:$104,MATCH(AM$4,'3.5.1'!$A:$A,0),MATCH(Summary!$C28,'3.5.1'!$1:$1,0)),"") | AP28: =_xlfn.IFNA(INDEX('3.5.1'!$1:$104,MATCH(AP$4,'3.5.1'!$A:$A,0),MATCH(Summary!$C28,'3.5.1'!$1:$1,0)),"") -> 14172.343 | AS28: =_xlfn.IFNA(INDEX('3.5.1'!$1:$104,MATCH(AS$4,'3.5.1'!$A:$A,0),MATCH(Summary!$C28,'3.5.1'!$1:$1,0)),"") | AV28: =_xlfn.IFNA(INDEX('3.5.1'!$1:$104,MATCH(AV$4,'3.5.1'!$A:$A,0),MATCH(Summary!$C28,'3.5.1'!$1:$1,0)),"") | AY28: =_xlfn.IFNA(INDEX('3.5.1'!$1:$104,MATCH(AY$4,'3.5.1'!$A:$A,0),MATCH(Summary!$C28,'3.5.1'!$1:$1,0)),"") -> 12774.037 | BB28: =_xlfn.IFNA(INDEX('3.5.1'!$1:$104,MATCH(BB$4,'3.5.1'!$A:$A,0),MATCH(Summary!$C28,'3.5.1'!$1:$1,0)),"") -> 13452.56 | BE28: =_xlfn.IFNA(INDEX('3.5.1'!$1:$104,MATCH(BE$4,'3.5.1'!$A:$A,0),MATCH(Summary!$C28,'3.5.1'!$1:$1,0)),"") | BH28: =_xlfn.IFNA(INDEX('3.5.1'!$1:$104,MATCH(BH$4,'3.5.1'!$A:$A,0),MATCH(Summary!$C28,'3.5.1'!$1:$1,0)),"") | BK28: =_xlfn.IFNA(INDEX('3.5.1'!$1:$104,MATCH(BK$4,'3.5.1'!$A:$A,0),MATCH(Summary!$C28,'3.5.1'!$1:$1,0)),"")
C29: mfg_printpub | F29: Printing and publishing | G29: 印刷及出版 | H29: =O29/$O$12 -> 0.0004226625 | I29: =IFERROR(L29/AV29-1,"") | L29: =_xlfn.IFNA(INDEX('3.5.1'!$1:$104,MATCH(L$4,'3.5.1'!$A:$A,0),MATCH(Summary!$C29,'3.5.1'!$1:$1,0)),"") | O29: =_xlfn.IFNA(INDEX('3.5.1'!$1:$104,MATCH(O$4,'3.5.1'!$A:$A,0),MATCH(Summary!$C29,'3.5.1'!$1:$1,0)),"") -> 4559.639 | R29: =_xlfn.IFNA(INDEX('3.5.1'!$1:$104,MATCH(R$4,'3.5.1'!$A:$A,0),MATCH(Summary!$C29,'3.5.1'!$1:$1,0)),"") | U29: =_xlfn.IFNA(INDEX('3.5.1'!$1:$104,MATCH(U$4,'3.5.1'!$A:$A,0),MATCH(Summary!$C29,'3.5.1'!$1:$1,0)),"") | X29: =_xlfn.IFNA(INDEX('3.5.1'!$1:$104,MATCH(X$4,'3.5.1'!$A:$A,0),MATCH(Summary!$C29,'3.5.1'!$1:$1,0)),"") -> 4752.796 | AA29: =_xlfn.IFNA(INDEX('3.5.1'!$1:$104,MATCH(AA$4,'3.5.1'!$A:$A,0),MATCH(Summary!$C29,'3.5.1'!$1:$1,0)),"") | AD29: =_xlfn.IFNA(INDEX('3.5.1'!$1:$104,MATCH(AD$4,'3.5.1'!$A:$A,0),MATCH(Summary!$C29,'3.5.1'!$1:$1,0)),"") | AG29: =_xlfn.IFNA(INDEX('3.5.1'!$1:$104,MATCH(AG$4,'3.5.1'!$A:$A,0),MATCH(Summary!$C29,'3.5.1'!$1:$1,0)),"") -> 4592.36 | AJ29: =_xlfn.IFNA(INDEX('3.5.1'!$1:$104,MATCH(AJ$4,'3.5.1'!$A:$A,0),MATCH(Summary!$C29,'3.5.1'!$1:$1,0)),"") | AM29: =_xlfn.IFNA(INDEX('3.5.1'!$1:$104,MATCH(AM$4,'3.5.1'!$A:$A,0),MATCH(Summary!$C29,'3.5.1'!$1:$1,0)),"") | AP29: =_xlfn.IFNA(INDEX('3.5.1'!$1:$104,MATCH(AP$4,'3.5.1'!$A:$A,0),MATCH(Summary!$C29,'3.5.1'!$1:$1,0)),"") -> 4926.074 | AS29: =_xlfn.IFNA(INDEX('3.5.1'!$1:$104,MATCH(AS$4,'3.5.1'!$A:$A,0),MATCH(Summary!$C29,'3.5.1'!$1:$1,0)),"") | AV29: =_xlfn.IFNA(INDEX('3.5.1'!$1:$104,MATCH(AV$4,'3.5.1'!$A:$A,0),MATCH(Summary!$C29,'3.5.1'!$1:$1,0)),"") | AY29: =_xlfn.IFNA(INDEX('3.5.1'!$1:$104,MATCH(AY$4,'3.5.1'!$A:$A,0),MATCH(Summary!$C29,'3.5.1'!$1:$1,0)),"") -> 4869.311 | BB29: =_xlfn.IFNA(INDEX('3.5.1'!$1:$104,MATCH(BB$4,'3.5.1'!$A:$A,0),MATCH(Summary!$C29,'3.5.1'!$1:$1,0)),"") -> 4312.302 | BE29: =_xlfn.IFNA(INDEX('3.5.1'!$1:$104,MATCH(BE$4,'3.5.1'!$A:$A,0),MATCH(Summary!$C29,'3.5.1'!$1:$1,0)),"") | BH29: =_xlfn.IFNA(INDEX('3.5.1'!$1:$104,MATCH(BH$4,'3.5.1'!$A:$A,0),MATCH(Summary!$C29,'3.5.1'!$1:$1,0)),"") | BK29: =_xlfn.IFNA(INDEX('3.5.1'!$1:$104,MATCH(BK$4,'3.5.1'!$A:$A,0),MATCH(Summary!$C29,'3.5.1'!$1:$1,0)),"")
... C66: misc_prof_purschflat | F66: For the purchase of flats in Home Ownership | G66: 購買「居者有其屋計劃」、「私人機構 | H66: =O66/$O$12 -> 0.015537359 | I66: =IFERROR(L66/AV66-1,"") | L66: =_xlfn.IFNA(INDEX('3.5.1'!$1:$104,MATCH(L$4,'3.5.1'!$A:$A,0),MATCH(Summary!$C66,'3.5.1'!$1:$1,0)),"") | O66: =_xlfn.IFNA(INDEX('3.5.1'!$1:$104,MATCH(O$4,'3.5.1'!$A:$A,0),MATCH(Summary!$C66,'3.5.1'!$1:$1,0)),"") -> 167615.41 | R66: =_xlfn.IFNA(INDEX('3.5.1'!$1:$104,MATCH(R$4,'3.5.1'!$A:$A,0),MATCH(Summary!$C66,'3.5.1'!$1:$1,0)),"") | U66: =_xlfn.IFNA(INDEX('3.5.1'!$1:$104,MATCH(U$4,'3.5.1'!$A:$A,0),MATCH(Summary!$C66,'3.5.1'!$1:$1,0)),"") | X66: =_xlfn.IFNA(INDEX('3.5.1'!$1:$104,MATCH(X$4,'3.5.1'!$A:$A,0),MATCH(Summary!$C66,'3.5.1'!$1:$1,0)),"") -> 156519.89 | AA66: =_xlfn.IFNA(INDEX('3.5.1'!$1:$104,MATCH(AA$4,'3.5.1'!$A:$A,0),MATCH(Summary!$C66,'3.5.1'!$1:$1,0)),"") | AD66: =_xlfn.IFNA(INDEX('3.5.1'!$1:$104,MATCH(AD$4,'3.5.1'!$A:$A,0),MATCH(Summary!$C66,'3.5.1'!$1:$1,0)),"") | AG66: =_xlfn.IFNA(INDEX('3.5.1'!$1:$104,MATCH(AG$4,'3.5.1'!$A:$A,0),MATCH(Summary!$C66,'3.5.1'!$1:$1,0)),"") -> 153280.41 | AJ66: =_xlfn.IFNA(INDEX('3.5.1'!$1:$104,MATCH(AJ$4,'3.5.1'!$A:$A,0),MATCH(Summary!$C66,'3.5.1'!$1:$1,0)),"") | AM66: =_xlfn.IFNA(INDEX('3.5.1'!$1:$104,MATCH(AM$4,'3.5.1'!$A:$A,0),MATCH(Summary!$C66,'3.5.1'!$1:$1,0)),"") | AP66: =_xlfn.IFNA(INDEX('3.5.1'!$1:$104,MATCH(AP$4,'3.5.1'!$A:$A,0),MATCH(Summary!$C66,'3.5.1'!$1:$1,0)),"") -> 152236.39 | AS66: =_xlfn.IFNA(INDEX('3.5.1'!$1:$104,MATCH(AS$4,'3.5.1'!$A:$A,0),MATCH(Summary!$C66,'3.5.1'!$1:$1,0)),"") | AV66: =_xlfn.IFNA(INDEX('3.5.1'!$1:$104,MATCH(AV$4,'3.5.1'!$A:$A,0),MATCH(Summary!$C66,'3.5.1'!$1:$1,0)),"") | AY66: =_xlfn.IFNA(INDEX('3.5.1'!$1:$104,MATCH(AY$4,'3.5.1'!$A:$A,0),MATCH(Summary!$C66,'3.5.1'!$1:$1,0)),"") -> 141918.08 | BB66: =_xlfn.IFNA(INDEX('3.5.1'!$1:$104,MATCH(BB$4,'3.5.1'!$A:$A,0),MATCH(Summary!$C66,'3.5.1'!$1:$1,0)),"") -> 132720.03 | BE66: =_xlfn.IFNA(INDEX('3.5.1'!$1:$104,MATCH(BE$4,'3.5.1'!$A:$A,0),MATCH(Summary!$C66,'3.5.1'!$1:$1,0)),"") | BH66: =_xlfn.IFNA(INDEX('3.5.1'!$1:$104,MATCH(BH$4,'3.5.1'!$A:$A,0),MATCH(Summary!$C66,'3.5.1'!$1:$1,0)),"") | BK66: =_xlfn.IFNA(INDEX('3.5.1'!$1:$104,MATCH(BK$4,'3.5.1'!$A:$A,0),MATCH(Summary!$C66,'3.5.1'!$1:$1,0)),"")
F67: Scheme, Private Sector Participation | G67: 參建居屋計劃」及「租者置其屋計劃」 | H67: =O67/$O$12 -> 0 | I67: =IFERROR(L67/AV67-1,"")
F68: Scheme & Tenants Purchase Scheme | G68: 單位 | H68: =O68/$O$12 -> 0 | I68: =IFERROR(L68/AV68-1,"")
C69: misc_prof_purother | F69: For the purchase of other residential properties | G69: 購買其他住宅樓宇 | H69: =O69/$O$12 -> 0.18153148 | I69: =IFERROR(L69/AV69-1,"") | L69: =_xlfn.IFNA(INDEX('3.5.1'!$1:$104,MATCH(L$4,'3.5.1'!$A:$A,0),MATCH(Summary!$C69,'3.5.1'!$1:$1,0)),"") | O69: =_xlfn.IFNA(INDEX('3.5.1'!$1:$104,MATCH(O$4,'3.5.1'!$A:$A,0),MATCH(Summary!$C69,'3.5.1'!$1:$1,0)),"") -> 1958342.7 | R69: =_xlfn.IFNA(INDEX('3.5.1'!$1:$104,MATCH(R$4,'3.5.1'!$A:$A,0),MATCH(Summary!$C69,'3.5.1'!$1:$1,0)),"") | U69: =_xlfn.IFNA(INDEX('3.5.1'!$1:$104,MATCH(U$4,'3.5.1'!$A:$A,0),MATCH(Summary!$C69,'3.5.1'!$1:$1,0)),"") | X69: =_xlfn.IFNA(INDEX('3.5.1'!$1:$104,MATCH(X$4,'3.5.1'!$A:$A,0),MATCH(Summary!$C69,'3.5.1'!$1:$1,0)),"") -> 1937565.9 | AA69: =_xlfn.IFNA(INDEX('3.5.1'!$1:$104,MATCH(AA$4,'3.5.1'!$A:$A,0),MATCH(Summary!$C69,'3.5.1'!$1:$1,0)),"") | AD69: =_xlfn.IFNA(INDEX('3.5.1'!$1:$104,MATCH(AD$4,'3.5.1'!$A:$A,0),MATCH(Summary!$C69,'3.5.1'!$1:$1,0)),"") | AG69: =_xlfn.IFNA(INDEX('3.5.1'!$1:$104,MATCH(AG$4,'3.5.1'!$A:$A,0),MATCH(Summary!$C69,'3.5.1'!$1:$1,0)),"") -> 1920476.5 | AJ69: =_xlfn.IFNA(INDEX('3.5.1'!$1:$104,MATCH(AJ$4,'3.5.1'!$A:$A,0),MATCH(Summary!$C69,'3.5.1'!$1:$1,0)),"") | AM69: =_xlfn.IFNA(INDEX('3.5.1'!$1:$104,MATCH(AM$4,'3.5.1'!$A:$A,0),MATCH(Summary!$C69,'3.5.1'!$1:$1,0)),"") | AP69: =_xlfn.IFNA(INDEX('3.5.1'!$1:$104,MATCH(AP$4,'3.5.1'!$A:$A,0),MATCH(Summary!$C69,'3.5.1'!$1:$1,0)),"") -> 1894347 | AS69: =_xlfn.IFNA(INDEX('3.5.1'!$1:$104,MATCH(AS$4,'3.5.1'!$A:$A,0),MATCH(Summary!$C69,'3.5.1'!$1:$1,0)),"") | AV69: =_xlfn.IFNA(INDEX('3.5.1'!$1:$104,MATCH(AV$4,'3.5.1'!$A:$A,0),MATCH(Summary!$C69,'3.5.1'!$1:$1,0)),"") | AY69: =_xlfn.IFNA(INDEX('3.5.1'!$1:$104,MATCH(AY$4,'3.5.1'!$A:$A,0),MATCH(Summary!$C69,'3.5.1'!$1:$1,0)),"") -> 1889329.5 | BB69: =_xlfn.IFNA(INDEX('3.5.1'!$1:$104,MATCH(BB$4,'3.5.1'!$A:$A,0),MATCH(Summary!$C69,'3.5.1'!$1:$1,0)),"") -> 1873532.5 | BE69: =_xlfn.IFNA(INDEX('3.5.1'!$1:$104,MATCH(BE$4,'3.5.1'!$A:$A,0),MATCH(Summary!$C69,'3.5.1'!$1:$1,0)),"") | BH69: =_xlfn.IFNA(INDEX('3.5.1'!$1:$104,MATCH(BH$4,'3.5.1'!$A:$A,0),MATCH(Summary!$C69,'3.5.1'!$1:$1,0)),"") | BK69: =_xlfn.IFNA(INDEX('3.5.1'!$1:$104,MATCH(BK$4,'3.5.1'!$A:$A,0),MATCH(Summary!$C69,'3.5.1'!$1:$1,0)),"")
C70: misc_prof_ccadv | F70: For credit card advances | G70: 信用卡墊款 | H70: =O70/$O$12 -> 0.013793243 | I70: =IFERROR(L70/AV70-1,"") | L70: =_xlfn.IFNA(INDEX('3.5.1'!$1:$104,MATCH(L$4,'3.5.1'!$A:$A,0),MATCH(Summary!$C70,'3.5.1'!$1:$1,0)),"") | O70: =_xlfn.IFNA(INDEX('3.5.1'!$1:$104,MATCH(O$4,'3.5.1'!$A:$A,0),MATCH(Summary!$C70,'3.5.1'!$1:$1,0)),"") -> 148800.06 | R70: =_xlfn.IFNA(INDEX('3.5.1'!$1:$104,MATCH(R$4,'3.5.1'!$A:$A,0),MATCH(Summary!$C70,'3.5.1'!$1:$1,0)),"") | U70: =_xlfn.IFNA(INDEX('3.5.1'!$1:$104,MATCH(U$4,'3.5.1'!$A:$A,0),MATCH(Summary!$C70,'3.5.1'!$1:$1,0)),"") | X70: =_xlfn.IFNA(INDEX('3.5.1'!$1:$104,MATCH(X$4,'3.5.1'!$A:$A,0),MATCH(Summary!$C70,'3.5.1'!$1:$1,0)),"") -> 151892.1 | AA70: =_xlfn.IFNA(INDEX('3.5.1'!$1:$104,MATCH(AA$4,'3.5.1'!$A:$A,0),MATCH(Summary!$C70,'3.5.1'!$1:$1,0)),"") | AD70: =_xlfn.IFNA(INDEX('3.5.1'!$1:$104,MATCH(AD$4,'3.5.1'!$A:$A,0),MATCH(Summary!$C70,'3.5.1'!$1:$1,0)),"") | AG70: =_xlfn.IFNA(INDEX('3.5.1'!$1:$104,MATCH(AG$4,'3.5.1'!$A:$A,0),MATCH(Summary!$C70,'3.5.1'!$1:$1,0)),"") -> 157738.37 | AJ70: =_xlfn.IFNA(INDEX('3.5.1'!$1:$104,MATCH(AJ$4,'3.5.1'!$A:$A,0),MATCH(Summary!$C70,'3.5.1'!$1:$1,0)),"") | AM70: =_xlfn.IFNA(INDEX('3.5.1'!$1:$104,MATCH(AM$4,'3.5.1'!$A:$A,0),MATCH(Summary!$C70,'3.5.1'!$1:$1,0)),"") | AP70: =_xlfn.IFNA(INDEX('3.5.1'!$1:$104,MATCH(AP$4,'3.5.1'!$A:$A,0),MATCH(Summary!$C70,'3.5.1'!$1:$1,0)),"") -> 145656.06 | AS70: =_xlfn.IFNA(INDEX('3.5.1'!$1:$104,MATCH(AS$4,'3.5.1'!$A:$A,0),MATCH(Summary!$C70,'3.5.1'!$1:$1,0)),"") | AV70: =_xlfn.IFNA(INDEX('3.5.1'!$1:$104,MATCH(AV$4,'3.5.1'!$A:$A,0),MATCH(Summary!$C70,'3.5.1'!$1:$1,0)),"") | AY70: =_xlfn.IFNA(INDEX('3.5.1'!$1:$104,MATCH(AY$4,'3.5.1'!$A:$A,0),MATCH(Summary!$C70,'3.5.1'!$1:$1,0)),"") -> 143687.94 | BB70: =_xlfn.IFNA(INDEX('3.5.1'!$1:$104,MATCH(BB$4,'3.5.1'!$A:$A,0),MATCH(Summary!$C70,'3.5.1'!$1:$1,0)),"") -> 154585.22 | BE70: =_xlfn.IFNA(INDEX('3.5.1'!$1:$104,MATCH(BE$4,'3.5.1'!$A:$A,0),MATCH(Summary!$C70,'3.5.1'!$1:$1,0)),"") | BH70: =_xlfn.IFNA(INDEX('3.5.1'!$1:$104,MATCH(BH$4,'3.5.1'!$A:$A,0),MATCH(Summary!$C70,'3.5.1'!$1:$1,0)),"") | BK70: =_xlfn.IFNA(INDEX('3.5.1'!$1:$104,MATCH(BK$4,'3.5.1'!$A:$A,0),MATCH(Summary!$C70,'3.5.1'!$1:$1,0)),"")
C71: misc_prof_otherbusi | F71: For other business purposes | G71: 其他商業用途 | H71: =O71/$O$12 -> 0.00070291605 | I71: =IFERROR(L71/AV71-1,"") | L71: =_xlfn.IFNA(INDEX('3.5.1'!$1:$104,MATCH(L$4,'3.5.1'!$A:$A,0),MATCH(Summary!$C71,'3.5.1'!$1:$1,0)),"") | O71: =_xlfn.IFNA(INDEX('3.5.1'!$1:$104,MATCH(O$4,'3.5.1'!$A:$A,0),MATCH(Summary!$C71,'3.5.1'!$1:$1,0)),"") -> 7582.985 | R71: =_xlfn.IFNA(INDEX('3.5.1'!$1:$104,MATCH(R$4,'3.5.1'!$A:$A,0),MATCH(Summary!$C71,'3.5.1'!$1:$1,0)),"") | U71: =_xlfn.IFNA(INDEX('3.5.1'!$1:$104,MATCH(U$4,'3.5.1'!$A:$A,0),MATCH(Summary!$C71,'3.5.1'!$1:$1,0)),"") | X71: =_xlfn.IFNA(INDEX('3.5.1'!$1:$104,MATCH(X$4,'3.5.1'!$A:$A,0),MATCH(Summary!$C71,'3.5.1'!$1:$1,0)),"") -> 6885.071 | AA71: =_xlfn.IFNA(INDEX('3.5.1'!$1:$104,MATCH(AA$4,'3.5.1'!$A:$A,0),MATCH(Summary!$C71,'3.5.1'!$1:$1,0)),"") | AD71: =_xlfn.IFNA(INDEX('3.5.1'!$1:$104,MATCH(AD$4,'3.5.1'!$A:$A,0),MATCH(Summary!$C71,'3.5.1'!$1:$1,0)),"") | AG71: =_xlfn.IFNA(INDEX('3.5.1'!$1:$104,MATCH(AG$4,'3.5.1'!$A:$A,0),MATCH(Summary!$C71,'3.5.1'!$1:$1,0)),"") -> 5630.61 | AJ71: =_xlfn.IFNA(INDEX('3.5.1'!$1:$104,MATCH(AJ$4,'3.5.1'!$A:$A,0),MATCH(Summary!$C71,'3.5.1'!$1:$1,0)),"") | AM71: =_xlfn.IFNA(INDEX('3.5.1'!$1:$104,MATCH(AM$4,'3.5.1'!$A:$A,0),MATCH(Summary!$C71,'3.5.1'!$1:$1,0)),"") | AP71: =_xlfn.IFNA(INDEX('3.5.1'!$1:$104,MATCH(AP$4,'3.5.1'!$A:$A,0),MATCH(Summary!$C71,'3.5.1'!$1:$1,0)),"") -> 5576.78 | AS71: =_xlfn.IFNA(INDEX('3.5.1'!$1:$104,MATCH(AS$4,'3.5.1'!$A:$A,0),MATCH(Summary!$C71,'3.5.1'!$1:$1,0)),"") | AV71: =_xlfn.IFNA(INDEX('3.5.1'!$1:$104,MATCH(AV$4,'3.5.1'!$A:$A,0),MATCH(Summary!$C71,'3.5.1'!$1:$1,0)),"") | AY71: =_xlfn.IFNA(INDEX('3.5.1'!$1:$104,MATCH(AY$4,'3.5.1'!$A:$A,0),MATCH(Summary!$C71,'3.5.1'!$1:$1,0)),"") -> 5638.183 | BB71: =_xlfn.IFNA(INDEX('3.5.1'!$1:$104,MATCH(BB$4,'3.5.1'!$A:$A,0),MATCH(Summary!$C71,'3.5.1'!$1:$1,0)),"") -> 5403.246 | BE71: =_xlfn.IFNA(INDEX('3.5.1'!$1:$104,MATCH(BE$4,'3.5.1'!$A:$A,0),MATCH(Summary!$C71,'3.5.1'!$1:$1,0)),"") | BH71: =_xlfn.IFNA(INDEX('3.5.1'!$1:$104,MATCH(BH$4,'3.5.1'!$A:$A,0),MATCH(Summary!$C71,'3.5.1'!$1:$1,0)),"") | BK71: =_xlfn.IFNA(INDEX('3.5.1'!$1:$104,MATCH(BK$4,'3.5.1'!$A:$A,0),MATCH(Summary!$C71,'3.5.1'!$1:$1,0)),"")
C72: misc_prof_otherpvt | F72: For other private purposes | G72: 其他私人用途 | H72: =O72/$O$12 -> 0.073617478 | I72: =IFERROR(L72/AV72-1,"") | L72: =_xlfn.IFNA(INDEX('3.5.1'!$1:$104,MATCH(L$4,'3.5.1'!$A:$A,0),MATCH(Summary!$C72,'3.5.1'!$1:$1,0)),"") | O72: =_xlfn.IFNA(INDEX('3.5.1'!$1:$104,MATCH(O$4,'3.5.1'!$A:$A,0),MATCH(Summary!$C72,'3.5.1'!$1:$1,0)),"") -> 794177.67 | R72: =_xlfn.IFNA(INDEX('3.5.1'!$1:$104,MATCH(R$4,'3.5.1'!$A:$A,0),MATCH(Summary!$C72,'3.5.1'!$1:$1,0)),"") | U72: =_xlfn.IFNA(INDEX('3.5.1'!$1:$104,MATCH(U$4,'3.5.1'!$A:$A,0),MATCH(Summary!$C72,'3.5.1'!$1:$1,0)),"") | X72: =_xlfn.IFNA(INDEX('3.5.1'!$1:$104,MATCH(X$4,'3.5.1'!$A:$A,0),MATCH(Summary!$C72,'3.5.1'!$1:$1,0)),"") -> 748476.8 | AA72: =_xlfn.IFNA(INDEX('3.5.1'!$1:$104,MATCH(AA$4,'3.5.1'!$A:$A,0),MATCH(Summary!$C72,'3.5.1'!$1:$1,0)),"") | AD72: =_xlfn.IFNA(INDEX('3.5.1'!$1:$104,MATCH(AD$4,'3.5.1'!$A:$A,0),MATCH(Summary!$C72,'3.5.1'!$1:$1,0)),"") | AG72: =_xlfn.IFNA(INDEX('3.5.1'!$1:$104,MATCH(AG$4,'3.5.1'!$A:$A,0),MATCH(Summary!$C72,'3.5.1'!$1:$1,0)),"") -> 685669.35 | AJ72: =_xlfn.IFNA(INDEX('3.5.1'!$1:$104,MATCH(AJ$4,'3.5.1'!$A:$A,0),MATCH(Summary!$C72,'3.5.1'!$1:$1,0)),"") | AM72: =_xlfn.IFNA(INDEX('3.5.1'!$1:$104,MATCH(AM$4,'3.5.1'!$A:$A,0),MATCH(Summary!$C72,'3.5.1'!$1:$1,0)),"") | AP72: =_xlfn.IFNA(INDEX('3.5.1'!$1:$104,MATCH(AP$4,'3.5.1'!$A:$A,0),MATCH(Summary!$C72,'3.5.1'!$1:$1,0)),"") -> 682089.89 | AS72: =_xlfn.IFNA(INDEX('3.5.1'!$1:$104,MATCH(AS$4,'3.5.1'!$A:$A,0),MATCH(Summary!$C72,'3.5.1'!$1:$1,0)),"") | AV72: =_xlfn.IFNA(INDEX('3.5.1'!$1:$104,MATCH(AV$4,'3.5.1'!$A:$A,0),MATCH(Summary!$C72,'3.5.1'!$1:$1,0)),"") | AY72: =_xlfn.IFNA(INDEX('3.5.1'!$1:$104,MATCH(AY$4,'3.5.1'!$A:$A,0),MATCH(Summary!$C72,'3.5.1'!$1:$1,0)),"") -> 664951.66 | BB72: =_xlfn.IFNA(INDEX('3.5.1'!$1:$104,MATCH(BB$4,'3.5.1'!$A:$A,0),MATCH(Summary!$C72,'3.5.1'!$1:$1,0)),"") -> 629430.8 | BE72: =_xlfn.IFNA(INDEX('3.5.1'!$1:$104,MATCH(BE$4,'3.5.1'!$A:$A,0),MATCH(Summary!$C72,'3.5.1'!$1:$1,0)),"") | BH72: =_xlfn.IFNA(INDEX('3.5.1'!$1:$104,MATCH(BH$4,'3.5.1'!$A:$A,0),MATCH(Summary!$C72,'3.5.1'!$1:$1,0)),"") | BK72: =_xlfn.IFNA(INDEX('3.5.1'!$1:$104,MATCH(BK$4,'3.5.1'!$A:$A,0),MATCH(Summary!$C72,'3.5.1'!$1:$1,0)),"")
C73: misc_allother | F73: All others | G73: 其他 | H73: =O73/$O$12 -> 0.042870153 | I73: =IFERROR(L73/AV73-1,"") | L73: =_xlfn.IFNA(INDEX('3.5.1'!$1:$104,MATCH(L$4,'3.5.1'!$A:$A,0),MATCH(Summary!$C73,'3.5.1'!$1:$1,0)),"") | O73: =_xlfn.IFNA(INDEX('3.5.1'!$1:$104,MATCH(O$4,'3.5.1'!$A:$A,0),MATCH(Summary!$C73,'3.5.1'!$1:$1,0)),"") -> 462478.74 | R73: =_xlfn.IFNA(INDEX('3.5.1'!$1:$104,MATCH(R$4,'3.5.1'!$A:$A,0),MATCH(Summary!$C73,'3.5.1'!$1:$1,0)),"") | U73: =_xlfn.IFNA(INDEX('3.5.1'!$1:$104,MATCH(U$4,'3.5.1'!$A:$A,0),MATCH(Summary!$C73,'3.5.1'!$1:$1,0)),"") | X73: =_xlfn.IFNA(INDEX('3.5.1'!$1:$104,MATCH(X$4,'3.5.1'!$A:$A,0),MATCH(Summary!$C73,'3.5.1'!$1:$1,0)),"") -> 475615.77 | AA73: =_xlfn.IFNA(INDEX('3.5.1'!$1:$104,MATCH(AA$4,'3.5.1'!$A:$A,0),MATCH(Summary!$C73,'3.5.1'!$1:$1,0)),"") | AD73: =_xlfn.IFNA(INDEX('3.5.1'!$1:$104,MATCH(AD$4,'3.5.1'!$A:$A,0),MATCH(Summary!$C73,'3.5.1'!$1:$1,0)),"") | AG73: =_xlfn.IFNA(INDEX('3.5.1'!$1:$104,MATCH(AG$4,'3.5.1'!$A:$A,0),MATCH(Summary!$C73,'3.5.1'!$1:$1,0)),"") -> 467099.3 | AJ73: =_xlfn.IFNA(INDEX('3.5.1'!$1:$104,MATCH(AJ$4,'3.5.1'!$A:$A,0),MATCH(Summary!$C73,'3.5.1'!$1:$1,0)),"") | AM73: =_xlfn.IFNA(INDEX('3.5.1'!$1:$104,MATCH(AM$4,'3.5.1'!$A:$A,0),MATCH(Summary!$C73,'3.5.1'!$1:$1,0)),"") | AP73: =_xlfn.IFNA(INDEX('3.5.1'!$1:$104,MATCH(AP$4,'3.5.1'!$A:$A,0),MATCH(Summary!$C73,'3.5.1'!$1:$1,0)),"") -> 457491.53 | AS73: =_xlfn.IFNA(INDEX('3.5.1'!$1:$104,MATCH(AS$4,'3.5.1'!$A:$A,0),MATCH(Summary!$C73,'3.5.1'!$1:$1,0)),"") | AV73: =_xlfn.IFNA(INDEX('3.5.1'!$1:$104,MATCH(AV$4,'3.5.1'!$A:$A,0),MATCH(Summary!$C73,'3.5.1'!$1:$1,0)),"") | AY73: =_xlfn.IFNA(INDEX('3.5.1'!$1:$104,MATCH(AY$4,'3.5.1'!$A:$A,0),MATCH(Summary!$C73,'3.5.1'!$1:$1,0)),"") -> 477331.76 | BB73: =_xlfn.IFNA(INDEX('3.5.1'!$1:$104,MATCH(BB$4,'3.5.1'!$A:$A,0),MATCH(Summary!$C73,'3.5.1'!$1:$1,0)),"") -> 474595.09 | BE73: =_xlfn.IFNA(INDEX('3.5.1'!$1:$104,MATCH(BE$4,'3.5.1'!$A:$A,0),MATCH(Summary!$C73,'3.5.1'!$1:$1,0)),"") | BH73: =_xlfn.IFNA(INDEX('3.5.1'!$1:$104,MATCH(BH$4,'3.5.1'!$A:$A,0),MATCH(Summary!$C73,'3.5.1'!$1:$1,0)),"") | BK73: =_xlfn.IFNA(INDEX('3.5.1'!$1:$104,MATCH(BK$4,'3.5.1'!$A:$A,0),MATCH(Summary!$C73,'3.5.1'!$1:$1,0)),"")
C74: loans_outside_hk | E74: Loans for use outside HK | H74: =O74/$O$12 -> 0.24959924 | I74: =IFERROR(L74/AV74-1,"") -> 0.11140611 | J74: =J75+J76 -> 461086.76 | K74: =K75+K76 -> 2277900.4 | L74: =INDEX('1.2'!$1:$104,MATCH(L$3,'1.2'!$A:$A,0),MATCH(Summary!$C74,'1.2'!$1:$1,0)) -> 2738987.2 | M74: =M75+M76 -> 464027.68 | N74: =N75+N76 -> 2228622.8 | O74: =INDEX('1.2'!$1:$104,MATCH(O$3,'1.2'!$A:$A,0),MATCH(Summary!$C74,'1.2'!$1:$1,0)) -> 2692650.5 | P74: =P75+P76 -> 470173.19 | Q74: =Q75+Q76 -> 2194772.7 | R74: =INDEX('1.2'!$1:$104,MATCH(R$3,'1.2'!$A:$A,0),MATCH(Summary!$C74,'1.2'!$1:$1,0)) -> 2664945.9 | S74: =S75+S76 -> 467276.78 | T74: =T75+T76 -> 2160385.3 | U74: =INDEX('1.2'!$1:$104,MATCH(U$3,'1.2'!$A:$A,0),MATCH(Summary!$C74,'1.2'!$1:$1,0)) -> 2627662.1 | V74: =V75+V76 -> 460528.25 | W74: =W75+W76 -> 2117928 | X74: =INDEX('1.2'!$1:$104,MATCH(X$3,'1.2'!$A:$A,0),MATCH(Summary!$C74,'1.2'!$1:$1,0)) -> 2578456.3 | Y74: =Y75+Y76 -> 457350.09 | Z74: =Z75+Z76 -> 2123022.8 | AA74: =INDEX('1.2'!$1:$104,MATCH(AA$3,'1.2'!$A:$A,0),MATCH(Summary!$C74,'1.2'!$1:$1,0)) -> 2580372.9 | AB74: =AB75+AB76 -> 459704.91 | AC74: =AC75+AC76 -> 2097012.3 | AD74: =INDEX('1.2'!$1:$104,MATCH(AD$3,'1.2'!$A:$A,0),MATCH(Summary!$C74,'1.2'!$1:$1,0)) -> 2556717.2 | AE74: =AE75+AE76 -> 455371.05 | AF74: =AF75+AF76 -> 2045466.3 | AG74: =INDEX('1.2'!$1:$104,MATCH(AG$3,'1.2'!$A:$A,0),MATCH(Summary!$C74,'1.2'!$1:$1,0)) -> 2500837.4 | AH74: =AH75+AH76 -> 466237.98 | AI74: =AI75+AI76 -> 1989553.4 | AJ74: =INDEX('1.2'!$1:$104,MATCH(AJ$3,'1.2'!$A:$A,0),MATCH(Summary!$C74,'1.2'!$1:$1,0)) -> 2455791.4 | AK74: =AK75+AK76 -> 462622.24 | AL74: =AL75+AL76 -> 1982695 | AM74: =INDEX('1.2'!$1:$104,MATCH(AM$3,'1.2'!$A:$A,0),MATCH(Summary!$C74,'1.2'!$1:$1,0)) -> 2445317.2 | AN74: =AN75+AN76 -> 472307.55 | AO74: =AO75+AO76 -> 1979012.9 | AP74: =INDEX('1.2'!$1:$104,MATCH(AP$3,'1.2'!$A:$A,0),MATCH(Summary!$C74,'1.2'!$1:$1,0)) -> 2451320.5 | AQ74: =AQ75+AQ76 -> 489459.1 | AR74: =AR75+AR76 -> 1944036.7 | AS74: =INDEX('1.2'!$1:$104,MATCH(AS$3,'1.2'!$A:$A,0),MATCH(Summary!$C74,'1.2'!$1:$1,0)) -> 2433495.8 | AT74: =AT75+AT76 -> 497502.04 | AU74: =AU75+AU76 -> 1966932.1 | AV74: =INDEX('1.2'!$1:$104,MATCH(AV$3,'1.2'!$A:$A,0),MATCH(Summary!$C74,'1.2'!$1:$1,0)) -> 2464434.2 | AW74: =AW75+AW76 -> 492832.73 | AX74: =AX75+AX76 -> 2015447.2 | AY74: =INDEX('1.2'!$1:$104,MATCH(AY$3,'1.2'!$A:$A,0),MATCH(Summary!$C74,'1.2'!$1:$1,0)) -> 2508280 | AZ74: =AZ75+AZ76 -> 532946.3 | BA74: =BA75+BA76 -> 1884879.5 | BB74: =INDEX('1.2'!$1:$104,MATCH(BB$3,'1.2'!$A:$A,0),MATCH(Summary!$C74,'1.2'!$1:$1,0)) -> 2417825.8 | BC74: =BC75+BC76 -> 718314.69 | BD74: =BD75+BD76 -> 1845049.9 | BE74: =INDEX('1.2'!$1:$104,MATCH(BE$3,'1.2'!$A:$A,0),MATCH(Summary!$C74,'1.2'!$1:$1,0)) -> 2563364.6 | BF74: =BF75+BF76 -> 883784.9 | BG74: =BG75+BG76 -> 1977172.2 | BH74: =INDEX('1.2'!$1:$104,MATCH(BH$3,'1.2'!$A:$A,0),MATCH(Summary!$C74,'1.2'!$1:$1,0)) -> 2860957.1 | BI74: =BI75+BI76 -> 888726.65 | BJ74: =BJ75+BJ76 -> 2292125.1 | BK74: =INDEX('1.2'!$1:$104,MATCH(BK$3,'1.2'!$A:$A,0),MATCH(Summary!$C74,'1.2'!$1:$1,0)) -> 3180851.8
A75: other_loans_outhk_hkd | B75: other_loans_outhk_fc | C75: other_loans_outhk_total | E75: Other loans for use outside H.K | H75: =O75/$O$12 -> 0.24959633 | I75: =IFERROR(L75/AV75-1,"") -> 0.11144198 | J75: =INDEX('3.4.1'!$1:$104,MATCH(J$4,'3.4.1'!$A:$A,0),MATCH(Summary!$A75,'3.4.1'!$1:$1,0)) -> 461086.16 | K75: =INDEX('3.4.1'!$1:$104,MATCH(K$4,'3.4.1'!$A:$A,0),MATCH(Summary!$B75,'3.4.1'!$1:$1,0)) -> 2277869.5 | L75: =INDEX('3.4.1'!$1:$104,MATCH(L$4,'3.4.1'!$A:$A,0),MATCH(Summary!$C75,'3.4.1'!$1:$1,0)) -> 2738955.6 | M75: =INDEX('3.4.1'!$1:$104,MATCH(M$4,'3.4.1'!$A:$A,0),MATCH(Summary!$A75,'3.4.1'!$1:$1,0)) -> 464027.09 | N75: =INDEX('3.4.1'!$1:$104,MATCH(N$4,'3.4.1'!$A:$A,0),MATCH(Summary!$B75,'3.4.1'!$1:$1,0)) -> 2228592.1 | O75: =INDEX('3.4.1'!$1:$104,MATCH(O$4,'3.4.1'!$A:$A,0),MATCH(Summary!$C75,'3.4.1'!$1:$1,0)) -> 2692619.2 | P75: =INDEX('3.4.1'!$1:$104,MATCH(P$4,'3.4.1'!$A:$A,0),MATCH(Summary!$A75,'3.4.1'!$1:$1,0)) -> 470172.59 | Q75: =INDEX('3.4.1'!$1:$104,MATCH(Q$4,'3.4.1'!$A:$A,0),MATCH(Summary!$B75,'3.4.1'!$1:$1,0)) -> 2194751.1 | R75: =INDEX('3.4.1'!$1:$104,MATCH(R$4,'3.4.1'!$A:$A,0),MATCH(Summary!$C75,'3.4.1'!$1:$1,0)) -> 2664923.7 | S75: =INDEX('3.4.1'!$1:$104,MATCH(S$4,'3.4.1'!$A:$A,0),MATCH(Summary!$A75,'3.4.1'!$1:$1,0)) -> 467276.18 | T75: =INDEX('3.4.1'!$1:$104,MATCH(T$4,'3.4.1'!$A:$A,0),MATCH(Summary!$B75,'3.4.1'!$1:$1,0)) -> 2160366.2 | U75: =INDEX('3.4.1'!$1:$104,MATCH(U$4,'3.4.1'!$A:$A,0),MATCH(Summary!$C75,'3.4.1'!$1:$1,0)) -> 2627642.4 | V75: =INDEX('3.4.1'!$1:$104,MATCH(V$4,'3.4.1'!$A:$A,0),MATCH(Summary!$A75,'3.4.1'!$1:$1,0)) -> 460527.65 | W75: =INDEX('3.4.1'!$1:$104,MATCH(W$4,'3.4.1'!$A:$A,0),MATCH(Summary!$B75,'3.4.1'!$1:$1,0)) -> 2117906.5 | X75: =INDEX('3.4.1'!$1:$104,MATCH(X$4,'3.4.1'!$A:$A,0),MATCH(Summary!$C75,'3.4.1'!$1:$1,0)) -> 2578434.1 | Y75: =INDEX('3.4.1'!$1:$104,MATCH(Y$4,'3.4.1'!$A:$A,0),MATCH(Summary!$A75,'3.4.1'!$1:$1,0)) -> 457349.19 | Z75: =INDEX('3.4.1'!$1:$104,MATCH(Z$4,'3.4.1'!$A:$A,0),MATCH(Summary!$B75,'3.4.1'!$1:$1,0)) -> 2122925 | AA75: =INDEX('3.4.1'!$1:$104,MATCH(AA$4,'3.4.1'!$A:$A,0),MATCH(Summary!$C75,'3.4.1'!$1:$1,0)) -> 2580274.2 | AB75: =INDEX('3.4.1'!$1:$104,MATCH(AB$4,'3.4.1'!$A:$A,0),MATCH(Summary!$A75,'3.4.1'!$1:$1,0)) -> 459704.01 | AC75: =INDEX('3.4.1'!$1:$104,MATCH(AC$4,'3.4.1'!$A:$A,0),MATCH(Summary!$B75,'3.4.1'!$1:$1,0)) -> 2096914.5 | AD75: =INDEX('3.4.1'!$1:$104,MATCH(AD$4,'3.4.1'!$A:$A,0),MATCH(Summary!$C75,'3.4.1'!$1:$1,0)) -> 2556618.5 | AE75: =INDEX('3.4.1'!$1:$104,MATCH(AE$4,'3.4.1'!$A:$A,0),MATCH(Summary!$A75,'3.4.1'!$1:$1,0)) -> 455370.15 | AF75: =INDEX('3.4.1'!$1:$104,MATCH(AF$4,'3.4.1'!$A:$A,0),MATCH(Summary!$B75,'3.4.1'!$1:$1,0)) -> 2045357.5 | AG75: =INDEX('3.4.1'!$1:$104,MATCH(AG$4,'3.4.1'!$A:$A,0),MATCH(Summary!$C75,'3.4.1'!$1:$1,0)) -> 2500727.7 | AH75: =INDEX('3.4.1'!$1:$104,MATCH(AH$4,'3.4.1'!$A:$A,0),MATCH(Summary!$A75,'3.4.1'!$1:$1,0)) -> 466237.08 | AI75: =INDEX('3.4.1'!$1:$104,MATCH(AI$4,'3.4.1'!$A:$A,0),MATCH(Summary!$B75,'3.4.1'!$1:$1,0)) -> 1989444.6 | AJ75: =INDEX('3.4.1'!$1:$104,MATCH(AJ$4,'3.4.1'!$A:$A,0),MATCH(Summary!$C75,'3.4.1'!$1:$1,0)) -> 2455681.6 | AK75: =INDEX('3.4.1'!$1:$104,MATCH(AK$4,'3.4.1'!$A:$A,0),MATCH(Summary!$A75,'3.4.1'!$1:$1,0)) -> 462621.34 | AL75: =INDEX('3.4.1'!$1:$104,MATCH(AL$4,'3.4.1'!$A:$A,0),MATCH(Summary!$B75,'3.4.1'!$1:$1,0)) -> 1982597.6 | AM75: =INDEX('3.4.1'!$1:$104,MATCH(AM$4,'3.4.1'!$A:$A,0),MATCH(Summary!$C75,'3.4.1'!$1:$1,0)) -> 2445219 | AN75: =INDEX('3.4.1'!$1:$104,MATCH(AN$4,'3.4.1'!$A:$A,0),MATCH(Summary!$A75,'3.4.1'!$1:$1,0)) -> 472306.65 | AO75: =INDEX('3.4.1'!$1:$104,MATCH(AO$4,'3.4.1'!$A:$A,0),MATCH(Summary!$B75,'3.4.1'!$1:$1,0)) -> 1978905.5 | AP75: =INDEX('3.4.1'!$1:$104,MATCH(AP$4,'3.4.1'!$A:$A,0),MATCH(Summary!$C75,'3.4.1'!$1:$1,0)) -> 2451212.2 | AQ75: =INDEX('3.4.1'!$1:$104,MATCH(AQ$4,'3.4.1'!$A:$A,0),MATCH(Summary!$A75,'3.4.1'!$1:$1,0)) -> 489457.9 | AR75: =INDEX('3.4.1'!$1:$104,MATCH(AR$4,'3.4.1'!$A:$A,0),MATCH(Summary!$B75,'3.4.1'!$1:$1,0)) -> 1943926.6 | AS75: =INDEX('3.4.1'!$1:$104,MATCH(AS$4,'3.4.1'!$A:$A,0),MATCH(Summary!$C75,'3.4.1'!$1:$1,0)) -> 2433384.5 | AT75: =INDEX('3.4.1'!$1:$104,MATCH(AT$4,'3.4.1'!$A:$A,0),MATCH(Summary!$A75,'3.4.1'!$1:$1,0)) -> 497500.84 | AU75: =INDEX('3.4.1'!$1:$104,MATCH(AU$4,'3.4.1'!$A:$A,0),MATCH(Summary!$B75,'3.4.1'!$1:$1,0)) -> 1966825.4 | AV75: =INDEX('3.4.1'!$1:$104,MATCH(AV$4,'3.4.1'!$A:$A,0),MATCH(Summary!$C75,'3.4.1'!$1:$1,0)) -> 2464326.2 | AW75: =INDEX('3.4.1'!$1:$104,MATCH(AW$4,'3.4.1'!$A:$A,0),MATCH(Summary!$A75,'3.4.1'!$1:$1,0)) -> 492831.53 | AX75: =INDEX('3.4.1'!$1:$104,MATCH(AX$4,'3.4.1'!$A:$A,0),MATCH(Summary!$B75,'3.4.1'!$1:$1,0)) -> 2015341.5 | AY75: =INDEX('3.4.1'!$1:$104,MATCH(AY$4,'3.4.1'!$A:$A,0),MATCH(Summary!$C75,'3.4.1'!$1:$1,0)) -> 2508173.1 | AZ75: =INDEX('3.4.1'!$1:$104,MATCH(AZ$4,'3.4.1'!$A:$A,0),MATCH(Summary!$A75,'3.4.1'!$1:$1,0)) -> 532944.8 | BA75: =INDEX('3.4.1'!$1:$104,MATCH(BA$4,'3.4.1'!$A:$A,0),MATCH(Summary!$B75,'3.4.1'!$1:$1,0)) -> 1884776 | BB75: =INDEX('3.4.1'!$1:$104,MATCH(BB$4,'3.4.1'!$A:$A,0),MATCH(Summary!$C75,'3.4.1'!$1:$1,0)) -> 2417720.8 | BC75: =INDEX('3.4.1'!$1:$104,MATCH(BC$4,'3.4.1'!$A:$A,0),MATCH(Summary!$A75,'3.4.1'!$1:$1,0)) -> 718313.3 | BD75: =INDEX('3.4.1'!$1:$104,MATCH(BD$4,'3.4.1'!$A:$A,0),MATCH(Summary!$B75,'3.4.1'!$1:$1,0)) -> 1844955.5 | BE75: =INDEX('3.4.1'!$1:$104,MATCH(BE$4,'3.4.1'!$A:$A,0),MATCH(Summary!$C75,'3.4.1'!$1:$1,0)) -> 2563268.8 | BF75: =INDEX('3.4.1'!$1:$104,MATCH(BF$4,'3.4.1'!$A:$A,0),MATCH(Summary!$A75,'3.4.1'!$1:$1,0)) -> 883783.4 | BG75: =INDEX('3.4.1'!$1:$104,MATCH(BG$4,'3.4.1'!$A:$A,0),MATCH(Summary!$B75,'3.4.1'!$1:$1,0)) -> 1976831 | BH75: =INDEX('3.4.1'!$1:$104,MATCH(BH$4,'3.4.1'!$A:$A,0),MATCH(Summary!$C75,'3.4.1'!$1:$1,0)) -> 2860614.4 | BI75: =INDEX('3.4.1'!$1:$104,MATCH(BI$4,'3.4.1'!$A:$A,0),MATCH(Summary!$A75,'3.4.1'!$1:$1,0)) -> 888678.05 | BJ75: =INDEX('3.4.1'!$1:$104,MATCH(BJ$4,'3.4.1'!$A:$A,0),MATCH(Summary!$B75,'3.4.1'!$1:$1,0)) -> 2291728.5 | BK75: =INDEX('3.4.1'!$1:$104,MATCH(BK$4,'3.4.1'!$A:$A,0),MATCH(Summary!$C75,'3.4.1'!$1:$1,0)) -> 3180406.5
A76: other_loans_unkplace_hkd | B76: other_loans_unkplace_fc | C76: other_loans_unkplace_total | E76: Other loans where the place of use is not known | H76: =O76/$O$12 -> 2.9052932e-06 | I76: =IFERROR(L76/AV76-1,"") -> -0.70781435 | J76: =INDEX('3.4.1'!$1:$104,MATCH(J$4,'3.4.1'!$A:$A,0),MATCH(Summary!$A76,'3.4.1'!$1:$1,0)) -> 0.6 | K76: =INDEX('3.4.1'!$1:$104,MATCH(K$4,'3.4.1'!$A:$A,0),MATCH(Summary!$B76,'3.4.1'!$1:$1,0)) -> 30.928 | L76: =INDEX('3.4.1'!$1:$104,MATCH(L$4,'3.4.1'!$A:$A,0),MATCH(Summary!$C76,'3.4.1'!$1:$1,0)) -> 31.528 | M76: =INDEX('3.4.1'!$1:$104,MATCH(M$4,'3.4.1'!$A:$A,0),MATCH(Summary!$A76,'3.4.1'!$1:$1,0)) -> 0.6 | N76: =INDEX('3.4.1'!$1:$104,MATCH(N$4,'3.4.1'!$A:$A,0),MATCH(Summary!$B76,'3.4.1'!$1:$1,0)) -> 30.742 | O76: =INDEX('3.4.1'!$1:$104,MATCH(O$4,'3.4.1'!$A:$A,0),MATCH(Summary!$C76,'3.4.1'!$1:$1,0)) -> 31.342 | P76: =INDEX('3.4.1'!$1:$104,MATCH(P$4,'3.4.1'!$A:$A,0),MATCH(Summary!$A76,'3.4.1'!$1:$1,0)) -> 0.6 | Q76: =INDEX('3.4.1'!$1:$104,MATCH(Q$4,'3.4.1'!$A:$A,0),MATCH(Summary!$B76,'3.4.1'!$1:$1,0)) -> 21.615 | R76: =INDEX('3.4.1'!$1:$104,MATCH(R$4,'3.4.1'!$A:$A,0),MATCH(Summary!$C76,'3.4.1'!$1:$1,0)) -> 22.215 | S76: =INDEX('3.4.1'!$1:$104,MATCH(S$4,'3.4.1'!$A:$A,0),MATCH(Summary!$A76,'3.4.1'!$1:$1,0)) -> 0.6 | T76: =INDEX('3.4.1'!$1:$104,MATCH(T$4,'3.4.1'!$A:$A,0),MATCH(Summary!$B76,'3.4.1'!$1:$1,0)) -> 19.166 | U76: =INDEX('3.4.1'!$1:$104,MATCH(U$4,'3.4.1'!$A:$A,0),MATCH(Summary!$C76,'3.4.1'!$1:$1,0)) -> 19.766 | V76: =INDEX('3.4.1'!$1:$104,MATCH(V$4,'3.4.1'!$A:$A,0),MATCH(Summary!$A76,'3.4.1'!$1:$1,0)) -> 0.6 | W76: =INDEX('3.4.1'!$1:$104,MATCH(W$4,'3.4.1'!$A:$A,0),MATCH(Summary!$B76,'3.4.1'!$1:$1,0)) -> 21.564 | X76: =INDEX('3.4.1'!$1:$104,MATCH(X$4,'3.4.1'!$A:$A,0),MATCH(Summary!$C76,'3.4.1'!$1:$1,0)) -> 22.164 | Y76: =INDEX('3.4.1'!$1:$104,MATCH(Y$4,'3.4.1'!$A:$A,0),MATCH(Summary!$A76,'3.4.1'!$1:$1,0)) -> 0.9 | Z76: =INDEX('3.4.1'!$1:$104,MATCH(Z$4,'3.4.1'!$A:$A,0),MATCH(Summary!$B76,'3.4.1'!$1:$1,0)) -> 97.823 | AA76: =INDEX('3.4.1'!$1:$104,MATCH(AA$4,'3.4.1'!$A:$A,0),MATCH(Summary!$C76,'3.4.1'!$1:$1,0)) -> 98.723 | AB76: =INDEX('3.4.1'!$1:$104,MATCH(AB$4,'3.4.1'!$A:$A,0),MATCH(Summary!$A76,'3.4.1'!$1:$1,0)) -> 0.9 | AC76: =INDEX('3.4.1'!$1:$104,MATCH(AC$4,'3.4.1'!$A:$A,0),MATCH(Summary!$B76,'3.4.1'!$1:$1,0)) -> 97.851 | AD76: =INDEX('3.4.1'!$1:$104,MATCH(AD$4,'3.4.1'!$A:$A,0),MATCH(Summary!$C76,'3.4.1'!$1:$1,0)) -> 98.751 | AE76: =INDEX('3.4.1'!$1:$104,MATCH(AE$4,'3.4.1'!$A:$A,0),MATCH(Summary!$A76,'3.4.1'!$1:$1,0)) -> 0.9 | AF76: =INDEX('3.4.1'!$1:$104,MATCH(AF$4,'3.4.1'!$A:$A,0),MATCH(Summary!$B76,'3.4.1'!$1:$1,0)) -> 108.837 | AG76: =INDEX('3.4.1'!$1:$104,MATCH(AG$4,'3.4.1'!$A:$A,0),MATCH(Summary!$C76,'3.4.1'!$1:$1,0)) -> 109.737 | AH76: =INDEX('3.4.1'!$1:$104,MATCH(AH$4,'3.4.1'!$A:$A,0),MATCH(Summary!$A76,'3.4.1'!$1:$1,0)) -> 0.9 | AI76: =INDEX('3.4.1'!$1:$104,MATCH(AI$4,'3.4.1'!$A:$A,0),MATCH(Summary!$B76,'3.4.1'!$1:$1,0)) -> 108.88 | AJ76: =INDEX('3.4.1'!$1:$104,MATCH(AJ$4,'3.4.1'!$A:$A,0),MATCH(Summary!$C76,'3.4.1'!$1:$1,0)) -> 109.78 | AK76: =INDEX('3.4.1'!$1:$104,MATCH(AK$4,'3.4.1'!$A:$A,0),MATCH(Summary!$A76,'3.4.1'!$1:$1,0)) -> 0.9 | AL76: =INDEX('3.4.1'!$1:$104,MATCH(AL$4,'3.4.1'!$A:$A,0),MATCH(Summary!$B76,'3.4.1'!$1:$1,0)) -> 97.347 | AM76: =INDEX('3.4.1'!$1:$104,MATCH(AM$4,'3.4.1'!$A:$A,0),MATCH(Summary!$C76,'3.4.1'!$1:$1,0)) -> 98.247 | AN76: =INDEX('3.4.1'!$1:$104,MATCH(AN$4,'3.4.1'!$A:$A,0),MATCH(Summary!$A76,'3.4.1'!$1:$1,0)) -> 0.9 | AO76: =INDEX('3.4.1'!$1:$104,MATCH(AO$4,'3.4.1'!$A:$A,0),MATCH(Summary!$B76,'3.4.1'!$1:$1,0)) -> 107.393 | AP76: =INDEX('3.4.1'!$1:$104,MATCH(AP$4,'3.4.1'!$A:$A,0),MATCH(Summary!$C76,'3.4.1'!$1:$1,0)) -> 108.293 | AQ76: =INDEX('3.4.1'!$1:$104,MATCH(AQ$4,'3.4.1'!$A:$A,0),MATCH(Summary!$A76,'3.4.1'!$1:$1,0)) -> 1.2 | AR76: =INDEX('3.4.1'!$1:$104,MATCH(AR$4,'3.4.1'!$A:$A,0),MATCH(Summary!$B76,'3.4.1'!$1:$1,0)) -> 110.101 | AS76: =INDEX('3.4.1'!$1:$104,MATCH(AS$4,'3.4.1'!$A:$A,0),MATCH(Summary!$C76,'3.4.1'!$1:$1,0)) -> 111.301 | AT76: =INDEX('3.4.1'!$1:$104,MATCH(AT$4,'3.4.1'!$A:$A,0),MATCH(Summary!$A76,'3.4.1'!$1:$1,0)) -> 1.2 | AU76: =INDEX('3.4.1'!$1:$104,MATCH(AU$4,'3.4.1'!$A:$A,0),MATCH(Summary!$B76,'3.4.1'!$1:$1,0)) -> 106.704 | AV76: =INDEX('3.4.1'!$1:$104,MATCH(AV$4,'3.4.1'!$A:$A,0),MATCH(Summary!$C76,'3.4.1'!$1:$1,0)) -> 107.904 | AW76: =INDEX('3.4.1'!$1:$104,MATCH(AW$4,'3.4.1'!$A:$A,0),MATCH(Summary!$A76,'3.4.1'!$1:$1,0)) -> 1.2 | AX76: =INDEX('3.4.1'!$1:$104,MATCH(AX$4,'3.4.1'!$A:$A,0),MATCH(Summary!$B76,'3.4.1'!$1:$1,0)) -> 105.7 | AY76: =INDEX('3.4.1'!$1:$104,MATCH(AY$4,'3.4.1'!$A:$A,0),MATCH(Summary!$C76,'3.4.1'!$1:$1,0)) -> 106.9 | AZ76: =INDEX('3.4.1'!$1:$104,MATCH(AZ$4,'3.4.1'!$A:$A,0),MATCH(Summary!$A76,'3.4.1'!$1:$1,0)) -> 1.5 | BA76: =INDEX('3.4.1'!$1:$104,MATCH(BA$4,'3.4.1'!$A:$A,0),MATCH(Summary!$B76,'3.4.1'!$1:$1,0)) -> 103.484 | BB76: =INDEX('3.4.1'!$1:$104,MATCH(BB$4,'3.4.1'!$A:$A,0),MATCH(Summary!$C76,'3.4.1'!$1:$1,0)) -> 104.984 | BC76: =INDEX('3.4.1'!$1:$104,MATCH(BC$4,'3.4.1'!$A:$A,0),MATCH(Summary!$A76,'3.4.1'!$1:$1,0)) -> 1.4 | BD76: =INDEX('3.4.1'!$1:$104,MATCH(BD$4,'3.4.1'!$A:$A,0),MATCH(Summary!$B76,'3.4.1'!$1:$1,0)) -> 94.331 | BE76: =INDEX('3.4.1'!$1:$104,MATCH(BE$4,'3.4.1'!$A:$A,0),MATCH(Summary!$C76,'3.4.1'!$1:$1,0)) -> 95.731 | BF76: =INDEX('3.4.1'!$1:$104,MATCH(BF$4,'3.4.1'!$A:$A,0),MATCH(Summary!$A76,'3.4.1'!$1:$1,0)) -> 1.5 | BG76: =INDEX('3.4.1'!$1:$104,MATCH(BG$4,'3.4.1'!$A:$A,0),MATCH(Summary!$B76,'3.4.1'!$1:$1,0)) -> 341.204 | BH76: =INDEX('3.4.1'!$1:$104,MATCH(BH$4,'3.4.1'!$A:$A,0),MATCH(Summary!$C76,'3.4.1'!$1:$1,0)) -> 342.704 | BI76: =INDEX('3.4.1'!$1:$104,MATCH(BI$4,'3.4.1'!$A:$A,0),MATCH(Summary!$A76,'3.4.1'!$1:$1,0)) -> 48.6 | BJ76: =INDEX('3.4.1'!$1:$104,MATCH(BJ$4,'3.4.1'!$A:$A,0),MATCH(Summary!$B76,'3.4.1'!$1:$1,0)) -> 396.627 | BK76: =INDEX('3.4.1'!$1:$104,MATCH(BK$4,'3.4.1'!$A:$A,0),MATCH(Summary!$C76,'3.4.1'!$1:$1,0)) -> 445.227
E78: (1). | F78: Loans and advances for use in Hong Kong refer to loans that have direct impact on the level of economic activity in Hong Kong. | O78: (1). | P78: 在香港使用的貸款是指對香港的經濟活動有直接影響的貸款。 這一般視乎 | R78: 在香港使用的貸款是指對香港的經濟活動有直接影響的貸款。 這一般視乎
F79: This is usually determined by whether the loan is made available or disbursed in Hong Kong, and by the principal business | P79: 該筆貸款是否由香港提供或在香港支付，以及客戶的主要業務所在地而定。 | R79: 該筆貸款是否由香港提供或在香港支付，以及客戶的主要業務所在地而定。
F80: location of the customer.

Sheet Chart

Sheet Data Source
B2: 1.Monthly Statistical Bulletin
B3: 2. HKMA-API
B5: TABLE | C5: Data Source Name | D5: Data Source Link
B6: TABLE 1.2 | C6: Banking statistics | D6: https://apidocs.hkma.gov.hk/apidata/?api=market-data-and-statistics.monthly-statistical-bulletin.financial.banking-statistics&page=1
B7: TABLE 3.4.1 | C7: Loans and advances by type - Authorized institutions | D7: https://apidocs.hkma.gov.hk/gb_chi/apidata/?api=market-data-and-statistics.monthly-statistical-bulletin.banking.loans-by-type-ais&page=1
B8: TABLE 3.5.1 | C8: Loans and advances for use in HONG KONG by economic sector - Authorized institutions | D8: https://apidocs.hkma.gov.hk/apidata/?api=market-data-and-statistics.monthly-statistical-bulletin.banking.loans-by-sector-ais
B9: TABLE 3.13.1 | C9: Mainland-related lending and other non-bank exposures – Mainland-related lending | D9: https://apidocs.hkma.gov.hk/gb_chi/documentation/market-data-and-statistics/monthly-statistical-bulletin/banking/mr-lending/
B12: Others sources
B13: import & export: C&SD Web Table
B14: re-export: Trades-IDDS
B15: TID 工貿處
B16: TDC - Trade Development

Sheet Hong Kong trade finance lenders
A1: 香港前20大贸易融资贷款机构（按客户垫款计，2024年，十亿港元）
A2: 排名 | B2: 机构名称（英文） | C2: 机构名称（中文） | D2: 客户垫款（十亿港元） | E2: 占总市场比例 | F2: 分组
A3: 1 | B3: HSBC | C3: 汇丰银行 | D3: 153.1 | E3: =D3/500.9 -> 0.30564983 | F3: 前10大
A4: 2 | B4: Standard Chartered Bank | C4: 渣打银行 | D4: 63.5 | E4: =D4/500.9 -> 0.12677181 | F4: 前10大
A5: 3 | B5: Bank of China | C5: 中国银行 | D5: 47 | E5: =D5/500.9 -> 0.093831104 | F5: 前10大
A6: 4 | B6: Hang Seng Bank | C6: 恒生银行 | D6: 30.5 | E6: =D6/500.9 -> 0.060890397 | F6: 前10大
A7: 5 | B7: DBS Bank | C7: 星展银行 | D7: 27.8 | E7: =D7/500.9 -> 0.0555001 | F7: 前10大
A8: 6 | B8: United Overseas Bank | C8: 大华银行 | D8: 16.9 | E8: =D8/500.9 -> 0.033739269 | F8: 前10大
A9: 7 | B9: Banco Santander, S.A. | C9: 桑坦德银行 | D9: 10.8 | E9: =D9/500.9 -> 0.02156119 | F9: 前10大
A10: 8 | B10: Banco Bilbao Vizcaya Argentaria S.A. | C10: 西班牙对外银行（BBVA） | D10: 10.4 | E10: =D10/500.9 -> 0.020762627 | F10: 前10大
A11: 9 | B11: BNP Paribas | C11: 法国巴黎银行 | D11: 9.8 | E11: =D11/500.9 -> 0.019564783 | F11: 前10大
A12: 10 | B12: ICBC | C12: 中国工商银行 | D12: 9.7 | E12: =D12/500.9 -> 0.019365143 | F12: 前10大
A13: 11 | B13: Citibank | C13: 花旗银行 | D13: 9.7 | E13: =D13/500.9 -> 0.019365143 | F13: 第11-20大
A14: 12 | B14: Deutsche Bank Aktiengesellschaft | C14: 德意志银行 | D14: 9.6 | E14: =D14/500.9 -> 0.019165502 | F14: 第11-20大
... A22: 20 | B22: Fubon | C22: 富邦银行 | D22: 4.7 | E22: =D22/500.9 -> 0.0093831104 | F22: 第11-20大
A23: — | B23: Others | C23: 其他 | D23: 49.1 | E23: =D23/500.9 -> 0.098023558 | F23: 其他
B24: 合计（前20大+其他） | D24: =SUM(D3:D23) -> 501 | E24: =D24/500.9 -> 1.0001996
A26: 注：占比按幻灯片披露的市场总额5,009亿港元计算；各机构垫款数值读取自图表柱形标签。资料来源：公司财务披露报表、香港金融管理局、毕马威分析。
A28: 图中文字提取：Hong Kong trade finance lenders landscape（KPMG 幻灯片，第22页）
A29: 项目 | B29: 英文原文 | C29: 中文翻译
A30: 标题 Title | B30: Hong Kong trade finance lenders landscape | C30: 香港贸易融资贷款机构格局
A31: 概要 Summary | B31: In 2024, 77 authorised institutions and local representative offices in Hong Kong provided trade financing of HKD 500.9 billion in advances, marking an 11.5% CAGR decline from 2021. Total loans and advances fell by 16.0% CAGR over the same period. The top 20 lenders accounted for approximately 90% of the market. | C31: 2024年，香港77家认可机构及本地代表处提供的贸易融资垫款为5,009亿港元，较2021年的年均复合增长率（CAGR）下降11.5%。同期贷款及垫款总额的年均复合增长率下降16.0%。前20大贷款机构约占市场的90%。
A32: 图表标题 Chart title | B32: Hong Kong top 20 trade finance lenders by advances to customers(1) | HKD b, 2024 | C32: 香港前20大贸易融资贷款机构（按客户垫款计）(1) ｜ 十亿港元，2024年
A33: 分组标注 Grouping | B33: Top 10 account for 76% of total market; Top 11-20 account for 14% of total market | C33: 前10大占总市场的76%；第11至20大占总市场的14%
A34: 注释 Note (1) | B34: Trade finance shown above represents loans covering finance of imports to Hong Kong, exports and re-exports from Hong Kong and merchandising trade classified with reference to the relevant guidelines issued by the HKMA. Authorised institutions and local representative offices have been aggregated by parent group, for example, DBS Bank (Hong Kong) Limited and DBS Bank Ltd. are referred to as DBS Bank. | C34: 上图所示贸易融资指为香港进口、香港出口及转口以及商品贸易提供融资的贷款，分类参照香港金融管理局（HKMA）发布的相关指引。认可机构及本地代表处已按母集团合并计算，例如星展银行（香港）有限公司与星展银行有限公司合并列示为星展银行。
A35: 资料来源 Source | B35: Company financial disclosure statements, HKMA, KPMG analysis | C35: 公司财务披露报表、香港金融管理局、毕马威分析
A36: 页脚 Footer | B36: © 2025 KPMG Advisory (Hong Kong) Limited, a Hong Kong (SAR) limited liability company and a member firm of the KPMG global organisation of independent member firms affiliated with KPMG International Limited, a private English company limited by guarantee. All rights reserved. Document Classification: KPMG Confidential | Page 22 | C36: © 2025 毕马威咨询（香港）有限公司——香港特别行政区有限责任公司，是与毕马威国际有限公司（英国私营担保有限公司）相关联的独立成员所全球性组织中的成员。版权所有。文件密级：毕马威机密｜第22页

Sheet 1.2
A1: end_of_month | B1: no_of_ais | C1: total_assets | D1: total_ext_claims | E1: total_ext_liab | F1: cust_deposites_hkd | G1: cust_deposits_fc | H1: cust_deposits_total | I1: loans_in_hk | J1: loans_outside_hk | K1: loans_total | L1: loans_resid_mort_lending | M1: classif_loans | N1: deli_ratio_resid_mort_lend | O1: chroff_ratio_of_crcard_rece | Q1: HK$Million
I2: Loans for use in H.K | J2: Loans for use outside H.K. | K2: Total loans and advances
A3: 2026-08 | B3: 174
A4: 2026-07 | B4: 174 | C4: 33352005 | F4: 8641180.4 | G4: 11920847 | H4: 20562027 | I4: 8070867 | J4: 2738987.2 | K4: 10809854 | L4: 1963470 | N4: 0.11
A5: 2026-06 | B5: 174 | C5: 33140209 | D5: 19749039 | E5: 12059633 | F5: 8567402.9 | G5: 11813616 | H5: 20381019 | I5: 8095245.2 | J5: 2692650.5 | K5: 10787896 | L5: 1955022 | M5: 1.9596694 | N5: 0.11 | O5: 2.45
A6: 2026-05 | B6: 175 | C6: 32694261 | D6: 18964653 | E6: 12119489 | F6: 8492985.3 | G6: 11875532 | H6: 20368517 | I6: 7981206.3 | J6: 2664945.9 | K6: 10646152 | L6: 1946916 | N6: 0.11
A7: 2026-04 | B7: 175 | C7: 31975046 | D7: 18482620 | E7: 11885756 | F7: 8393181.2 | G7: 11512350 | H7: 19905531 | I7: 7869195.5 | J7: 2627662.1 | K7: 10496858 | L7: 1939561 | N7: 0.12
A8: 2026-03 | B8: 175 | C8: 31610691 | D8: 18444095 | E8: 11503996 | F8: 8289063.1 | G8: 11328273 | H8: 19617336 | I8: 7861821.8 | J8: 2578456.3 | K8: 10440278 | L8: 1934866 | M8: 2.0595169 | N8: 0.13 | O8: 2.25
A9: 2026-02 | B9: 175 | C9: 31606316 | D9: 18293946 | E9: 11647086 | F9: 8232336.4 | G9: 11367191 | H9: 19599527 | I9: 7721916.9 | J9: 2580372.9 | K9: 10302290 | L9: 1926330 | N9: 0.13
A10: 2026-01 | B10: 176 | C10: 31305047 | D10: 18136106 | E10: 11454208 | F10: 8244954.1 | G10: 11174159 | H10: 19419113 | I10: 7688694.2 | J10: 2556717.2 | K10: 10245411 | L10: 1923354 | N10: 0.13
A11: 2025-12 | B11: 176 | C11: 30637568 | D11: 18027007 | E11: 10858537 | F11: 8136778.4 | G11: 11294485 | H11: 19431264 | I11: 7635305.1 | J11: 2500837.4 | K11: 10136142 | L11: 1917499 | M11: 2.1944648 | N11: 0.14 | O11: 2.5
A12: 2025-11 | B12: 176 | C12: 30103348 | D12: 17428578 | E12: 10881447 | F12: 8102066.2 | G12: 11101196 | H12: 19203262 | I12: 7546764.4 | J12: 2455791.4 | K12: 10002556 | L12: 1913539 | N12: 0.14
A13: 2025-10 | B13: 176 | C13: 29719149 | D13: 17180342 | E13: 10779361 | F13: 8083717.4 | G13: 10976794 | H13: 19060512 | I13: 7551750.3 | J13: 2445317.2 | K13: 9997067.5 | L13: 1907407 | N13: 0.13
A14: 2025-09 | B14: 176 | C14: 30022231 | D14: 17345507 | E14: 10578398 | F14: 8159087.8 | G14: 10985365 | H14: 19144453 | I14: 7617255.6 | J14: 2451320.5 | K14: 10068576 | L14: 1891402 | M14: 2.1430387 | N14: 0.13 | O14: 2.57
A15: 2025-08 | B15: 176 | C15: 29751686 | D15: 17043374 | E15: 10741681 | F15: 8045178.4 | G15: 10847153 | H15: 18892331 | I15: 7570020.6 | J15: 2433495.8 | K15: 10003516 | L15: 1888314 | N15: 0.13
A16: 2025-07 | B16: 175 | C16: 29633337 | D16: 16988948 | E16: 10818121 | F16: 8221343.9 | G16: 10505291 | H16: 18726635 | I16: 7577126.3 | J16: 2464434.2 | K16: 10041560 | L16: 1887335 | N16: 0.13
A17: 2025-06 | B17: 175 | C17: 29846237 | D17: 17077498 | E17: 10716437 | F17: 8386245.9 | G17: 10312216 | H17: 18698462 | I17: 7650101.4 | J17: 2508280 | K17: 10158381 | L17: 1885559 | M17: 2.1348758 | N17: 0.13 | O17: 2.57
A18: 2025-00 | B18: 176 | C18: 30637568 | D18: 18027007 | E18: 10858537 | F18: 8136778.4 | G18: 11294485 | H18: 19431264 | I18: 7635305.1 | J18: 2500837.4 | K18: 10136142 | L18: 1917499 | M18: 2.1944648 | N18: 0.14 | O18: 2.37
A19: 2024-00 | B19: 176 | C19: 28457223 | D19: 16028131 | E19: 10458537 | F19: 7839207.4 | G19: 9533510.3 | H19: 17372718 | I19: 7489982.2 | J19: 2417825.8 | K19: 9907808 | L19: 1870642 | M19: 2.1788857 | N19: 0.11 | O19: 2.18
A20: 2023-00 | B20: 179 | C20: 27283034 | D20: 14620985 | E20: 10394505 | F20: 7623772.3 | G20: 8598297.4 | H20: 16222070 | I20: 7627950.9 | J20: 2563364.6 | K20: 10191315 | L20: 1855080 | M20: 1.6820806 | N20: 0.08 | O20: 1.74
A21: 2022-00 | B21: 182 | C21: 27031411 | D21: 14249254 | E21: 10698112 | F21: 7468229.9 | G21: 7971455.4 | H21: 15439685 | I21: 7710340.6 | J21: 2860957.1 | K21: 10571298 | L21: 1809906 | M21: 1.4177867 | N21: 0.06 | O21: 1.49
A22: 2021-00 | B22: 188 | C22: 26367228 | D22: 13592959 | E22: 10725207 | F22: 7414380.9 | G22: 7771839.3 | H22: 15186220 | I22: 7712295.5 | J22: 3180851.8 | K22: 10893147 | L22: 1736412 | M22: 0.84785395 | N22: 0.04 | O22: 1.75

Sheet 3.4.1
A1: end_of_month | B1: imp_exp_reexp_fromhk_hkd | C1: imp_exp_reexp_fromhk_fc | D1: imp_exp_reexp_fromhk_total | E1: merch_trade_nonhk_hkd | F1: merch_trade_nonhk_fc | G1: merch_trade_nonhk_total | H1: loans_inhk_hkd | I1: loans_inhk_fc | J1: loans_inhk_total | K1: other_loans_outhk_hkd | L1: other_loans_outhk_fc | M1: other_loans_outhk_total | N1: other_loans_unkplace_hkd | O1: other_loans_unkplace_fc | P1: other_loans_unkplace_total | Q1: total_loans_hkd | R1: total_loans_fc | S1: total_loans | U1: HK$Million
B2: 香港貨物的出入口及轉口融資 | E2: 香港境外的商品貿易融資 | K2: Other loans for use outside H.K. | N2: Loans for use outside H.K.
A3: 2026-07 | B3: 56511.102 | C3: 193800.71 | D3: 250311.81 | E3: 13053.365 | F3: 158463.42 | G3: 171516.78 | H3: 5580470.7 | I3: 2068567.8 | J3: 7649038.4 | K3: 461086.16 | L3: 2277869.5 | M3: 2738955.6 | N3: 0.6 | O3: 30.928 | P3: 31.528 | Q3: 6111121.9 | R3: 4698732.3 | S3: 10809854
A4: 2026-06 | B4: 57111.395 | C4: 205705.76 | D4: 262817.16 | E4: 12780.198 | F4: 160491.84 | G4: 173272.03 | H4: 5589675.4 | I4: 2069480.6 | J4: 7659156 | K4: 464027.09 | L4: 2228592.1 | M4: 2692619.2 | N4: 0.6 | O4: 30.742 | P4: 31.342 | Q4: 6123594.7 | R4: 4664301.1 | S4: 10787896
A5: 2026-05 | B5: 57013.091 | C5: 186630.31 | D5: 243643.4 | E5: 12466.324 | F5: 158653.3 | G5: 171119.62 | H5: 5488152.2 | I5: 2078291 | J5: 7566443.3 | K5: 470172.59 | L5: 2194751.1 | M5: 2664923.7 | N5: 0.6 | O5: 21.615 | P5: 22.215 | Q5: 6027804.8 | R5: 4618347.4 | S5: 10646152
A6: 2026-04 | B6: 59126.986 | C6: 173799.62 | D6: 232926.61 | E6: 11984.01 | F6: 160556.36 | G6: 172540.37 | H6: 5472828.6 | I6: 1990899.9 | J6: 7463728.5 | K6: 467276.18 | L6: 2160366.2 | M6: 2627642.4 | N6: 0.6 | O6: 19.166 | P6: 19.766 | Q6: 6011216.4 | R6: 4485641.3 | S6: 10496858
A7: 2026-03 | B7: 59339.624 | C7: 182422.15 | D7: 241761.77 | E7: 11972.022 | F7: 167767.32 | G7: 179739.34 | H7: 5461882.5 | I7: 1978438.2 | J7: 7440320.7 | K7: 460527.65 | L7: 2117906.5 | M7: 2578434.1 | N7: 0.6 | O7: 21.564 | P7: 22.164 | Q7: 5993722.4 | R7: 4446555.7 | S7: 10440278
A8: 2026-02 | B8: 58040.729 | C8: 172201.21 | D8: 230241.94 | E8: 13041.727 | F8: 126050.45 | G8: 139092.18 | H8: 5431952.5 | I8: 1920630.3 | J8: 7352582.8 | K8: 457349.19 | L8: 2122925 | M8: 2580274.2 | N8: 0.9 | O8: 97.823 | P8: 98.723 | Q8: 5960385 | R8: 4341904.8 | S8: 10302290
A9: 2026-01 | B9: 58057.961 | C9: 166061.31 | D9: 224119.27 | E9: 13924.763 | F9: 121553.74 | G9: 135478.5 | H9: 5430504.2 | I9: 1898592.3 | J9: 7329096.5 | K9: 459704.01 | L9: 2096914.5 | M9: 2556618.5 | N9: 0.9 | O9: 97.851 | P9: 98.751 | Q9: 5962191.8 | R9: 4283219.7 | S9: 10245411
A10: 2025-12 | B10: 55987.338 | C10: 186177.14 | D10: 242164.48 | E10: 14415.68 | F10: 134200.05 | G10: 148615.73 | H10: 5408698.2 | I10: 1835826.7 | J10: 7244524.9 | K10: 455370.15 | L10: 2045357.5 | M10: 2500727.7 | N10: 0.9 | O10: 108.837 | P10: 109.737 | Q10: 5934472.2 | R10: 4201670.2 | S10: 10136142
A11: 2025-11 | B11: 58570.371 | C11: 154966.04 | D11: 213536.41 | E11: 13974.943 | F11: 116204.61 | G11: 130179.55 | H11: 5391482.5 | I11: 1811566 | J11: 7203048.4 | K11: 466237.08 | L11: 1989444.6 | M11: 2455681.6 | N11: 0.9 | O11: 108.88 | P11: 109.78 | Q11: 5930265.7 | R11: 4072290 | S11: 10002556
A12: 2025-10 | B12: 57795.635 | C12: 153915.67 | D12: 211711.3 | E12: 14483.044 | F12: 113621.16 | G12: 128104.21 | H12: 5414751.6 | I12: 1797183.2 | J12: 7211934.8 | K12: 462621.34 | L12: 1982597.6 | M12: 2445219 | N12: 0.9 | O12: 97.347 | P12: 98.247 | Q12: 5949652.5 | R12: 4047415 | S12: 9997067.5
A13: 2025-09 | B13: 61251.15 | C13: 166019.3 | D13: 227270.45 | E13: 15221.531 | F13: 131263.17 | G13: 146484.71 | H13: 5452570 | I13: 1790930.5 | J13: 7243500.5 | K13: 472306.65 | L13: 1978905.5 | M13: 2451212.2 | N13: 0.9 | O13: 107.393 | P13: 108.293 | Q13: 6001350.2 | R13: 4067225.9 | S13: 10068576
A14: 2025-08 | B14: 64970.17 | C14: 148628.36 | D14: 213598.53 | E14: 15025.371 | F14: 121429.41 | G14: 136454.78 | H14: 5433198.2 | I14: 1786769.1 | J14: 7219967.3 | K14: 489457.9 | L14: 1943926.6 | M14: 2433384.5 | N14: 1.2 | O14: 110.101 | P14: 111.301 | Q14: 6002652.8 | R14: 4000863.6 | S14: 10003516
... A94: 2018-12 | B94: 74875.096 | C94: 202995.69 | D94: 277870.79 | E94: 12467.458 | F94: 165653.27 | G94: 178120.73 | H94: 4900393.8 | I94: 1419127.5 | J94: 6319521.4 | K94: 848348.08 | L94: 2098451.3 | M94: 2946799.4 | N94: 153.5 | O94: 156.819 | P94: 310.319 | Q94: 5836238 | R94: 3886384.6 | S94: 9722622.6

Sheet 3.5.1
A1: end_of_month | B1: mfg | C1: mfg_chg | D1: mfg_textiles | E1: mfg_textiles_chg | F1: mfg_footwear | G1: mfg_footwear_chg | H1: mfg_metalengr | I1: mfg_metalengr_chg | J1: mfg_rubbplastchem | K1: mfg_rubbplastchem_chg | L1: mfg_shipbuildrepair | M1: mfg_shipbuildrepair_chg | N1: mfg_ee | O1: mfg_ee_chg | P1: mfg_ee_teleequip | Q1: mfg_ee_teleequip_chg | R1: mfg_ee_other | S1: mfg_ee_other_chg | T1: mfg_food | U1: mfg_food_chg | V1: mfg_bevtob | W1: mfg_bevtob_chg | X1: mfg_printpub | Y1: mfg_printpub_chg | Z1: mfg_misc | AA1: mfg_misc_chg | AB1: af | AC1: af_chg | AD1: af_fisheries | AE1: af_fisheries_chg | AF1: af_livestock | AG1: af_livestock_chg | AH1: af_veghort | AI1: af_veghort_chg | AJ1: tran | AK1: tran_chg | AL1: tran_shipping | AM1: tran_shipping_chg | AN1: tran_airtran | AO1: tran_airtran_chg | AP1: tran_taxisplb | AQ1: tran_taxisplb_chg | AR1: tran_taxisplb_taxis | AS1: tran_taxisplb_taxis_chg | AT1: tran_taxisplb_plb | AU1: tran_taxisplb_plb_chg | AV1: tran_other | AW1: tran_other_chg | AX1: egt | AY1: egt_chg | AZ1: eg | BA1: eg_chg | BB1: rec | BC1: rec_chg | BD1: it | BE1: it_chg | BF1: it_telecom | BG1: it_telecom_chg | BH1: it_other | BI1: it_other_chg | BJ1: bcpi | BK1: bcpi_chg | BL1: bcpi_propdev | BM1: bcpi_propdev_chg | BN1: bcpi_propdev_ind | BO1: bcpi_propdev_ind_chg | BP1: bcpi_propdev_res | BQ1: bcpi_propdev_res_chg | BR1: bcpi_propdev_comm | BS1: bcpi_propdev_comm_chg | BT1: bcpi_propdev_other | BU1: bcpi_propdev_other_chg | BV1: bcpi_other | BW1: bcpi_other_chg | BX1: wsale | BY1: wsale_chg | BZ1: mine | CA1: mine_chg | CB1: misc | CC1: misc_chg | CD1: misc_hotelcater | CE1: misc_hotelcater_chg | CF1: misc_fin | CG1: misc_fin_chg | CH1: misc_fin_inv | CI1: misc_fin_inv_chg | CJ1: misc_fin_ins | CK1: misc_fin_ins_chg | CL1: misc_fin_futbrok | CM1: misc_fin_futbrok_chg | CN1: misc_fin_finother | CO1: misc_fin_finother_chg | CP1: misc_stockbrok | CQ1: misc_stockbrok_chg | CR1: misc_prof | CS1: misc_prof_chg | CT1: misc_prof_purschflat | CU1: misc_prof_purschflat_chg | CV1: misc_prof_purother | CW1: misc_prof_purother_chg | CX1: misc_prof_ccadv | CY1: misc_prof_ccadv_chg | CZ1: misc_prof_otherbusi | DA1: misc_prof_otherbusi_chg | DB1: misc_prof_otherpvt | DC1: misc_prof_otherpvt_chg | DD1: misc_allother | DE1: misc_allother_chg | DF1: loan_inhk | DG1: loan_inhk_chg
A2: 贷款是按用途分类，但不包括贸易融资贷款。 | B2: Manugacturing | D2: Textiles | F2: Footwear and wearing apparel | H2: Metal products and engineering | J2: Rubber, plastic and chemicals | L2: Shipbuilding and repair 3 | N2: Electrical and electronic4 | P2: Telecommunication equipment | Q2: 電子通訊設備 | R2: Others | S2: 其他 | T2: food | U2: 食品 | V2: Beverages and tobacco | W2: 飲料及煙草 | X2: Printing and publishing | Y2: 印刷及出版 | Z2: Miscellaneous | AA2: 雜類 | AB2: Agriculture and fisheries5,6 | AC2: 農業及漁業5,6 | AD2: Fisheries | AE2: 漁業 | AF2: Livestock and livestock products | AG2: 禽畜及禽畜產品 | AH2: Vegetables and horticulture | AI2: 蔬菜及園藝 | AJ2: Transport and transport equipment | AK2: 運輸及運輸設備 | AL2: Shipping | AM2: 航運 | AN2: Air transport | AO2: 空運 | AP2: Taxis and public light buses | AQ2: 的士及公共輕型巴士 | AR2: Taxis | AS2: 的士 | AT2: Public light buses | AU2: 公共輕型巴士 | AV2: Others | AW2: 其他 | AX2: Electricity, gas and telecommunications7 | AY2: 電力、氣體燃料及電訊7 | AZ2: Electricity and gas | BA2: 電力及氣體燃料 | BB2: Recreational activities | BC2: 康樂活動 | BD2: Information technology | BE2: 資訊科技 | BF2: Telecommunications | BG2: 電子通訊 | BH2: Others | BI2: 其他 | BJ2: Building and construction, property development investment | BK2: 建築業、物業發展與投資 | BL2: Property development and investment | BM2: 物業發展及投資 | BN2: Industrial | BO2: 工業 | BP2: Residential | BQ2: 住宅 | BR2: Commercial | BS2: 商業 | BT2: Other properties | BU2: 其他物業 | BV2: Others | BW2: 其他 | BX2: Wholesale and retail trade | BY2: 批發及零售業 | BZ2: Mining and quarrying6 | CA2: 採礦及採石業6 | CB2: Miscellaneous | CC2: 其他經濟行業 | CD2: Hotels, boarding houses and catering | CE2: 酒店、旅舍及飲食業 | CF2: Financial concerns | CG2: 與財務及金融有關公司 | CH2: Investment companies | CI2: 投資公司 | CJ2: Insurance companies | CK2: 保險公司 | CL2: Futures brokers | CM2: 期貨買賣商 | CN2: Finance companies and others | CO2: 金融公司及其他 | CP2: Stockbrokers | CQ2: 證券經紀 | CR2: Professional and private individuals | CS2: 專業人士及個人 | CT2: for the purchase of flats | CU2: 購買居屋 | CV2: for the purchase of other properties | CW2: 購買其他住宅樓宇 | CX2: For credit card advances | CY2: 信用卡墊款 | CZ2: For other business purposes | DA2: 其他商業用途 | DB2: For other private purposes | DC2: 其他私人用途 | DD2: All others | DE2: 其他 | DF2: Loans and advances for use in Hong Kong | DG2: 在香港使用的貸款及墊款
B3: 製造業 | C3: 与上季度比对的增减百分比 | D3: 紡織 | F3: 鞋類及衣飾 | H3: 金屬製品及工程 | J3: 橡膠、塑膠及化工 | L3: 造船及修理3 | N3: 電器及電子4
A4: 2026-06 | B4: 363633.97 | C4: 10.8 | D4: 10607.882 | F4: 31347.566 | H4: 45948.115 | J4: 73129.923 | N4: 60925.997 | P4: 9998.647 | R4: 50927.35 | T4: 25250.155 | V4: 17583.24 | X4: 4559.639 | Z4: 94281.454 | AJ4: 331240.65 | AK4: 9.4 | AL4: 105026.27 | AN4: 45450.289 | AP4: 51265.854 | AR4: 43354.876 | AT4: 7910.978 | AV4: 129498.24 | AZ4: 215920.42 | BB4: 11933.617 | BD4: 228617.92 | BF4: 85341.292 | BH4: 143276.63 | BJ4: 1385663 | BK4: -1.4 | BL4: 1313893.8 | BN4: 68879.153 | BP4: 523266.12 | BR4: 517893.4 | BT4: 203855.17 | BV4: 71769.189 | BX4: 312060.83 | BY4: 9.7 | CB4: 4809931.3 | CD4: 138518.37 | CF4: 1032728.3 | CG4: 4.9 | CH4: 674173.49 | CJ4: 40038.929 | CL4: 2236.778 | CN4: 316279.09 | CP4: 99687.109 | CQ4: 15.1 | CR4: 3076518.8 | CT4: 167615.41 | CU4: 7.1 | CV4: 1958342.7 | CW4: 1.1 | CX4: 148800.06 | CZ4: 7582.985 | DB4: 794177.67 | DD4: 462478.74 | DF4: 7659001.8 | DG4: 2.9
A5: 2026-03 | B5: 328188.24 | C5: 7 | D5: 10407.843 | F5: 27516.138 | H5: 44021.965 | J5: 63578.479 | N5: 61296.591 | P5: 6636.04 | R5: 54660.551 | T5: 21536.222 | V5: 13861.623 | X5: 4752.796 | Z5: 81216.584 | AJ5: 302874.14 | AK5: 6.1 | AL5: 110085.69 | AN5: 42722.098 | AP5: 51264.121 | AR5: 43907.262 | AT5: 7356.859 | AV5: 98802.229 | AZ5: 205053.45 | BB5: 11139.161 | BD5: 215874.99 | BF5: 88620.095 | BH5: 127254.89 | BJ5: 1405132.7 | BK5: -2.3 | BL5: 1339249.2 | BN5: 70240.539 | BP5: 532245.95 | BR5: 528207.44 | BT5: 208555.27 | BV5: 65883.52 | BX5: 284551.08 | BY5: 2 | CB5: 4687506.9 | CD5: 139804.43 | CF5: 984139.37 | CG5: 4.7 | CH5: 632191.77 | CJ5: 39901.347 | CL5: 1445.849 | CN5: 310600.4 | CP5: 86607.603 | CQ5: 36.5 | CR5: 3001339.7 | CT5: 156519.89 | CU5: 2.1 | CV5: 1937565.9 | CW5: 0.9 | CX5: 151892.1 | CZ5: 6885.071 | DB5: 748476.8 | DD5: 475615.77 | DF5: 7440320.7 | DG5: 2.7
A6: 2025-12 | B6: 306596.64 | C6: -5 | D6: 10579.608 | F6: 26813.224 | H6: 39803.767 | J6: 62683.653 | N6: 54150.184 | P6: 6090.297 | R6: 48059.887 | T6: 21795.043 | V6: 10977.891 | X6: 4592.36 | Z6: 75200.913 | AJ6: 285580.51 | AK6: 1.3 | AL6: 100947.03 | AN6: 34495.647 | AP6: 52015.664 | AR6: 44497.902 | AT6: 7517.762 | AV6: 98122.162 | AZ6: 194690 | BB6: 12926.27 | BD6: 203059.65 | BF6: 78288.138 | BH6: 124771.51 | BJ6: 1437648.8 | BK6: -1.5 | BL6: 1372331.1 | BN6: 71745.791 | BP6: 548460.04 | BR6: 539089.66 | BT6: 213035.63 | BV6: 65317.624 | BX6: 278886.35 | BY6: -1.3 | CB6: 4525136.7 | CD6: 131413.74 | CF6: 940367.2 | CG6: 0.2 | CH6: 602510.59 | CJ6: 37284.217 | CL6: 2160.781 | CN6: 298411.61 | CP6: 63461.214 | CQ6: -0.1 | CR6: 2922795.2 | CT6: 153280.41 | CU6: 0.7 | CV6: 1920476.5 | CW6: 1.4 | CX6: 157738.37 | CZ6: 5630.61 | DB6: 685669.35 | DD6: 467099.3 | DF6: 7244524.9 | DG6: 0
A7: 2025-09 | B7: 322774.75 | C7: -0.6 | D7: 10888.719 | F7: 27397.964 | H7: 43053.556 | J7: 72133.026 | N7: 49492.873 | P7: 5069.957 | R7: 44422.916 | T7: 26661.418 | V7: 14172.343 | X7: 4926.074 | Z7: 74048.774 | AJ7: 282034.28 | AK7: -0.7 | AL7: 101675.29 | AN7: 30209.397 | AP7: 52786.394 | AR7: 45031.026 | AT7: 7755.368 | AV7: 97363.198 | AZ7: 213416.25 | BB7: 12032.436 | BD7: 197962.55 | BF7: 83789.733 | BH7: 114172.81 | BJ7: 1458964 | BK7: -3.2 | BL7: 1388211 | BN7: 71564.501 | BP7: 568713.39 | BR7: 536222.5 | BT7: 211710.6 | BV7: 70752.97 | BX7: 282430.92 | BY7: -3.8 | CB7: 4473885.3 | CD7: 134852.39 | CF7: 938125.02 | CG7: 3 | CH7: 594053.39 | CJ7: 38001.532 | CL7: 2308.27 | CN7: 303761.83 | CP7: 63510.261 | CQ7: 0.4 | CR7: 2879906.1 | CT7: 152236.39 | CU7: 7.3 | CV7: 1894347 | CW7: 0.3 | CX7: 145656.06 | CZ7: 5576.78 | DB7: 682089.89 | DD7: 457491.53 | DF7: 7243500.5 | DG7: -0.4
A8: 2025-06 | B8: 324870.77 | C8: 4.8 | D8: 10105.352 | F8: 27564.337 | H8: 43381.244 | J8: 64991.74 | N8: 51873.188 | P8: 5434.78 | R8: 46438.408 | T8: 26633.559 | V8: 12774.037 | X8: 4869.311 | Z8: 82678.003 | AJ8: 283977.7 | AK8: -4.6 | AL8: 91728.232 | AN8: 37844.359 | AP8: 53651.024 | AR8: 45553.542 | AT8: 8097.482 | AV8: 100754.08 | AZ8: 215013.89 | BB8: 12206.375 | BD8: 202849.75 | BF8: 79662.793 | BH8: 123186.96 | BJ8: 1507238.4 | BK8: -0.2 | BL8: 1445796.3 | BN8: 71888.765 | BP8: 602360.45 | BR8: 550029.99 | BT8: 221517.12 | BV8: 61442.079 | BX8: 293650.49 | BY8: 2.5 | CB8: 4434070.2 | CD8: 137518.28 | CF8: 910454.89 | CG8: 3.8 | CH8: 563542.47 | CJ8: 41933.241 | CL8: 104.891 | CN8: 304874.28 | CP8: 63239.895 | CQ8: 16.3 | CR8: 2845525.4 | CT8: 141918.08 | CU8: 2.8 | CV8: 1889329.5 | CW8: 0.5 | CX8: 143687.94 | CZ8: 5638.183 | DB8: 664951.66 | DD8: 477331.76 | DF8: 7273877.6 | DG8: 1.5
A9: 2025-03 | B9: 310084.31 | C9: 5.1 | D9: 11400.696 | F9: 23510.864 | H9: 38669.503 | J9: 58615.268 | N9: 52345.671 | P9: 5375.815 | R9: 46969.856 | T9: 27284.712 | V9: 12755.422 | X9: 4843.162 | Z9: 80659.016 | AJ9: 297595.2 | AK9: 1.3 | AL9: 86832.722 | AN9: 49180.488 | AP9: 54231.535 | AR9: 45988.494 | AT9: 8243.041 | AV9: 107350.45 | AZ9: 184154.22 | BB9: 10682.11 | BD9: 201060.38 | BF9: 68338.829 | BH9: 132721.55 | BJ9: 1509798.8 | BK9: -2.7 | BL9: 1446113.9 | BN9: 71552.436 | BP9: 620775.78 | BR9: 547986.93 | BT9: 205798.77 | BV9: 63684.837 | BX9: 286619.04 | BY9: -2.1 | CB9: 4364146.5 | CD9: 142179.54 | CF9: 877063.12 | CG9: 4.4 | CH9: 546405.52 | CJ9: 40406.9 | CL9: 1416.625 | CN9: 288834.08 | CP9: 54380.557 | CQ9: 10.6 | CR9: 2815936.1 | CT9: 138077.25 | CU9: 4 | CV9: 1880587.6 | CW9: 0.4 | CX9: 146279.68 | CZ9: 5624.51 | DB9: 645367.03 | DD9: 474587.2 | DF9: 7164140.5 | DG9: 0.8
A10: 2024-12 | B10: 295132.54 | C10: -0.9 | D10: 12543.956 | F10: 21597.563 | H10: 37385.872 | J10: 57264.194 | N10: 52623.241 | P10: 6571.414 | R10: 46051.827 | T10: 23465.175 | V10: 13452.56 | X10: 4312.302 | Z10: 72487.679 | AJ10: 293659.3 | AK10: 4.8 | AL10: 83948.318 | AN10: 55624.595 | AP10: 55063.993 | AR10: 46295.807 | AT10: 8768.186 | AV10: 99022.398 | AZ10: 190847.02 | BB10: 8431.267 | BD10: 183124.3 | BF10: 65267.46 | BH10: 117856.84 | BJ10: 1552482.1 | BK10: -1.1 | BL10: 1488357.5 | BN10: 73944.409 | BP10: 633676.85 | BR10: 560687.67 | BT10: 220048.58 | BV10: 64124.581 | BX10: 292621.66 | BY10: -1.5 | CB10: 4292441.2 | CD10: 132742.94 | CF10: 840262.48 | CG10: 1.8 | CH10: 510769.51 | CJ10: 36242.792 | CL10: 282.178 | CN10: 292968.01 | CP10: 49168.879 | CQ10: -23.1 | CR10: 2795671.8 | CT10: 132720.03 | CU10: 0.8 | CV10: 1873532.5 | CW10: -0.1 | CX10: 154585.22 | CZ10: 5403.246 | DB10: 629430.8 | DD10: 474595.09 | DF10: 7108739.3 | DG10: -0.2

Sheet 3.13.1
A1: end_of_month | B1: loans_excl_trade_finance | C1: trade_finance | D1: lending_total
A2: 2026-06 | B2: 3993307 | C2: 269807.86 | D2: 4263114.9
A3: 2026-03 | B3: 3855312.1 | C3: 278043.84 | D3: 4133355.9
A4: 2025-12 | B4: 3733130.7 | C4: 229720.64 | D4: 3962851.3
A5: 2025-09 | B5: 3751475 | C5: 214069.51 | D5: 3965544.6
A6: 2025-06 | B6: 3801731.7 | C6: 222210.83 | D6: 4023942.5

Sheet Economics Sectors(integrate)
B1: Domestic loans by economic sectors1, 2
B2: Manufacturing | C2: Property development and investment | D2: To purchase other residential properties | E2: Property lending* | F2: Wholesale and retail trade | G2: Trade financing | H2: =B2 -> Manufacturing | I2: =E2 -> Property lending* | J2: =F2 -> Wholesale and retail trade | K2: =G2 -> Trade financing
B3: (HK$mn) | C3: (HK$mn) | D3: (HK$mn) | E3: (HK$mn) | F3: (HK$mn) | G3: (HK$mn) | H3: yoy% | I3: yoy% | J3: yoy% | K3: yoy%
A4: 2003 Q1 | B4: 71673.39 | C4: 358382.05 | D4: 536875.84 | E4: =C4+D4 -> 895257.9 | F4: 102657.13 | G4: 92853.878 | H4: -0.9 | I4: -1.9692577 | J4: -1.3 | K4: 7.5615072
A5: Q2 | B5: 75192.999 | C5: 353365.91 | D5: 531083.53 | E5: =C5+D5 -> 884449.44 | F5: 102114.93 | G5: 98610.076 | H5: 2.6 | I5: -3.1 | J5: -1.7 | K5: 6.5
A6: Q3 | B6: 77636.151 | C6: 345793.74 | D6: 528107.29 | E6: =C6+D6 -> 873901.03 | F6: 96589.625 | G6: 97171.159 | H6: 11.3 | I6: -3.2 | J6: -6.2 | K6: 3
A7: Q4 | B7: 80148.65 | C7: 341018.68 | D7: 529388.84 | E7: =C7+D7 -> 870407.52 | F7: 93625.526 | G7: 100117.86 | H7: 13.5 | I7: -3.5 | J7: -6.7 | K7: 10.2
A8: 2004 Q1 | B8: 84511.672 | C8: 338368.82 | D8: 532623.39 | E8: =C8+D8 -> 870992.2 | F8: 97967.415 | G8: 106521.75 | H8: 17.6 | I8: -2.7 | J8: -6.5 | K8: =(G8/G4-1)*100 -> 14.719769
A9: Q2 | B9: 91953.276 | C9: 344041.84 | D9: 531115.28 | E9: =C9+D9 -> 875157.12 | F9: 98449.582 | G9: 122205.92 | H9: 21.8 | I9: -1 | J9: -5.8 | K9: =(G9/G5-1)*100 -> 23.928431
A10: Q3 | B10: 93741.476 | C10: 343092.55 | D10: 530316.22 | E10: =C10+D10 -> 873408.77 | F10: 98805.567 | G10: 128867.95 | H10: 23.9 | I10: 0 | J10: 5.3 | K10: =(G10/G6-1)*100 -> 32.619544
A11: Q4 | B11: 99322.904 | C11: 368828.09 | D11: 534188.33 | E11: =C11+D11 -> 903016.42 | F11: 99190.233 | G11: 130109.47 | H11: 27.8 | I11: 3.8 | J11: 9.2 | K11: =(G11/G7-1)*100 -> 29.956301
A12: 2005 Q1 | B12: 109346.71 | C12: 385429.22 | D12: 539952.95 | E12: =C12+D12 -> 925382.17 | F12: 97522.661 | G12: 133212.9 | H12: 31.1 | I12: 6.3 | J12: 5.9 | K12: =(G12/G8-1)*100 -> 25.056992
A13: Q2 | B13: 117468.2 | C13: 396918.83 | D13: 549089.03 | E13: =C13+D13 -> 946007.85 | F13: 103791.97 | G13: 150024.39 | H13: 32.8 | I13: 8.1 | J13: 11.9 | K13: =(G13/G9-1)*100 -> 22.763604
A14: Q3 | B14: 114553.05 | C14: 404826.91 | D14: 544758.04 | E14: =C14+D14 -> 949584.95 | F14: 101925.71 | G14: 147225.77 | H14: 23.5 | I14: 8.9 | J14: 3 | K14: =(G14/G10-1)*100 -> 14.245453
A15: Q4 | B15: 119232.42 | C15: 437604.65 | D15: 539192.16 | E15: =C15+D15 -> 976796.8 | F15: 100643.84 | G15: 141642.16 | H15: 20.4 | I15: 8.5 | J15: 1.2 | K15: =(G15/G11-1)*100 -> 8.8638342
A16: 2006 Q1 | B16: 116917.82 | C16: 440887.64 | D16: 534529.55 | F16: 101565.56 | G16: 138252.51 | H16: 9.3 | I16: 5.6 | J16: 2.8 | K16: =(G16/G12-1)*100 -> 3.7831253
A17: Q2 | B17: 120238.31 | C17: 466748.11 | D17: 532926.99 | E17: =C17+D17 -> 999675.1 | F17: 104508.05 | G17: 152182.14 | H17: 2.9 | I17: 5.9 | J17: -1 | K17: =(G17/G13-1)*100 -> 1.4382675
A18: Q3 | B18: 107190.29 | C18: 463482.61 | D18: 531732.45 | E18: =C18+D18 -> 995215.06 | F18: 103797.9 | G18: 159574.49 | H18: -0.3 | I18: 5 | J18: 1.7 | K18: =(G18/G14-1)*100 -> 8.3876063
A19: Q4 | B19: 103030.5 | C19: 481611.57 | D19: 535021.67 | E19: =C19+D19 -> 1016633.2 | F19: 105456.17 | G19: 152058.64 | H19: -6.5 | I19: 4.3 | J19: 5.2 | K19: =(G19/G15-1)*100 -> 7.3540844
A20: 2007 Q1 | B20: 106098.8 | C20: 486675.94 | D20: 536270.85 | E20: =C20+D20 -> 1022946.8 | F20: 107629.16 | G20: 150480.41 | H20: -1.3 | I20: 5.2 | J20: 6.2 | K20: =(G20/G16-1)*100 -> 8.8446147
A21: Q2 | B21: 113766.06 | C21: 516047.06 | D21: 542026.96 | E21: =C21+D21 -> 1058074 | F21: 112176.82 | G21: 168882.05 | H21: 2.3 | I21: 6.1 | J21: 8.4 | K21: =(G21/G17-1)*100 -> 10.973628
A22: Q3 | B22: 119344.26 | C22: 545597.15 | D22: 552004.12 | E22: =C22+D22 -> 1097601.3 | F22: 113114.66 | G22: 175991.21 | H22: 13.3 | I22: 10.6 | J22: 10.1 | K22: =(G22/G18-1)*100 -> 10.287811
A23: Q4 | B23: 121369.25 | C23: 569918.34 | D23: 564127.12 | E23: =C23+D23 -> 1134045.5 | F23: 116244.79 | G23: 183134.79 | H23: 18.5 | I23: 11.7 | J23: 10.9 | K23: =(G23/G19-1)*100 -> 20.436947
A24: 2008 Q1 | B24: 140875.82 | C24: 606378.09 | D24: 581002.02 | E24: =C24+D24 -> 1187380.1 | F24: 135600.02 | G24: 198516.49 | H24: 32.9 | I24: 16.2 | J24: 26.9 | K24: =(G24/G20-1)*100 -> 31.921811
A25: Q2 | B25: 147749.15 | C25: 633024.18 | D25: 595890.68 | E25: =C25+D25 -> 1228914.9 | F25: 156894.59 | G25: 228655.04 | H25: 29.7 | I25: 16.3 | J25: 40.9 | K25: =(G25/G21-1)*100 -> 35.393336
A26: Q3 | B26: 154401.28 | C26: 662250.22 | D26: 602213.64 | E26: =C26+D26 -> 1264463.9 | F26: 157031.87 | G26: 222107.99 | H26: 29.4 | I26: 15.2 | J26: 38.5 | K26: =(G26/G22-1)*100 -> 26.204026
A27: Q4 | B27: 146617.54 | C27: 676214.61 | D27: 592980.44 | E27: =C27+D27 -> 1269195 | F27: 152148.26 | G27: 186214.49 | H27: 20.4 | I27: 11.8 | J27: 30.4 | K27: =(G27/G23-1)*100 -> 1.6816559
A28: 2009 Q1 | B28: 144456.15 | C28: 668940.74 | D28: 591986.87 | E28: =C28+D28 -> 1260927.6 | F28: 143817.39 | G28: 158035.08 | H28: 2.2 | I28: 6.1 | J28: 5.7 | K28: =(G28/G24-1)*100 -> -20.39196
... A31: Q4 | B31: 126588.99 | C31: 676521.75 | D31: 646506.08 | E31: =C31+D31 -> 1323027.8 | F31: 150430.94 | G31: 174805.2 | H31: -13.7 | I31: 4.2 | J31: -1.1 | K31: =(G31/G27-1)*100 -> -6.1269599
A32: 2010 Q1 | B32: 129149.56 | C32: 717910.42 | D32: 663820.02 | E32: =C32+D32 -> 1381730.4 | F32: 164408.46 | G32: 196059.73 | H32: -10.6 | I32: 9.6 | J32: 14.3 | K32: 24.1
A33: Q2 | B33: 141646.9 | C33: 758779.49 | D33: 683678.19 | E33: =C33+D33 -> 1442457.7 | F33: 189434.07 | G33: 234896.29 | H33: 4.1 | I33: 13.3 | J33: 29.3 | K33: 43.9
A34: Q3 | B34: 153272.93 | C34: 805633.49 | D34: 723441.51 | E34: =C34+D34 -> 1529075 | F34: 215542.62 | G34: 256378.54 | H34: 10.6 | I34: 19.1 | J34: 41.8 | K34: 53.5
A35: Q4 | B35: 162329.06 | C35: 815477.04 | D35: 745168.95 | E35: =C35+D35 -> 1560646 | F35: 229419.5 | G35: 273932.5 | H35: 28.2 | I35: 18 | J35: 52.5 | K35: 56.7
A36: 2011 Q1 | B36: 174412.97 | C36: 848777.18 | D36: 765735.25 | E36: =C36+D36 -> 1614512.4 | F36: 268498.33 | G36: 309496.47 | H36: 35 | I36: 16.8 | J36: 63.3 | K36: 57.9
A37: Q2 | B37: 184628.35 | C37: 867714.93 | D37: 792109.01 | E37: =C37+D37 -> 1659823.9 | F37: 312968.75 | G37: 345652.18 | H37: 30.3 | I37: 15.1 | J37: 65.2 | K37: 47.2
A38: Q3 | B38: 192235.71 | C38: 892778.44 | D38: 802997.87 | E38: =C38+D38 -> 1695776.3 | F38: 323352.06 | G38: 358394.65 | H38: 25.4 | I38: 10.9 | J38: 50 | K38: 39.8
A39: Q4 | B39: 189425.43 | C39: 900567.64 | D39: 804625.01 | E39: =C39+D39 -> 1705192.7 | F39: 313869.68 | G39: 350588.98 | H39: 16.7 | I39: 9.3 | J39: 36.8 | K39: 28
A40: 2012 Q1 | B40: 189293.33 | C40: 887458.41 | D40: 806785.51 | E40: =C40+D40 -> 1694243.9 | F40: 323062.22 | G40: 376021.53 | H40: 8.5 | I40: 4.9 | J40: 20.3 | K40: 21.5
A41: Q2 | B41: 183977.6 | C41: 875868.67 | D41: 827564.59 | E41: =C41+D41 -> 1703433.3 | F41: 332725.46 | G41: 394933.36 | H41: -0.4 | I41: 2.6 | J41: 6.3 | K41: 14.3
A42: Q3 | B42: 184309.42 | C42: 891853.44 | D42: 846214.57 | E42: =C42+D42 -> 1738068 | F42: 343732.32 | G42: 416907.33 | H42: -4.1 | I42: 2.5 | J42: 6.3 | K42: 16.3
A43: Q4 | B43: 183817.2 | C43: 906656.85 | D43: 872648.35 | E43: =C43+D43 -> 1779305.2 | F43: 350834.92 | G43: 382576.21 | H43: -3 | I43: 4.3 | J43: 11.8 | K43: 9.1
... A70: Q3 | B70: 304202.3 | C70: 1543614.1 | D70: 1442407.5 | E70: =C70+D70 -> 2986021.6 | F70: 386215.2 | G70: 493528.84 | H70: -1.5800233 | I70: 6.3735476 | J70: -1.4335984 | K70: -1.9162037
A71: Q4 | B71: 301405.15 | C71: 1582047.9 | D71: 1466259.6 | E71: =C71+D71 -> 3048307.4 | F71: 376397.69 | G71: 452983.37 | H71: =B71/B67*100-100 -> 0.5874007 | I71: =E71/E67*100-100 -> 7.7510313 | J71: =F71/F67*100-100 -> -3.5481907 | K71: =G71/G67*100-100 -> -0.65969167
A72: 2020 Q1 | B72: 321072.67 | C72: 1621687.2 | D72: 1489884.9 | E72: =C72+D72 -> 3111572.1 | F72: 372935.19 | G72: 480609.92 | H72: =B72/B68*100-100 -> 8.7500773 | I72: =E72/E68*100-100 -> 8.5001159 | J72: =F72/F68*100-100 -> 0.53617197 | K72: =G72/G68*100-100 -> -1.3455907
A73: Q2 | B73: 308311.47 | C73: 1575027.3 | D73: 1516794.7 | E73: =C73+D73 -> 3091822 | F73: 372042.46 | G73: 474488.05 | H73: =B73/B69*100-100 -> 1.0481827 | I73: =E73/E69*100-100 -> 5.4587786 | J73: =F73/F69*100-100 -> -3.0462023 | K73: =G73/G69*100-100 -> -5.6481595
A74: Q3 | B74: 305155.53 | C74: 1557313.6 | D74: 1554007.8 | E74: =C74+D74 -> 3111321.4 | F74: 358775.28 | G74: 457219.27 | H74: =B74/B70*100-100 -> 0.31335562 | I74: =E74/E70*100-100 -> 4.1962127 | J74: =F74/F70*100-100 -> -7.1048275 | K74: =G74/G70*100-100 -> -7.3571329
A75: Q4 | B75: 306455.01 | C75: 1580235.6 | D75: 1580348.7 | E75: =C75+D75 -> 3160584.3 | F75: 348927.98 | G75: 424801.37 | H75: =B75/B71*100-100 -> 1.6754399 | I75: =E75/E71*100-100 -> 3.6832522 | J75: =F75/F71*100-100 -> -7.2980562 | K75: =G75/G71*100-100 -> -6.2214213
A76: 2021 Q1 | B76: 319427.86 | C76: 1634115.6 | D76: 1603519.6 | E76: =C76+D76 -> 3237635.2 | F76: 349244.57 | G76: 461069.26 | H76: =B76/B72*100-100 -> -0.51228559 | I76: =E76/E72*100-100 -> 4.0514279 | J76: =F76/F72*100-100 -> -6.352478 | K76: =G76/G72*100-100 -> -4.0658037
A77: Q2 | B77: 314037.68 | C77: 1643299.9 | D77: 1647100.7 | E77: =C77+D77 -> 3290400.6 | F77: 342527.75 | G77: 543143.77 | H77: =B77/B73*100-100 -> 1.8572815 | I77: =E77/E73*100-100 -> 6.422703 | J77: =F77/F73*100-100 -> -7.9331562 | K77: =G77/G73*100-100 -> 14.46943
A78: Q3 | B78: 322639.88 | C78: 1622435.6 | D78: 1695436.3 | E78: =C78+D78 -> 3317872 | F78: 333854.65 | G78: 573024.8 | H78: =B78/B74*100-100 -> 5.7296493 | I78: =E78/E74*100-100 -> 6.6386757 | J78: =F78/F74*100-100 -> -6.9460274 | K78: =G78/G74*100-100 -> 25.328226
A79: Q4 | B79: 312857.79 | C79: 1671043.5 | D79: 1735068.9 | E79: =C79+D79 -> 3406112.4 | F79: 325285.98 | G79: 485030.24 | H79: =B79/B75*100-100 -> 2.0893077 | I79: =E79/E75*100-100 -> 7.76844 | J79: =F79/F75*100-100 -> -6.7756103 | K79: =G79/G75*100-100 -> 14.178127
A80: 2022 Q1 | B80: 331184.66 | C80: 1703335.1 | D80: 1758881.6 | E80: =C80+D80 -> 3462216.7 | F80: 351699.85 | G80: 531484.85 | H80: =B80/B76*100-100 -> 3.6805797 | I80: =E80/E76*100-100 -> 6.936591 | J80: =F80/F76*100-100 -> 0.70302626 | K80: =G80/G76*100-100 -> 15.272235
A81: Q2 | B81: 328112.35 | C81: 1683254.6 | D81: 1773027.8 | E81: =C81+D81 -> 3456282.3 | F81: 356536.94 | G81: 524338.47 | H81: =B81/B77*100-100 -> 4.4818424 | I81: =E81/E77*100-100 -> 5.041385 | J81: =F81/F77*100-100 -> 4.0899449 | K81: =G81/G77*100-100 -> -3.4623067
A82: Q3 | B82: 343200.56 | C82: 1659805 | D82: 1795080.9 | E82: =C82+D82 -> 3454885.9 | F82: 342974.39 | G82: 487758.41 | H82: =B82/B78*100-100 -> 6.3726416 | I82: =E82/E78*100-100 -> 4.1295726 | J82: =F82/F78*100-100 -> 2.7316492 | K82: =G82/G78*100-100 -> -14.880052
... A97: Q2 | B97: 363633.97 | C97: 1313893.8 | D97: 1958342.7 | E97: =C97+D97 -> 3272236.5 | F97: 312054.14 | G97: 436089.19 | H97: =B97/B93*100-100 -> 11.931883 | I97: =E97/E93*100-100 -> -1.8856645 | J97: =F97/F93*100-100 -> 6.2671933 | K97: =G97/G93*100-100 -> 15.91215
A98: Q3
A99: Q4
A102: 1. Some loans have been reclassified. As such, figures are not strictly comparable with those of previous quarters.
A104: 2. The December 2018 figures for loans for use in/outside Hong Kong have been restated to reflect authorized institutions'
A105: reclassification of working capital loans. As reclassified loan data before December 2018 are not available, quarter-on-quarter
A106: growth rates of domestic loans (including their sub-components) are calculated based on the data without such
A107: reclassification.
A109: * Includes property development & investment and purchase of private residential properties.
